Workbook

Sheet README
A1: PlotArmour: Verity & Studio Master Reference
A2: Single source of truth for sales, outreach, product and engineering. If this workbook and anything else disagree, fix this one first.
A4: Last refreshed | B4: 2026-10-06
A5: Rule | B5: Edit here first. Website copy, decks and quotes follow this workbook.
A6: Code snapshot | B6: D:/Code/verity main and D:/Code/verity-explore, scanned 2026-10-06
A7: Site base URL | B7: https://verity.plotarmour.in
A8: Owner
A10: Start here
A11: Sales / account managers | B11: Quick Quote, Packages, Package Matrix, Modules (filter Sellable today = Yes), Pricing Rules, Biz FAQ, Website Capabilities (language rules)
A12: Outreach managers and teams | B12: Business Types (targeting, pain points, discovery question), Biz Pain Points, Biz Roles, Biz Use Cases, Biz AI Questions, Industries
A13: Product managers | B13: Modules, Roadmap & Gaps, Pricing Review, Package Matrix, Dev Capabilities, Biz Modules (what the website promises)
A14: Developers | B14: Dev Capabilities, Dev Commands, Dev Queries, Dev Events, Dev Data Model, Dev Platform, Dev Screens
A15: Finance / leadership | B15: Pricing Rules, Packages, Customization Rates, Pricing Review, Studio Services, Studio Packages
A17: Status legend (Modules tab) | C17: Modules
A18: Live | B18: In product code and usable. | C18: =COUNTIF(Modules!$F$5:$F$116,A18)
A19: Live (client-built) | B19: Built for one client, reusable without a fork. | C19: =COUNTIF(Modules!$F$5:$F$116,A19)
A20: Partial | B20: Works with stated limits. | C20: =COUNTIF(Modules!$F$5:$F$116,A20)
A21: Built, not live-verified | B21: Code exists, no real-world call yet. Do not sell. | C21: =COUNTIF(Modules!$F$5:$F$116,A21)
A22: Designed | B22: Specification only. | C22: =COUNTIF(Modules!$F$5:$F$116,A22)
A23: Planned | B23: Named, no design or code. | C23: =COUNTIF(Modules!$F$5:$F$116,A23)
A24: Reference | B24: Research only. | C24: =COUNTIF(Modules!$F$5:$F$116,A24)
A26: Tab index
A27: Tab | B27: What it holds | C27: Rows | D27: Audience
A28: README | B28: This page | D28: Everyone
A29: Quick Quote | B29: Price a deal: package, add-ons, customization, GST | D29: Sales
A30: Packages | B30: The seven Verity packages and floors | C30: =COUNTA('Packages'!A:A)-3 | D30: Sales
A31: Package Matrix | B31: Which module is in which package | C31: =COUNTA('Package Matrix'!A:A)-3 | D31: Sales
A32: Modules | B32: Every module with status, price class and pitch | C32: =COUNTA('Modules'!A:A)-3 | D32: Everyone
A33: Pricing Rules | B33: Inputs behind every price formula plus policy | D33: Pricing / finance
A34: Customization Rates | B34: Per-item rate card | C34: =COUNTA('Customization Rates'!A:A)-3 | D34: Pricing / finance
A35: Pricing Review | B35: Open conflicts in the commercial model | C35: =COUNTA('Pricing Review'!A:A)-3 | D35: Product
A36: Roadmap & Gaps | B36: Unbuilt and partial items with blockers | C36: =COUNTA('Roadmap & Gaps'!A:A)-3 | D36: Product
A37: Industries | B37: Nine industry hubs | C37: =COUNTA('Industries'!A:A)-3 | D37: Outreach
A38: Business Types | B38: 123 business types for outreach targeting | C38: =COUNTA('Business Types'!A:A)-3 | D38: Outreach
A39: Biz Modules | B39: Business pages: modules for every business type | C39: =COUNTA('Biz Modules'!A:A)-3 | D39: Sales
A40: Biz Workflows | B40: Business pages: workflows for every business type | C40: =COUNTA('Biz Workflows'!A:A)-3 | D40: Sales
A41: Biz Automations | B41: Business pages: automations for every business type | C41: =COUNTA('Biz Automations'!A:A)-3 | D41: Sales
A42: Biz Reports | B42: Business pages: reports for every business type | C42: =COUNTA('Biz Reports'!A:A)-3 | D42: Sales
A43: Biz Roles | B43: Business pages: roles for every business type | C43: =COUNTA('Biz Roles'!A:A)-3 | D43: Sales
A44: Biz Use Cases | B44: Business pages: use cases for every business type | C44: =COUNTA('Biz Use Cases'!A:A)-3 | D44: Sales
A45: Biz Pain Points | B45: Business pages: pain points for every business type | C45: =COUNTA('Biz Pain Points'!A:A)-3 | D45: Sales
A46: Biz FAQ | B46: Business pages: faq for every business type | C46: =COUNTA('Biz FAQ'!A:A)-3 | D46: Sales
A47: Biz AI Questions | B47: Business pages: ai questions for every business type | C47: =COUNTA('Biz AI Questions'!A:A)-3 | D47: Sales
A48: Biz Terminology | B48: Business pages: terminology for every business type | C48: =COUNTA('Biz Terminology'!A:A)-3 | D48: Sales
A49: Website Capabilities | B49: What the site may claim and what to avoid saying | C49: =COUNTA('Website Capabilities'!A:A)-3 | D49: Sales
A50: Dev Capabilities | B50: 21 capabilities in code with counts | C50: =COUNTA('Dev Capabilities'!A:A)-3 | D50: Dev
A51: Dev Commands | B51: Write operations | C51: =COUNTA('Dev Commands'!A:A)-3 | D51: Dev
A52: Dev Queries | B52: Read operations | C52: =COUNTA('Dev Queries'!A:A)-3 | D52: Dev
A53: Dev Events | B53: Domain events | C53: =COUNTA('Dev Events'!A:A)-3 | D53: Dev
A54: Dev Data Model | B54: Prisma models | C54: =COUNTA('Dev Data Model'!A:A)-3 | D54: Dev
A55: Dev Platform | B55: Platform foundation files | C55: =COUNTA('Dev Platform'!A:A)-3 | D55: Dev
A56: Dev Screens | B56: Routes in the app | C56: =COUNTA('Dev Screens'!A:A)-3 | D56: Dev
A57: Studio Services | B57: Studio rate card | C57: =COUNTA('Studio Services'!A:A)-3 | D57: Pricing / finance
A58: Studio Packages | B58: Studio packages | C58: =COUNTA('Studio Packages'!A:A)-3 | D58: Pricing / finance
A59: Glossary | B59: Shared vocabulary | C59: =COUNTA('Glossary'!A:A)-3 | D59: Everyone
A60: Sources & Changelog | B60: Method and history | D60: Everyone

Sheet Quick Quote
A1: Quick Quote
A2: Blue cells are inputs. Proposed 2026 list rates, ex-GST. Read Pricing Review before sending any number to a client. Example rows are pre-filled: overwrite them.
A4: Package | B4: Verity Trade | D4: Package setup (floor) | E4: =INDEX(Packages!$E$5:$E$11,MATCH($B$4,Packages!$A$5:$A$11,0))
A5: Total locations | B5: 2 | D5: Extra locations setup | E5: =MAX($B$5-1,0)*'Pricing Rules'!$B$13
A6: Billing | B6: Annual | D6: Add-on modules setup | E6: =SUM(C21:C40)
A7: GST rate | B7: ='Pricing Rules'!B11 | D7: Customization one-time | E7: =SUM(F44:F58)
A8: Annual prepay discount | B8: ='Pricing Rules'!B12 | D8: TOTAL ONE-TIME (ex-GST) | E8: =SUM(E4:E7)
D9: Package monthly (floor) | E9: =INDEX(Packages!$H$5:$H$11,MATCH($B$4,Packages!$A$5:$A$11,0))
A10: Rules | D10: Extra locations monthly | E10: =MAX($B$5-1,0)*'Pricing Rules'!$B$14
A11: Package floors are minimums; final price depends on scope. | D11: Add-on modules monthly | E11: =SUM(D21:D40)
A12: Add-on = built module priced from Modules. Roadmap = not built, price is 0 and it must not be promised. | D12: Customization monthly | E12: =SUM(G44:G58)
A13: Included modules cost nothing extra. Package contents live on Package Matrix. | D13: TOTAL MONTHLY, list (ex-GST) | E13: =SUM(E9:E12)
A14: Customization rows read the Customization Rates tab by tier; monthly items go to the monthly total. | D14: Monthly after billing choice | E14: =IF($B$6="Annual",E13*(1-$B$8),E13)
A15: Hosting, third-party messaging, AI usage and data migration are quoted separately (Pricing Rules policy). | D15: FIRST-YEAR TOTAL (ex-GST) | E15: =E8+12*E14
D16: GST | E16: =E15*$B$7
D17: FIRST-YEAR TOTAL (incl. GST) | E17: =E15+E16
D18: Recommended minimum check | E18: =IF(AND(E8>='Pricing Rules'!$B$15,E13>='Pricing Rules'!$B$16),"Meets recommended minimum","Below recommended minimum (see Pricing Review 1, 2)")
A20: Add-on module | B20: Package status | C20: Setup | D20: Monthly | E20: Note
A21: Recipes & Food Cost | B21: =IF(A21="","",IFERROR(INDEX('Package Matrix'!$D$5:$J$116,MATCH(A21,'Package Matrix'!$B$5:$B$116,0),MATCH($B$4,'Package Matrix'!$D$4:$J$4,0)),"Not found")) | C21: =IF(OR(A21="",B21="Included",B21="Roadmap",B21="Internal",B21="Not found"),0,INDEX(Modules!$K$5:$K$116,MATCH(A21,Modules!$C$5:$C$116,0))) | D21: =IF(OR(A21="",B21="Included",B21="Roadmap",B21="Internal",B21="Not found"),0,INDEX(Modules!$L$5:$L$116,MATCH(A21,Modules!$C$5:$C$116,0))) | E21: =IF(B21="Roadmap","Not built: cannot be sold as a deliverable",IF(B21="Included","Already in package",IF(B21="Not found","Pick from the list",IF(A21="","",IF(INDEX(Modules!$F$5:$F$116,MATCH(A21,Modules!$C$5:$C$116,0))="Partial","Partial: check limits in Modules","")))))
A22: Dine-in Floor & Tables | B22: =IF(A22="","",IFERROR(INDEX('Package Matrix'!$D$5:$J$116,MATCH(A22,'Package Matrix'!$B$5:$B$116,0),MATCH($B$4,'Package Matrix'!$D$4:$J$4,0)),"Not found")) | C22: =IF(OR(A22="",B22="Included",B22="Roadmap",B22="Internal",B22="Not found"),0,INDEX(Modules!$K$5:$K$116,MATCH(A22,Modules!$C$5:$C$116,0))) | D22: =IF(OR(A22="",B22="Included",B22="Roadmap",B22="Internal",B22="Not found"),0,INDEX(Modules!$L$5:$L$116,MATCH(A22,Modules!$C$5:$C$116,0))) | E22: =IF(B22="Roadmap","Not built: cannot be sold as a deliverable",IF(B22="Included","Already in package",IF(B22="Not found","Pick from the list",IF(A22="","",IF(INDEX(Modules!$F$5:$F$116,MATCH(A22,Modules!$C$5:$C$116,0))="Partial","Partial: check limits in Modules","")))))
A23: Attendance & Shifts | B23: =IF(A23="","",IFERROR(INDEX('Package Matrix'!$D$5:$J$116,MATCH(A23,'Package Matrix'!$B$5:$B$116,0),MATCH($B$4,'Package Matrix'!$D$4:$J$4,0)),"Not found")) | C23: =IF(OR(A23="",B23="Included",B23="Roadmap",B23="Internal",B23="Not found"),0,INDEX(Modules!$K$5:$K$116,MATCH(A23,Modules!$C$5:$C$116,0))) | D23: =IF(OR(A23="",B23="Included",B23="Roadmap",B23="Internal",B23="Not found"),0,INDEX(Modules!$L$5:$L$116,MATCH(A23,Modules!$C$5:$C$116,0))) | E23: =IF(B23="Roadmap","Not built: cannot be sold as a deliverable",IF(B23="Included","Already in package",IF(B23="Not found","Pick from the list",IF(A23="","",IF(INDEX(Modules!$F$5:$F$116,MATCH(A23,Modules!$C$5:$C$116,0))="Partial","Partial: check limits in Modules","")))))
B24: =IF(A24="","",IFERROR(INDEX('Package Matrix'!$D$5:$J$116,MATCH(A24,'Package Matrix'!$B$5:$B$116,0),MATCH($B$4,'Package Matrix'!$D$4:$J$4,0)),"Not found")) | C24: =IF(OR(A24="",B24="Included",B24="Roadmap",B24="Internal",B24="Not found"),0,INDEX(Modules!$K$5:$K$116,MATCH(A24,Modules!$C$5:$C$116,0))) | D24: =IF(OR(A24="",B24="Included",B24="Roadmap",B24="Internal",B24="Not found"),0,INDEX(Modules!$L$5:$L$116,MATCH(A24,Modules!$C$5:$C$116,0))) | E24: =IF(B24="Roadmap","Not built: cannot be sold as a deliverable",IF(B24="Included","Already in package",IF(B24="Not found","Pick from the list",IF(A24="","",IF(INDEX(Modules!$F$5:$F$116,MATCH(A24,Modules!$C$5:$C$116,0))="Partial","Partial: check limits in Modules","")))))
B25: =IF(A25="","",IFERROR(INDEX('Package Matrix'!$D$5:$J$116,MATCH(A25,'Package Matrix'!$B$5:$B$116,0),MATCH($B$4,'Package Matrix'!$D$4:$J$4,0)),"Not found")) | C25: =IF(OR(A25="",B25="Included",B25="Roadmap",B25="Internal",B25="Not found"),0,INDEX(Modules!$K$5:$K$116,MATCH(A25,Modules!$C$5:$C$116,0))) | D25: =IF(OR(A25="",B25="Included",B25="Roadmap",B25="Internal",B25="Not found"),0,INDEX(Modules!$L$5:$L$116,MATCH(A25,Modules!$C$5:$C$116,0))) | E25: =IF(B25="Roadmap","Not built: cannot be sold as a deliverable",IF(B25="Included","Already in package",IF(B25="Not found","Pick from the list",IF(A25="","",IF(INDEX(Modules!$F$5:$F$116,MATCH(A25,Modules!$C$5:$C$116,0))="Partial","Partial: check limits in Modules","")))))
B26: =IF(A26="","",IFERROR(INDEX('Package Matrix'!$D$5:$J$116,MATCH(A26,'Package Matrix'!$B$5:$B$116,0),MATCH($B$4,'Package Matrix'!$D$4:$J$4,0)),"Not found")) | C26: =IF(OR(A26="",B26="Included",B26="Roadmap",B26="Internal",B26="Not found"),0,INDEX(Modules!$K$5:$K$116,MATCH(A26,Modules!$C$5:$C$116,0))) | D26: =IF(OR(A26="",B26="Included",B26="Roadmap",B26="Internal",B26="Not found"),0,INDEX(Modules!$L$5:$L$116,MATCH(A26,Modules!$C$5:$C$116,0))) | E26: =IF(B26="Roadmap","Not built: cannot be sold as a deliverable",IF(B26="Included","Already in package",IF(B26="Not found","Pick from the list",IF(A26="","",IF(INDEX(Modules!$F$5:$F$116,MATCH(A26,Modules!$C$5:$C$116,0))="Partial","Partial: check limits in Modules","")))))
B27: =IF(A27="","",IFERROR(INDEX('Package Matrix'!$D$5:$J$116,MATCH(A27,'Package Matrix'!$B$5:$B$116,0),MATCH($B$4,'Package Matrix'!$D$4:$J$4,0)),"Not found")) | C27: =IF(OR(A27="",B27="Included",B27="Roadmap",B27="Internal",B27="Not found"),0,INDEX(Modules!$K$5:$K$116,MATCH(A27,Modules!$C$5:$C$116,0))) | D27: =IF(OR(A27="",B27="Included",B27="Roadmap",B27="Internal",B27="Not found"),0,INDEX(Modules!$L$5:$L$116,MATCH(A27,Modules!$C$5:$C$116,0))) | E27: =IF(B27="Roadmap","Not built: cannot be sold as a deliverable",IF(B27="Included","Already in package",IF(B27="Not found","Pick from the list",IF(A27="","",IF(INDEX(Modules!$F$5:$F$116,MATCH(A27,Modules!$C$5:$C$116,0))="Partial","Partial: check limits in Modules","")))))
B28: =IF(A28="","",IFERROR(INDEX('Package Matrix'!$D$5:$J$116,MATCH(A28,'Package Matrix'!$B$5:$B$116,0),MATCH($B$4,'Package Matrix'!$D$4:$J$4,0)),"Not found")) | C28: =IF(OR(A28="",B28="Included",B28="Roadmap",B28="Internal",B28="Not found"),0,INDEX(Modules!$K$5:$K$116,MATCH(A28,Modules!$C$5:$C$116,0))) | D28: =IF(OR(A28="",B28="Included",B28="Roadmap",B28="Internal",B28="Not found"),0,INDEX(Modules!$L$5:$L$116,MATCH(A28,Modules!$C$5:$C$116,0))) | E28: =IF(B28="Roadmap","Not built: cannot be sold as a deliverable",IF(B28="Included","Already in package",IF(B28="Not found","Pick from the list",IF(A28="","",IF(INDEX(Modules!$F$5:$F$116,MATCH(A28,Modules!$C$5:$C$116,0))="Partial","Partial: check limits in Modules","")))))
B29: =IF(A29="","",IFERROR(INDEX('Package Matrix'!$D$5:$J$116,MATCH(A29,'Package Matrix'!$B$5:$B$116,0),MATCH($B$4,'Package Matrix'!$D$4:$J$4,0)),"Not found")) | C29: =IF(OR(A29="",B29="Included",B29="Roadmap",B29="Internal",B29="Not found"),0,INDEX(Modules!$K$5:$K$116,MATCH(A29,Modules!$C$5:$C$116,0))) | D29: =IF(OR(A29="",B29="Included",B29="Roadmap",B29="Internal",B29="Not found"),0,INDEX(Modules!$L$5:$L$116,MATCH(A29,Modules!$C$5:$C$116,0))) | E29: =IF(B29="Roadmap","Not built: cannot be sold as a deliverable",IF(B29="Included","Already in package",IF(B29="Not found","Pick from the list",IF(A29="","",IF(INDEX(Modules!$F$5:$F$116,MATCH(A29,Modules!$C$5:$C$116,0))="Partial","Partial: check limits in Modules","")))))
B30: =IF(A30="","",IFERROR(INDEX('Package Matrix'!$D$5:$J$116,MATCH(A30,'Package Matrix'!$B$5:$B$116,0),MATCH($B$4,'Package Matrix'!$D$4:$J$4,0)),"Not found")) | C30: =IF(OR(A30="",B30="Included",B30="Roadmap",B30="Internal",B30="Not found"),0,INDEX(Modules!$K$5:$K$116,MATCH(A30,Modules!$C$5:$C$116,0))) | D30: =IF(OR(A30="",B30="Included",B30="Roadmap",B30="Internal",B30="Not found"),0,INDEX(Modules!$L$5:$L$116,MATCH(A30,Modules!$C$5:$C$116,0))) | E30: =IF(B30="Roadmap","Not built: cannot be sold as a deliverable",IF(B30="Included","Already in package",IF(B30="Not found","Pick from the list",IF(A30="","",IF(INDEX(Modules!$F$5:$F$116,MATCH(A30,Modules!$C$5:$C$116,0))="Partial","Partial: check limits in Modules","")))))
B31: =IF(A31="","",IFERROR(INDEX('Package Matrix'!$D$5:$J$116,MATCH(A31,'Package Matrix'!$B$5:$B$116,0),MATCH($B$4,'Package Matrix'!$D$4:$J$4,0)),"Not found")) | C31: =IF(OR(A31="",B31="Included",B31="Roadmap",B31="Internal",B31="Not found"),0,INDEX(Modules!$K$5:$K$116,MATCH(A31,Modules!$C$5:$C$116,0))) | D31: =IF(OR(A31="",B31="Included",B31="Roadmap",B31="Internal",B31="Not found"),0,INDEX(Modules!$L$5:$L$116,MATCH(A31,Modules!$C$5:$C$116,0))) | E31: =IF(B31="Roadmap","Not built: cannot be sold as a deliverable",IF(B31="Included","Already in package",IF(B31="Not found","Pick from the list",IF(A31="","",IF(INDEX(Modules!$F$5:$F$116,MATCH(A31,Modules!$C$5:$C$116,0))="Partial","Partial: check limits in Modules","")))))
B32: =IF(A32="","",IFERROR(INDEX('Package Matrix'!$D$5:$J$116,MATCH(A32,'Package Matrix'!$B$5:$B$116,0),MATCH($B$4,'Package Matrix'!$D$4:$J$4,0)),"Not found")) | C32: =IF(OR(A32="",B32="Included",B32="Roadmap",B32="Internal",B32="Not found"),0,INDEX(Modules!$K$5:$K$116,MATCH(A32,Modules!$C$5:$C$116,0))) | D32: =IF(OR(A32="",B32="Included",B32="Roadmap",B32="Internal",B32="Not found"),0,INDEX(Modules!$L$5:$L$116,MATCH(A32,Modules!$C$5:$C$116,0))) | E32: =IF(B32="Roadmap","Not built: cannot be sold as a deliverable",IF(B32="Included","Already in package",IF(B32="Not found","Pick from the list",IF(A32="","",IF(INDEX(Modules!$F$5:$F$116,MATCH(A32,Modules!$C$5:$C$116,0))="Partial","Partial: check limits in Modules","")))))
B33: =IF(A33="","",IFERROR(INDEX('Package Matrix'!$D$5:$J$116,MATCH(A33,'Package Matrix'!$B$5:$B$116,0),MATCH($B$4,'Package Matrix'!$D$4:$J$4,0)),"Not found")) | C33: =IF(OR(A33="",B33="Included",B33="Roadmap",B33="Internal",B33="Not found"),0,INDEX(Modules!$K$5:$K$116,MATCH(A33,Modules!$C$5:$C$116,0))) | D33: =IF(OR(A33="",B33="Included",B33="Roadmap",B33="Internal",B33="Not found"),0,INDEX(Modules!$L$5:$L$116,MATCH(A33,Modules!$C$5:$C$116,0))) | E33: =IF(B33="Roadmap","Not built: cannot be sold as a deliverable",IF(B33="Included","Already in package",IF(B33="Not found","Pick from the list",IF(A33="","",IF(INDEX(Modules!$F$5:$F$116,MATCH(A33,Modules!$C$5:$C$116,0))="Partial","Partial: check limits in Modules","")))))
B34: =IF(A34="","",IFERROR(INDEX('Package Matrix'!$D$5:$J$116,MATCH(A34,'Package Matrix'!$B$5:$B$116,0),MATCH($B$4,'Package Matrix'!$D$4:$J$4,0)),"Not found")) | C34: =IF(OR(A34="",B34="Included",B34="Roadmap",B34="Internal",B34="Not found"),0,INDEX(Modules!$K$5:$K$116,MATCH(A34,Modules!$C$5:$C$116,0))) | D34: =IF(OR(A34="",B34="Included",B34="Roadmap",B34="Internal",B34="Not found"),0,INDEX(Modules!$L$5:$L$116,MATCH(A34,Modules!$C$5:$C$116,0))) | E34: =IF(B34="Roadmap","Not built: cannot be sold as a deliverable",IF(B34="Included","Already in package",IF(B34="Not found","Pick from the list",IF(A34="","",IF(INDEX(Modules!$F$5:$F$116,MATCH(A34,Modules!$C$5:$C$116,0))="Partial","Partial: check limits in Modules","")))))
B35: =IF(A35="","",IFERROR(INDEX('Package Matrix'!$D$5:$J$116,MATCH(A35,'Package Matrix'!$B$5:$B$116,0),MATCH($B$4,'Package Matrix'!$D$4:$J$4,0)),"Not found")) | C35: =IF(OR(A35="",B35="Included",B35="Roadmap",B35="Internal",B35="Not found"),0,INDEX(Modules!$K$5:$K$116,MATCH(A35,Modules!$C$5:$C$116,0))) | D35: =IF(OR(A35="",B35="Included",B35="Roadmap",B35="Internal",B35="Not found"),0,INDEX(Modules!$L$5:$L$116,MATCH(A35,Modules!$C$5:$C$116,0))) | E35: =IF(B35="Roadmap","Not built: cannot be sold as a deliverable",IF(B35="Included","Already in package",IF(B35="Not found","Pick from the list",IF(A35="","",IF(INDEX(Modules!$F$5:$F$116,MATCH(A35,Modules!$C$5:$C$116,0))="Partial","Partial: check limits in Modules","")))))
... B40: =IF(A40="","",IFERROR(INDEX('Package Matrix'!$D$5:$J$116,MATCH(A40,'Package Matrix'!$B$5:$B$116,0),MATCH($B$4,'Package Matrix'!$D$4:$J$4,0)),"Not found")) | C40: =IF(OR(A40="",B40="Included",B40="Roadmap",B40="Internal",B40="Not found"),0,INDEX(Modules!$K$5:$K$116,MATCH(A40,Modules!$C$5:$C$116,0))) | D40: =IF(OR(A40="",B40="Included",B40="Roadmap",B40="Internal",B40="Not found"),0,INDEX(Modules!$L$5:$L$116,MATCH(A40,Modules!$C$5:$C$116,0))) | E40: =IF(B40="Roadmap","Not built: cannot be sold as a deliverable",IF(B40="Included","Already in package",IF(B40="Not found","Pick from the list",IF(A40="","",IF(INDEX(Modules!$F$5:$F$116,MATCH(A40,Modules!$C$5:$C$116,0))="Partial","Partial: check limits in Modules","")))))
A42: Customization
A43: Customization | B43: Tier | C43: Qty | D43: Unit price | E43: Charge type | F43: One-time total | G43: Monthly total
A44: Approval workflow | B44: Standard | C44: 2 | D44: =IF(A44="","",IFERROR(INDEX('Customization Rates'!$C$5:$E$22,MATCH(A44,'Customization Rates'!$A$5:$A$22,0),MATCH(B44,'Customization Rates'!$C$4:$E$4,0)),0)) | E44: =IF(A44="","",IFERROR(INDEX('Customization Rates'!$F$5:$F$22,MATCH(A44,'Customization Rates'!$A$5:$A$22,0)),"")) | F44: =IF(OR(A44="",E44="Monthly"),0,D44*C44) | G44: =IF(AND(A44<>"",E44="Monthly"),D44*C44,0)
A45: Custom report | B45: Basic | C45: 3 | D45: =IF(A45="","",IFERROR(INDEX('Customization Rates'!$C$5:$E$22,MATCH(A45,'Customization Rates'!$A$5:$A$22,0),MATCH(B45,'Customization Rates'!$C$4:$E$4,0)),0)) | E45: =IF(A45="","",IFERROR(INDEX('Customization Rates'!$F$5:$F$22,MATCH(A45,'Customization Rates'!$A$5:$A$22,0)),"")) | F45: =IF(OR(A45="",E45="Monthly"),0,D45*C45) | G45: =IF(AND(A45<>"",E45="Monthly"),D45*C45,0)
A46: Data migration | B46: Standard | C46: 1 | D46: =IF(A46="","",IFERROR(INDEX('Customization Rates'!$C$5:$E$22,MATCH(A46,'Customization Rates'!$A$5:$A$22,0),MATCH(B46,'Customization Rates'!$C$4:$E$4,0)),0)) | E46: =IF(A46="","",IFERROR(INDEX('Customization Rates'!$F$5:$F$22,MATCH(A46,'Customization Rates'!$A$5:$A$22,0)),"")) | F46: =IF(OR(A46="",E46="Monthly"),0,D46*C46) | G46: =IF(AND(A46<>"",E46="Monthly"),D46*C46,0)
D47: =IF(A47="","",IFERROR(INDEX('Customization Rates'!$C$5:$E$22,MATCH(A47,'Customization Rates'!$A$5:$A$22,0),MATCH(B47,'Customization Rates'!$C$4:$E$4,0)),0)) | E47: =IF(A47="","",IFERROR(INDEX('Customization Rates'!$F$5:$F$22,MATCH(A47,'Customization Rates'!$A$5:$A$22,0)),"")) | F47: =IF(OR(A47="",E47="Monthly"),0,D47*C47) | G47: =IF(AND(A47<>"",E47="Monthly"),D47*C47,0)
D48: =IF(A48="","",IFERROR(INDEX('Customization Rates'!$C$5:$E$22,MATCH(A48,'Customization Rates'!$A$5:$A$22,0),MATCH(B48,'Customization Rates'!$C$4:$E$4,0)),0)) | E48: =IF(A48="","",IFERROR(INDEX('Customization Rates'!$F$5:$F$22,MATCH(A48,'Customization Rates'!$A$5:$A$22,0)),"")) | F48: =IF(OR(A48="",E48="Monthly"),0,D48*C48) | G48: =IF(AND(A48<>"",E48="Monthly"),D48*C48,0)
D49: =IF(A49="","",IFERROR(INDEX('Customization Rates'!$C$5:$E$22,MATCH(A49,'Customization Rates'!$A$5:$A$22,0),MATCH(B49,'Customization Rates'!$C$4:$E$4,0)),0)) | E49: =IF(A49="","",IFERROR(INDEX('Customization Rates'!$F$5:$F$22,MATCH(A49,'Customization Rates'!$A$5:$A$22,0)),"")) | F49: =IF(OR(A49="",E49="Monthly"),0,D49*C49) | G49: =IF(AND(A49<>"",E49="Monthly"),D49*C49,0)
D50: =IF(A50="","",IFERROR(INDEX('Customization Rates'!$C$5:$E$22,MATCH(A50,'Customization Rates'!$A$5:$A$22,0),MATCH(B50,'Customization Rates'!$C$4:$E$4,0)),0)) | E50: =IF(A50="","",IFERROR(INDEX('Customization Rates'!$F$5:$F$22,MATCH(A50,'Customization Rates'!$A$5:$A$22,0)),"")) | F50: =IF(OR(A50="",E50="Monthly"),0,D50*C50) | G50: =IF(AND(A50<>"",E50="Monthly"),D50*C50,0)
D51: =IF(A51="","",IFERROR(INDEX('Customization Rates'!$C$5:$E$22,MATCH(A51,'Customization Rates'!$A$5:$A$22,0),MATCH(B51,'Customization Rates'!$C$4:$E$4,0)),0)) | E51: =IF(A51="","",IFERROR(INDEX('Customization Rates'!$F$5:$F$22,MATCH(A51,'Customization Rates'!$A$5:$A$22,0)),"")) | F51: =IF(OR(A51="",E51="Monthly"),0,D51*C51) | G51: =IF(AND(A51<>"",E51="Monthly"),D51*C51,0)
D52: =IF(A52="","",IFERROR(INDEX('Customization Rates'!$C$5:$E$22,MATCH(A52,'Customization Rates'!$A$5:$A$22,0),MATCH(B52,'Customization Rates'!$C$4:$E$4,0)),0)) | E52: =IF(A52="","",IFERROR(INDEX('Customization Rates'!$F$5:$F$22,MATCH(A52,'Customization Rates'!$A$5:$A$22,0)),"")) | F52: =IF(OR(A52="",E52="Monthly"),0,D52*C52) | G52: =IF(AND(A52<>"",E52="Monthly"),D52*C52,0)
D53: =IF(A53="","",IFERROR(INDEX('Customization Rates'!$C$5:$E$22,MATCH(A53,'Customization Rates'!$A$5:$A$22,0),MATCH(B53,'Customization Rates'!$C$4:$E$4,0)),0)) | E53: =IF(A53="","",IFERROR(INDEX('Customization Rates'!$F$5:$F$22,MATCH(A53,'Customization Rates'!$A$5:$A$22,0)),"")) | F53: =IF(OR(A53="",E53="Monthly"),0,D53*C53) | G53: =IF(AND(A53<>"",E53="Monthly"),D53*C53,0)
D54: =IF(A54="","",IFERROR(INDEX('Customization Rates'!$C$5:$E$22,MATCH(A54,'Customization Rates'!$A$5:$A$22,0),MATCH(B54,'Customization Rates'!$C$4:$E$4,0)),0)) | E54: =IF(A54="","",IFERROR(INDEX('Customization Rates'!$F$5:$F$22,MATCH(A54,'Customization Rates'!$A$5:$A$22,0)),"")) | F54: =IF(OR(A54="",E54="Monthly"),0,D54*C54) | G54: =IF(AND(A54<>"",E54="Monthly"),D54*C54,0)
D55: =IF(A55="","",IFERROR(INDEX('Customization Rates'!$C$5:$E$22,MATCH(A55,'Customization Rates'!$A$5:$A$22,0),MATCH(B55,'Customization Rates'!$C$4:$E$4,0)),0)) | E55: =IF(A55="","",IFERROR(INDEX('Customization Rates'!$F$5:$F$22,MATCH(A55,'Customization Rates'!$A$5:$A$22,0)),"")) | F55: =IF(OR(A55="",E55="Monthly"),0,D55*C55) | G55: =IF(AND(A55<>"",E55="Monthly"),D55*C55,0)
D56: =IF(A56="","",IFERROR(INDEX('Customization Rates'!$C$5:$E$22,MATCH(A56,'Customization Rates'!$A$5:$A$22,0),MATCH(B56,'Customization Rates'!$C$4:$E$4,0)),0)) | E56: =IF(A56="","",IFERROR(INDEX('Customization Rates'!$F$5:$F$22,MATCH(A56,'Customization Rates'!$A$5:$A$22,0)),"")) | F56: =IF(OR(A56="",E56="Monthly"),0,D56*C56) | G56: =IF(AND(A56<>"",E56="Monthly"),D56*C56,0)
D57: =IF(A57="","",IFERROR(INDEX('Customization Rates'!$C$5:$E$22,MATCH(A57,'Customization Rates'!$A$5:$A$22,0),MATCH(B57,'Customization Rates'!$C$4:$E$4,0)),0)) | E57: =IF(A57="","",IFERROR(INDEX('Customization Rates'!$F$5:$F$22,MATCH(A57,'Customization Rates'!$A$5:$A$22,0)),"")) | F57: =IF(OR(A57="",E57="Monthly"),0,D57*C57) | G57: =IF(AND(A57<>"",E57="Monthly"),D57*C57,0)
D58: =IF(A58="","",IFERROR(INDEX('Customization Rates'!$C$5:$E$22,MATCH(A58,'Customization Rates'!$A$5:$A$22,0),MATCH(B58,'Customization Rates'!$C$4:$E$4,0)),0)) | E58: =IF(A58="","",IFERROR(INDEX('Customization Rates'!$F$5:$F$22,MATCH(A58,'Customization Rates'!$A$5:$A$22,0)),"")) | F58: =IF(OR(A58="",E58="Monthly"),0,D58*C58) | G58: =IF(AND(A58<>"",E58="Monthly"),D58*C58,0)

Sheet Packages
A1: Verity Packages
A2: Numeric floors (blue) drive Quick Quote. Fees marked + are floors, final price depends on scope. Prices are proposed 2026 rates, ex-GST.
A4: Package | B4: Positioning | C4: Scope (as sold) | D4: Implementation fee (as sold) | E4: Setup floor | F4: Open-ended? | G4: Platform fee (as sold) | H4: Monthly floor | I4: Ideal customer | J4: First year, monthly billing | K4: First year, annual prepay | L4: Modules included | M4: Known scope gaps | N4: Meets recommended minimum?
A5: Verity Core | B5: Core business operations | C5: CRM; customers; leads; quotations; sales orders; invoicing; basic inventory; dashboards; users/roles | D5: ₹40,000+ setup | E5: 40000 | F5: Yes | G5: ₹2,000/mo | H5: 2000 | I5: Best for service/professional MSMEs | J5: =E5+12*H5 | K5: =E5+12*H5*(1-'Pricing Rules'!$B$12) | L5: ='Package Matrix'!D118 | M5: Quotations (M152) not built. Leads use the outreach pipeline (M120). | N5: =IF(AND(E5>='Pricing Rules'!$B$15,H5>='Pricing Rules'!$B$16),"Yes","Below minimum")
A6: Verity Trade | B6: Trading / distribution | C6: Core + procurement; vendors; purchase orders; inventory; warehouses; stock controls; receivables; | D6: ₹50,000+ setup | E6: 50000 | F6: Yes | G6: ₹3,000/mo | H6: 3000 | I6: For distributors, dealers and trading businesses | J6: =E6+12*H6 | K6: =E6+12*H6*(1-'Pricing Rules'!$B$12) | L6: ='Package Matrix'!E118 | M6: Inherits Core gap: quotations (M152). | N6: =IF(AND(E6>='Pricing Rules'!$B$15,H6>='Pricing Rules'!$B$16),"Yes","Below minimum")
A7: Verity Services | B7: Service businesses | C7: Core + projects; jobs; scheduling; timesheets; work logs; service workflows; customer portal-ready architecture | D7: ₹75,000+ setup | E7: 75000 | F7: Yes | G7: ₹5,000/mo | H7: 5000 | I7: For consulting, agencies, engineering, legal/accounting and field services | J7: =E7+12*H7 | K7: =E7+12*H7*(1-'Pricing Rules'!$B$12) | L7: ='Package Matrix'!F118 | M7: Projects, timesheets, customer portal (M153, M154) not built. Core gap M152. | N7: =IF(AND(E7>='Pricing Rules'!$B$15,H7>='Pricing Rules'!$B$16),"Yes","Below minimum")
A8: Verity Production | B8: Manufacturing | C8: Core + inventory; BOM; production planning; work orders; material consumption; QC; wastage; shop-floor workflows | D8: ₹90,000+ setup | E8: 90000 | F8: Yes | G8: ₹8,000/mo | H8: 8000 | I8: For small and mid-sized manufacturers | J8: =E8+12*H8 | K8: =E8+12*H8*(1-'Pricing Rules'!$B$12) | L8: ='Package Matrix'!G118 | M8: Wastage exists (M061); advanced QC (M109) and MRP (M110) not built. | N8: =IF(AND(E8>='Pricing Rules'!$B$15,H8>='Pricing Rules'!$B$16),"Yes","Below minimum")
A9: Verity Manufacturing Plus | B9: Advanced manufacturing | C9: Production + advanced QC; multi-level BOM; revisions; job tracking; dashboards; approvals; traceability; integrations | D9: ₹1,25,000+ setup | E9: 125000 | F9: Yes | G9: ₹10,000/mo | H9: 10000 | I9: For more complex factories | J9: =E9+12*H9 | K9: =E9+12*H9*(1-'Pricing Rules'!$B$12) | L9: ='Package Matrix'!H118 | M9: Multi-level BOM revisions, advanced QC, approvals on production not confirmed (M109). | N9: =IF(AND(E9>='Pricing Rules'!$B$15,H9>='Pricing Rules'!$B$16),"Yes","Below minimum")
A10: Verity Enterprise | B10: Multi-function enterprise | C10: Custom combination of CRM, sales, procurement, inventory, production, projects, workforce, finance, QC, analytics and integrations | D10: ₹1,50,000+ setup | E10: 150000 | F10: Yes | G10: ₹12,000+/mo | H10: 12000 | I10: Custom architecture and SLA | J10: =E10+12*H10 | K10: =E10+12*H10*(1-'Pricing Rules'!$B$12) | L10: ='Package Matrix'!I118 | M10: Roadmap items cannot be sold until built; see Roadmap & Gaps. | N10: =IF(AND(E10>='Pricing Rules'!$B$15,H10>='Pricing Rules'!$B$16),"Yes","Below minimum")
A11: Verity Dedicated | B11: Dedicated business OS | C11: Dedicated environment; custom modules; custom workflows; integrations; PWA/offline; priority support; dedicated roadmap | D11: ₹1,80,000 | E11: 180000 | F11: No | G11: ₹15,000/mo | H11: 15000 | I11: For organizations requiring deep adaptation | J11: =E11+12*H11 | K11: =E11+12*H11*(1-'Pricing Rules'!$B$12) | L11: ='Package Matrix'!J118 | M11: Dedicated environment is an ops service (HQ console M016), not a product SKU in code. | N11: =IF(AND(E11>='Pricing Rules'!$B$15,H11>='Pricing Rules'!$B$16),"Yes","Below minimum")

Sheet Package Matrix
A1: Package x Module Matrix
A2: Included = in the package price. Add-on = built, priced from Modules. Roadmap = not built, cannot be quoted as a deliverable. Edit a cell to change a package definition.
A4: ID | B4: Module | C4: Status | D4: Verity Core | E4: Verity Trade | F4: Verity Services | G4: Verity Production | H4: Verity Manufacturing Plus | I4: Verity Enterprise | J4: Verity Dedicated
A5: M001 | B5: Tenancy & Organizations | C5: Live | D5: Included | E5: Included | F5: Included | G5: Included | H5: Included | I5: Included | J5: Included
A6: M002 | B6: Users, Roles & Permissions | C6: Live | D6: Included | E6: Included | F6: Included | G6: Included | H6: Included | I6: Included | J6: Included
A7: M003 | B7: SSO / OIDC Login | C7: Live | D7: Included | E7: Included | F7: Included | G7: Included | H7: Included | I7: Included | J7: Included
A8: M004 | B8: Audit Trail & Activity History | C8: Live | D8: Included | E8: Included | F8: Included | G8: Included | H8: Included | I8: Included | J8: Included
A9: M005 | B9: Workflow & State Engine | C9: Live | D9: Included | E9: Included | F9: Included | G9: Included | H9: Included | I9: Included | J9: Included
A10: M006 | B10: Approvals | C10: Live | D10: Included | E10: Included | F10: Included | G10: Included | H10: Included | I10: Included | J10: Included
A11: M007 | B11: Notifications | C11: Partial | D11: Included | E11: Included | F11: Included | G11: Included | H11: Included | I11: Included | J11: Included
A12: M008 | B12: SLA Clocks & Business Calendar | C12: Live | D12: Included | E12: Included | F12: Included | G12: Included | H12: Included | I12: Included | J12: Included
A13: M009 | B13: Custom Fields & Configuration | C13: Live | D13: Included | E13: Included | F13: Included | G13: Included | H13: Included | I13: Included | J13: Included
A14: M010 | B14: Industry Packs & Templates | C14: Live | D14: Included | E14: Included | F14: Included | G14: Included | H14: Included | I14: Included | J14: Included
A15: M011 | B15: Capability Activation & Upgrades | C15: Live | D15: Included | E15: Included | F15: Included | G15: Included | H15: Included | I15: Included | J15: Included
... A116: M160 | B116: Custom Report Builder | C116: Planned | D116: Roadmap | E116: Roadmap | F116: Roadmap | G116: Roadmap | H116: Roadmap | I116: Roadmap | J116: Roadmap
B118: Modules included | D118: =COUNTIF(D5:D116,"Included") | E118: =COUNTIF(E5:E116,"Included") | F118: =COUNTIF(F5:F116,"Included") | G118: =COUNTIF(G5:G116,"Included") | H118: =COUNTIF(H5:H116,"Included") | I118: =COUNTIF(I5:I116,"Included") | J118: =COUNTIF(J5:J116,"Included")

Sheet Modules
A1: Verity Module Catalogue
A2: 112 modules. Status is verified against the Verity codebase as of 2026-10-06. Add-on prices are formulas driven by Complexity and Pricing Rules.
A4: ID | B4: Group | C4: Module | D4: What the customer gets | E4: Key features | F4: Status | G4: Proof client | H4: Code reference | I4: Complexity | J4: Depends on | K4: Add-on setup | L4: Add-on monthly | M4: Sellable today? | N4: Sales pitch line | O4: Dev / PM notes
A5: M001 | B5: Platform Foundation | C5: Tenancy & Organizations | D5: Every client gets an isolated workspace with its own organisations, branches and people. | E5: Tenant isolation enforced in the database; organisation hierarchy; Party model for people and companies | F5: Live | G5: All tenants | H5: platform/tenancy.ts, identity.ts | I5: S | K5: =INDEX('Pricing Rules'!$B$5:$B$8,MATCH(I5,'Pricing Rules'!$A$5:$A$8,0)) | L5: =INDEX('Pricing Rules'!$C$5:$C$8,MATCH(I5,'Pricing Rules'!$A$5:$A$8,0)) | M5: =IF(OR(F5="Live",F5="Live (client-built)"),"Yes",IF(F5="Partial","Yes, with limits","No")) | N5: Your data is walled off from every other client at database level, not just in the app. | O5: Tables: Tenant, Organization, Party. RLS via withTenant().
A6: M002 | B6: Platform Foundation | C6: Users, Roles & Permissions | D6: Define who can see and do what, down to individual fields. | E6: Roles and role composition; permission matrix; field-level permissions | F6: Live | G6: All tenants | H6: platform/authorization.ts | I6: S | J6: M001 | K6: =INDEX('Pricing Rules'!$B$5:$B$8,MATCH(I6,'Pricing Rules'!$A$5:$A$8,0)) | L6: =INDEX('Pricing Rules'!$C$5:$C$8,MATCH(I6,'Pricing Rules'!$A$5:$A$8,0)) | M6: =IF(OR(F6="Live",F6="Live (client-built)"),"Yes",IF(F6="Partial","Yes, with limits","No")) | N6: Warehouse sees stock, finance sees money, owner sees everything, set once. | O6: Tables: Role, RoleComposition, Permission, FieldPermission. UI: /roles, /people.
A7: M003 | B7: Platform Foundation | C7: SSO / OIDC Login | D7: Staff sign in with the company identity provider. | E7: OIDC browser flow; external auth adapter; password reset and verification | F7: Live | G7: OIDC lab identity | H7: platform/oidc.ts, external-auth.ts | I7: M | J7: M001 | K7: =INDEX('Pricing Rules'!$B$5:$B$8,MATCH(I7,'Pricing Rules'!$A$5:$A$8,0)) | L7: =INDEX('Pricing Rules'!$C$5:$C$8,MATCH(I7,'Pricing Rules'!$A$5:$A$8,0)) | M7: =IF(OR(F7="Live",F7="Live (client-built)"),"Yes",IF(F7="Partial","Yes, with limits","No")) | N7: Plug into the client's existing sign-in instead of another password. | O7: Tables: Credential, OidcLoginTransaction. Routes: /sign-in, /reset-password.
A8: M004 | B8: Platform Foundation | C8: Audit Trail & Activity History | D8: Who changed what and when, on every record, impossible to edit. | E8: Append-only audit events; per-record timeline; security audit events; audit viewer | F8: Live | G8: All tenants | H8: platform/audit.ts | I8: S | J8: M001 | K8: =INDEX('Pricing Rules'!$B$5:$B$8,MATCH(I8,'Pricing Rules'!$A$5:$A$8,0)) | L8: =INDEX('Pricing Rules'!$C$5:$C$8,MATCH(I8,'Pricing Rules'!$A$5:$A$8,0)) | M8: =IF(OR(F8="Live",F8="Live (client-built)"),"Yes",IF(F8="Partial","Yes, with limits","No")) | N8: Every change has a name and a timestamp. | O8: Tables: Activity, SecurityAuditEvent, DomainEvent. UI: /audit, /hq/audit.
A9: M005 | B9: Platform Foundation | C9: Workflow & State Engine | D9: Every record moves through defined states, and the rules are configurable. | E9: State definitions and transitions; workflow nodes, edges, runs; guarded transitions | F9: Live | G9: All tenants | H9: platform/workflow.ts, state.ts | I9: M | J9: M001 | K9: =INDEX('Pricing Rules'!$B$5:$B$8,MATCH(I9,'Pricing Rules'!$A$5:$A$8,0)) | L9: =INDEX('Pricing Rules'!$C$5:$C$8,MATCH(I9,'Pricing Rules'!$A$5:$A$8,0)) | M9: =IF(OR(F9="Live",F9="Live (client-built)"),"Yes",IF(F9="Partial","Yes, with limits","No")) | N9: Orders, invoices, leave and approvals all follow the same enforced path. | O9: Tables: StateDefinition, TransitionDefinition, WorkflowDefinition/Node/Edge/Run/StepRun.
A10: M006 | B10: Platform Foundation | C10: Approvals | D10: Multi-step approval chains by role, in sequence. | E10: Approval by role not person; ordered steps; rejection ends chain; comments; inbox | F10: Live | G10: Kent's, Shree Ganesh | H10: capabilities/approval | I10: S | J10: M005 | K10: =INDEX('Pricing Rules'!$B$5:$B$8,MATCH(I10,'Pricing Rules'!$A$5:$A$8,0)) | L10: =INDEX('Pricing Rules'!$C$5:$C$8,MATCH(I10,'Pricing Rules'!$A$5:$A$8,0)) | M10: =IF(OR(F10="Live",F10="Live (client-built)"),"Yes",IF(F10="Partial","Yes, with limits","No")) | N10: Spend above a limit goes to the right person automatically and survives staff changes. | O10: Commands: approval.request, approval.decide. UI: /approvals.
A11: M007 | B11: Platform Foundation | C11: Notifications | D11: In-app notifications driven by business events, with templates and preferences. | E11: Notification templates; preferences; written transactionally with the business change | F11: Partial | G11: All tenants | H11: platform/notification.ts | I11: M | J11: M005 | K11: =INDEX('Pricing Rules'!$B$5:$B$8,MATCH(I11,'Pricing Rules'!$A$5:$A$8,0)) | L11: =INDEX('Pricing Rules'!$C$5:$C$8,MATCH(I11,'Pricing Rules'!$A$5:$A$8,0)) | M11: =IF(OR(F11="Live",F11="Live (client-built)"),"Yes",IF(F11="Partial","Yes, with limits","No")) | N11: Overdue, approvals and low stock reach the person who owns them. | O11: In-app only. Email/WhatsApp/SMS delivery adapters not built (see M155).
A12: M008 | B12: Platform Foundation | C12: SLA Clocks & Business Calendar | D12: Deadlines that respect working hours and holidays. | E12: SLA policies and clocks; business calendars, hours, holidays | F12: Live | G12: Platform | H12: platform/sla.ts, temporal.ts | I12: M | J12: M001 | K12: =INDEX('Pricing Rules'!$B$5:$B$8,MATCH(I12,'Pricing Rules'!$A$5:$A$8,0)) | L12: =INDEX('Pricing Rules'!$C$5:$C$8,MATCH(I12,'Pricing Rules'!$A$5:$A$8,0)) | M12: =IF(OR(F12="Live",F12="Live (client-built)"),"Yes",IF(F12="Partial","Yes, with limits","No")) | N12: Response and delivery deadlines count working time only. | O12: Tables: SlaPolicy, SlaClock, BusinessCalendar, BusinessHours, BusinessHoliday.
A13: M009 | B13: Platform Foundation | C13: Custom Fields & Configuration | D13: Add fields and settings per client without code. | E13: Custom field schemas per entity; config parameters; settings pages | F13: Live | G13: All tenants | H13: platform/config.ts | I13: S | J13: M001 | K13: =INDEX('Pricing Rules'!$B$5:$B$8,MATCH(I13,'Pricing Rules'!$A$5:$A$8,0)) | L13: =INDEX('Pricing Rules'!$C$5:$C$8,MATCH(I13,'Pricing Rules'!$A$5:$A$8,0)) | M13: =IF(OR(F13="Live",F13="Live (client-built)"),"Yes",IF(F13="Partial","Yes, with limits","No")) | N13: Track the extra thing this business cares about without a developer. | O13: Tables: CustomFieldSchema, ConfigParameter. UI: /configuration, /settings.
A14: M010 | B14: Platform Foundation | C14: Industry Packs & Templates | D14: Install a pre-built industry setup in one step. | E14: Pack releases, instances, operations; template definitions and instances | F14: Live | G14: Plywood, Kent's | H14: platform/pack.ts, template.ts | I14: M | J14: M011 | K14: =INDEX('Pricing Rules'!$B$5:$B$8,MATCH(I14,'Pricing Rules'!$A$5:$A$8,0)) | L14: =INDEX('Pricing Rules'!$C$5:$C$8,MATCH(I14,'Pricing Rules'!$A$5:$A$8,0)) | M14: =IF(OR(F14="Live",F14="Live (client-built)"),"Yes",IF(F14="Partial","Yes, with limits","No")) | N14: Start from a proven setup for your industry, then tune it. | O14: Tables: PackRelease/Instance/Operation/Contribution/Event, TemplateDefinition/Instance.
A15: M011 | B15: Platform Foundation | C15: Capability Activation & Upgrades | D15: Switch modules on per client and upgrade safely. | E15: Per-tenant activation; dependency enforcement by DB trigger; upgrade operations | F15: Live | G15: All tenants | H15: platform/capability.ts, capability-upgrade.ts | I15: M | J15: M001 | K15: =INDEX('Pricing Rules'!$B$5:$B$8,MATCH(I15,'Pricing Rules'!$A$5:$A$8,0)) | L15: =INDEX('Pricing Rules'!$C$5:$C$8,MATCH(I15,'Pricing Rules'!$A$5:$A$8,0)) | M15: =IF(OR(F15="Live",F15="Live (client-built)"),"Yes",IF(F15="Partial","Yes, with limits","No")) | N15: Pay for and see only the modules you use; add more later with no migration. | O15: Tables: CapabilityDefinition, TenantActivation, CapabilityUpgradeOperation. UI: /capabilities.
A16: M012 | B16: Platform Foundation | C16: Files & Storage | D16: Documents and attachments stored per client with access control. | E16: Stored file records; pluggable storage backend; checksum-verified files | F16: Live | G16: Outreach research files | H16: platform/files.ts, storage | I16: S | J16: M001 | K16: =INDEX('Pricing Rules'!$B$5:$B$8,MATCH(I16,'Pricing Rules'!$A$5:$A$8,0)) | L16: =INDEX('Pricing Rules'!$C$5:$C$8,MATCH(I16,'Pricing Rules'!$A$5:$A$8,0)) | M16: =IF(OR(F16="Live",F16="Live (client-built)"),"Yes",IF(F16="Partial","Yes, with limits","No")) | N16: Attach the contract, photo or PDF to the record it belongs to. | O16: Table: StoredFile.
A17: M013 | B17: Platform Foundation | C17: Offline Sync Runtime | D17: Commands captured offline replay safely when back online. | E17: Idempotent inbox; ordered replay; optimistic concurrency; conflict surfacing | F17: Partial | G17: None live | H17: platform/sync.ts | I17: L | J17: M001 | K17: =INDEX('Pricing Rules'!$B$5:$B$8,MATCH(I17,'Pricing Rules'!$A$5:$A$8,0)) | L17: =INDEX('Pricing Rules'!$C$5:$C$8,MATCH(I17,'Pricing Rules'!$A$5:$A$8,0)) | M17: =IF(OR(F17="Live",F17="Live (client-built)"),"Yes",IF(F17="Partial","Yes, with limits","No")) | N17: Shop-floor and field work survives bad connectivity. | O17: Runtime only. No installable PWA shell or client queue UI. Tables: OfflineCommand, SyncException.
A18: M014 | B18: Platform Foundation | C18: API Keys & External Tool Invocation | D18: Let other systems call Verity commands securely. | E18: External API keys; idempotency keys; tool manifest; /api/tools/invoke; quotas | F18: Partial | G18: None live | H18: platform/external-tools.ts, tool-manifest.ts | I18: L | J18: M002 | K18: =INDEX('Pricing Rules'!$B$5:$B$8,MATCH(I18,'Pricing Rules'!$A$5:$A$8,0)) | L18: =INDEX('Pricing Rules'!$C$5:$C$8,MATCH(I18,'Pricing Rules'!$A$5:$A$8,0)) | M18: =IF(OR(F18="Live",F18="Live (client-built)"),"Yes",IF(F18="Partial","Yes, with limits","No")) | N18: Connect an outside system without opening the database. | O18: Tables: ExternalApiKey, ExternalIdempotency, RequestQuota. Relay integration is ADR-029 proposed (Task 120). No public API docs.
A19: M015 | B19: Platform Foundation | C19: Security Hardening | D19: Rate limits, strict CSP, redaction and telemetry scrubbing. | E19: Shared rate limiting; CSP; log redaction; request size limits | F19: Live | G19: Platform | H19: platform/rate-limit.ts, csp.ts, redaction.ts | I19: S | K19: =INDEX('Pricing Rules'!$B$5:$B$8,MATCH(I19,'Pricing Rules'!$A$5:$A$8,0)) | L19: =INDEX('Pricing Rules'!$C$5:$C$8,MATCH(I19,'Pricing Rules'!$A$5:$A$8,0)) | M19: =IF(OR(F19="Live",F19="Live (client-built)"),"Yes",IF(F19="Partial","Yes, with limits","No")) | N19: Built-in protection against abuse and accidental data leaks. | O19: Enterprise-hardening claims need the evidence programme (Task 123) finished.
A20: M016 | B20: Platform Foundation | C20: HQ Operator Console | D20: PlotArmour's own console to run every client workspace. | E20: Client list; per-client modules, packs, people, roles, organisations, operations, settings | F20: Live | G20: PlotArmour internal | H20: src/app/(hq) | I20: M | J20: M011 | K20: =INDEX('Pricing Rules'!$B$5:$B$8,MATCH(I20,'Pricing Rules'!$A$5:$A$8,0)) | L20: =INDEX('Pricing Rules'!$C$5:$C$8,MATCH(I20,'Pricing Rules'!$A$5:$A$8,0)) | M20: =IF(OR(F20="Live",F20="Live (client-built)"),"Yes",IF(F20="Partial","Yes, with limits","No")) | N20: One place to onboard, configure and support every client. | O20: Routes: /hq, /hq/clients/[tenantId]/*. Internal, not sold.
A21: M017 | B21: Platform Foundation | C21: Data Import & Migration | D21: Bring items, customers and suppliers across from Excel or an old system. | E21: Import wizard; duplicate handling; item, customer, supplier scope | F21: Partial | G21: Shree Ganesh | H21: server/actions/import.ts | I21: M | J21: M001 | K21: =INDEX('Pricing Rules'!$B$5:$B$8,MATCH(I21,'Pricing Rules'!$A$5:$A$8,0)) | L21: =INDEX('Pricing Rules'!$C$5:$C$8,MATCH(I21,'Pricing Rules'!$A$5:$A$8,0)) | M21: =IF(OR(F21="Live",F21="Live (client-built)"),"Yes",IF(F21="Partial","Yes, with limits","No")) | N21: Day-one data without retyping. | O21: Only item, customer and supplier import. Orders, balances, ledgers not importable. UI: /import.
A22: M018 | B22: Platform Foundation | C22: Dashboards & Workspaces | D22: Role-based home screens with live KPIs and sparklines. | E22: Overview dashboard; workspace home; metric snapshots with history | F22: Live | G22: All tenants | H22: platform/dashboard.ts | I22: S | J22: M001 | K22: =INDEX('Pricing Rules'!$B$5:$B$8,MATCH(I22,'Pricing Rules'!$A$5:$A$8,0)) | L22: =INDEX('Pricing Rules'!$C$5:$C$8,MATCH(I22,'Pricing Rules'!$A$5:$A$8,0)) | M22: =IF(OR(F22="Live",F22="Live (client-built)"),"Yes",IF(F22="Partial","Yes, with limits","No")) | N22: Open Verity and see today's business, not last month's report. | O22: UI: /overview, /workspace. Table: TradingMetricSnapshot.
A23: M019 | B23: Platform Foundation | C23: Verity AI Assistant | D23: Ask questions in plain language, answered from the client's own records. | E23: Permission-aware agent chat; grounded answers; tool manifest; bulk ops with partial failure | F23: Live | G23: All tenants | H23: platform/agent-chat.ts, grounding.ts | I23: L | J23: M002 | K23: =INDEX('Pricing Rules'!$B$5:$B$8,MATCH(I23,'Pricing Rules'!$A$5:$A$8,0)) | L23: =INDEX('Pricing Rules'!$C$5:$C$8,MATCH(I23,'Pricing Rules'!$A$5:$A$8,0)) | M23: =IF(OR(F23="Live",F23="Live (client-built)"),"Yes",IF(F23="Partial","Yes, with limits","No")) | N23: Ask which customers owe more than 30 days and get the answer with the records behind it. | O23: Model/API usage not metered or priced; set allowance in Pricing Rules.
A24: M020 | B24: Platform Foundation | C24: Jev Decision Node (AI advisory in workflows) | D24: An AI advice step inside a workflow under seven safety constraints. | E24: Workflow node verity.decision.ask; needs egress capability and API key | F24: Built, not live-verified | G24: None | H24: platform/decision.ts | I24: L | J24: M005, M019 | K24: =INDEX('Pricing Rules'!$B$5:$B$8,MATCH(I24,'Pricing Rules'!$A$5:$A$8,0)) | L24: =INDEX('Pricing Rules'!$C$5:$C$8,MATCH(I24,'Pricing Rules'!$A$5:$A$8,0)) | M24: =IF(OR(F24="Live",F24="Live (client-built)"),"Yes",IF(F24="Partial","Yes, with limits","No")) | N24: AI recommends, a human decides, everything is logged. | O24: Unit-proven only. Needs migration, key, one real call (Task 119). Do not sell yet.
A25: M021 | B25: Platform Foundation | C25: Reports & MIS | D25: Standard sales, purchase, inventory and finance reports. | E25: Report hub; sales, purchases, inventory, finance reports; date-range filters | F25: Live | G25: Shree Ganesh, Kent's | H25: src/app/(shell)/reports | I25: M | K25: =INDEX('Pricing Rules'!$B$5:$B$8,MATCH(I25,'Pricing Rules'!$A$5:$A$8,0)) | L25: =INDEX('Pricing Rules'!$C$5:$C$8,MATCH(I25,'Pricing Rules'!$A$5:$A$8,0)) | M25: =IF(OR(F25="Live",F25="Live (client-built)"),"Yes",IF(F25="Partial","Yes, with limits","No")) | N25: The reports owners ask for every Monday, already built. | O25: UI: /reports/*. No custom report builder (see M160).
A26: M030 | B26: Locations & Field | C26: Locations, Places & Geofences | D26: Sites, outlets and godowns with addresses and map boundaries. | E26: Location records with custom fields; place and address; geofences; user assignment | F26: Live | G26: Kent's, Shree Ganesh | H26: capabilities/location | I26: S | J26: M001 | K26: =INDEX('Pricing Rules'!$B$5:$B$8,MATCH(I26,'Pricing Rules'!$A$5:$A$8,0)) | L26: =INDEX('Pricing Rules'!$C$5:$C$8,MATCH(I26,'Pricing Rules'!$A$5:$A$8,0)) | M26: =IF(OR(F26="Live",F26="Live (client-built)"),"Yes",IF(F26="Partial","Yes, with limits","No")) | N26: Multi-site from day one: outlets, godowns, offices. | O26: 7 commands. UI: /locations, /godowns.
A27: M031 | B27: Locations & Field | C27: Assets & Equipment Register | D27: Track machines, vehicles and equipment with state and location. | E27: Asset register; state changes; relocation; no industry-specific columns | F27: Live | G27: Platform | H27: capabilities/asset | I27: S | J27: M030 | K27: =INDEX('Pricing Rules'!$B$5:$B$8,MATCH(I27,'Pricing Rules'!$A$5:$A$8,0)) | L27: =INDEX('Pricing Rules'!$C$5:$C$8,MATCH(I27,'Pricing Rules'!$A$5:$A$8,0)) | M27: =IF(OR(F27="Live",F27="Live (client-built)"),"Yes",IF(F27="Partial","Yes, with limits","No")) | N27: Know where every asset is and what condition it is in. | O27: UI: /assets.
A28: M032 | B28: Locations & Field | C28: Evidence Capture | D28: Photos, GPS and signatures that cannot be altered afterwards. | E28: Append-only evidence records; geofence-checked capture | F28: Live | G28: Platform | H28: capabilities/evidence | I28: M | J28: M030, M012 | K28: =INDEX('Pricing Rules'!$B$5:$B$8,MATCH(I28,'Pricing Rules'!$A$5:$A$8,0)) | L28: =INDEX('Pricing Rules'!$C$5:$C$8,MATCH(I28,'Pricing Rules'!$A$5:$A$8,0)) | M28: =IF(OR(F28="Live",F28="Live (client-built)"),"Yes",IF(F28="Partial","Yes, with limits","No")) | N28: Proof of delivery or inspection that stands up in a dispute. | O28: UI: /evidence.
A29: M033 | B29: Locations & Field | C29: Scheduling & Resource Booking | D29: Book people, rooms and equipment without double-booking. | E29: Resources backed by a person or asset; resource groups; availability; bookings | F29: Live | G29: Platform | H29: capabilities/scheduling | I29: M | J29: M031 | K29: =INDEX('Pricing Rules'!$B$5:$B$8,MATCH(I29,'Pricing Rules'!$A$5:$A$8,0)) | L29: =INDEX('Pricing Rules'!$C$5:$C$8,MATCH(I29,'Pricing Rules'!$A$5:$A$8,0)) | M29: =IF(OR(F29="Live",F29="Live (client-built)"),"Yes",IF(F29="Partial","Yes, with limits","No")) | N29: Crews, rooms and machines scheduled against real availability. | O29: UI: /scheduling.
A30: M040 | B30: Sales & Trading | C30: Customers & Credit | D30: Customer master with credit limits and customer-specific pricing. | E30: Customer records; credit limit and approval; customer price lists; supplier linking | F30: Live | G30: Shree Ganesh | H30: capabilities/trading | I30: S | J30: M001 | K30: =INDEX('Pricing Rules'!$B$5:$B$8,MATCH(I30,'Pricing Rules'!$A$5:$A$8,0)) | L30: =INDEX('Pricing Rules'!$C$5:$C$8,MATCH(I30,'Pricing Rules'!$A$5:$A$8,0)) | M30: =IF(OR(F30="Live",F30="Live (client-built)"),"Yes",IF(F30="Partial","Yes, with limits","No")) | N30: Know who owes you and stop shipping to those over limit. | O30: Commands: create/edit/remove_customer, set_credit_limit, approve_credit, set_customer_price. UI: /customers.
A31: M041 | B31: Sales & Trading | C31: Suppliers & Supplier Prices | D31: Supplier master with price history per item. | E31: Supplier records; supplier price sets; supplier-customer linking | F31: Live | G31: Shree Ganesh | H31: capabilities/trading | I31: S | J31: M001 | K31: =INDEX('Pricing Rules'!$B$5:$B$8,MATCH(I31,'Pricing Rules'!$A$5:$A$8,0)) | L31: =INDEX('Pricing Rules'!$C$5:$C$8,MATCH(I31,'Pricing Rules'!$A$5:$A$8,0)) | M31: =IF(OR(F31="Live",F31="Live (client-built)"),"Yes",IF(F31="Partial","Yes, with limits","No")) | N31: Compare what each supplier charged last time before you order. | O31: UI: /suppliers.
A32: M042 | B32: Sales & Trading | C32: Product Catalogue | D32: Products with brand, HSN code and tax details. | E32: Brands; products; active flags; catalogue admin | F32: Live | G32: Shree Ganesh | H32: capabilities/trading | I32: S | K32: =INDEX('Pricing Rules'!$B$5:$B$8,MATCH(I32,'Pricing Rules'!$A$5:$A$8,0)) | L32: =INDEX('Pricing Rules'!$C$5:$C$8,MATCH(I32,'Pricing Rules'!$A$5:$A$8,0)) | M32: =IF(OR(F32="Live",F32="Live (client-built)"),"Yes",IF(F32="Partial","Yes, with limits","No")) | N32: One clean catalogue behind sales, purchase and stock. | O32: UI: /catalogue. Pack-specific attributes live in packs such as plywood.
A33: M043 | B33: Sales & Trading | C33: Sales Orders | D33: Create, edit, reserve stock for and fulfil customer orders. | E33: Order lines; stock reservation; fulfilment; cancel; order timeline | F33: Live | G33: Shree Ganesh | H33: capabilities/trading | I33: M | J33: M040, M042 | K33: =INDEX('Pricing Rules'!$B$5:$B$8,MATCH(I33,'Pricing Rules'!$A$5:$A$8,0)) | L33: =INDEX('Pricing Rules'!$C$5:$C$8,MATCH(I33,'Pricing Rules'!$A$5:$A$8,0)) | M33: =IF(OR(F33="Live",F33="Live (client-built)"),"Yes",IF(F33="Partial","Yes, with limits","No")) | N33: From order to dispatch on one record. | O33: UI: /sales, /sales/[orderId]. No quotation step (see M152).
A34: M044 | B34: Sales & Trading | C34: Sales Invoicing & Notes | D34: GST invoices with series, credit notes and debit notes. | E34: Invoice series; sales invoices; invoice notes | F34: Live | G34: Shree Ganesh | H34: capabilities/trading | I34: M | J34: M043 | K34: =INDEX('Pricing Rules'!$B$5:$B$8,MATCH(I34,'Pricing Rules'!$A$5:$A$8,0)) | L34: =INDEX('Pricing Rules'!$C$5:$C$8,MATCH(I34,'Pricing Rules'!$A$5:$A$8,0)) | M34: =IF(OR(F34="Live",F34="Live (client-built)"),"Yes",IF(F34="Partial","Yes, with limits","No")) | N34: Invoices numbered and taxed correctly the first time. | O34: UI: /finance, /finance/[invoiceId].
A35: M045 | B35: Sales & Trading | C35: Payments & Receivables | D35: Record payments and allocate them against invoices. | E35: Payments; allocations; party payments; outstanding view; ledgers | F35: Live | G35: Shree Ganesh | H35: capabilities/trading | I35: M | J35: M044 | K35: =INDEX('Pricing Rules'!$B$5:$B$8,MATCH(I35,'Pricing Rules'!$A$5:$A$8,0)) | L35: =INDEX('Pricing Rules'!$C$5:$C$8,MATCH(I35,'Pricing Rules'!$A$5:$A$8,0)) | M35: =IF(OR(F35="Live",F35="Live (client-built)"),"Yes",IF(F35="Partial","Yes, with limits","No")) | N35: See at a glance who has paid and who has not. | O35: UI: /transactions, /ledgers. No online gateway (see M076).
A36: M046 | B36: Sales & Trading | C36: Purchase Orders & Goods Receipt | D36: Raise purchase orders and receive goods against them. | E36: PO create, edit, submit, cancel; goods receipt; partial receipts | F36: Live | G36: Shree Ganesh | H36: capabilities/trading | I36: M | J36: M041 | K36: =INDEX('Pricing Rules'!$B$5:$B$8,MATCH(I36,'Pricing Rules'!$A$5:$A$8,0)) | L36: =INDEX('Pricing Rules'!$C$5:$C$8,MATCH(I36,'Pricing Rules'!$A$5:$A$8,0)) | M36: =IF(OR(F36="Live",F36="Live (client-built)"),"Yes",IF(F36="Partial","Yes, with limits","No")) | N36: Know what is on order, what arrived and what is short. | O36: UI: /purchases.
A37: M047 | B37: Sales & Trading | C37: Purchase Bills & Review Queue | D37: Turn supplier bills into confirmed purchase entries. | E37: Purchase invoice; bill from order; confirmation queue | F37: Live | G37: Shree Ganesh | H37: capabilities/trading | I37: M | J37: M046 | K37: =INDEX('Pricing Rules'!$B$5:$B$8,MATCH(I37,'Pricing Rules'!$A$5:$A$8,0)) | L37: =INDEX('Pricing Rules'!$C$5:$C$8,MATCH(I37,'Pricing Rules'!$A$5:$A$8,0)) | M37: =IF(OR(F37="Live",F37="Live (client-built)"),"Yes",IF(F37="Partial","Yes, with limits","No")) | N37: Supplier bills checked against what was actually received. | O37: Commands: raise_purchase_invoice, raise_purchase_bill_from_order, confirm_purchase_bill.
A38: M048 | B38: Sales & Trading | C38: Stock Ledger & Godowns | D38: Every stock movement recorded, by godown and rack. | E38: Receive, issue, transfer, adjust, damage, return; racks; balances; reservations | F38: Live | G38: Shree Ganesh | H38: capabilities/trading | I38: L | J38: M042, M030 | K38: =INDEX('Pricing Rules'!$B$5:$B$8,MATCH(I38,'Pricing Rules'!$A$5:$A$8,0)) | L38: =INDEX('Pricing Rules'!$C$5:$C$8,MATCH(I38,'Pricing Rules'!$A$5:$A$8,0)) | M38: =IF(OR(F38="Live",F38="Live (client-built)"),"Yes",IF(F38="Partial","Yes, with limits","No")) | N38: Stock you can trust because every unit has a history. | O38: UI: /stock, /godowns. Append-only ledger.
A39: M049 | B39: Sales & Trading | C39: Price Sheets & Customer Pricing | D39: Different prices for different customers and periods. | E39: Price sheets; customer overrides; supplier price sets | F39: Live | G39: Shree Ganesh | H39: capabilities/trading | I39: S | J39: M040 | K39: =INDEX('Pricing Rules'!$B$5:$B$8,MATCH(I39,'Pricing Rules'!$A$5:$A$8,0)) | L39: =INDEX('Pricing Rules'!$C$5:$C$8,MATCH(I39,'Pricing Rules'!$A$5:$A$8,0)) | M39: =IF(OR(F39="Live",F39="Live (client-built)"),"Yes",IF(F39="Partial","Yes, with limits","No")) | N39: Quote consistently, protect margin. | O39: UI: /prices.
A40: M050 | B40: Sales & Trading | C40: GST Compliance Workspace | D40: Prepare GSTR-1 and GSTR-3B, track input tax credit, reconcile with the portal. | E40: Tax rule sets; GSTR-1, GSTR-3B; ITC; portal record import; exceptions; period close | F40: Live | G40: Shree Ganesh | H40: capabilities/trading (tax, itc, period) | I40: L | J40: M044, M047 | K40: =INDEX('Pricing Rules'!$B$5:$B$8,MATCH(I40,'Pricing Rules'!$A$5:$A$8,0)) | L40: =INDEX('Pricing Rules'!$C$5:$C$8,MATCH(I40,'Pricing Rules'!$A$5:$A$8,0)) | M40: =IF(OR(F40="Live",F40="Live (client-built)"),"Yes",IF(F40="Partial","Yes, with limits","No")) | N40: Return preparation without exporting to Excel. Preparation only, Verity does not file. | O40: UI: /tax/*. Website copy rule forbids the phrase GST filing.
A41: M051 | B41: Sales & Trading | C41: Accounting Periods & Ledgers | D41: Close months, lock them, reopen with a record. | E41: Accounting periods; ledger entries; party ledgers | F41: Live | G41: Shree Ganesh | H41: capabilities/trading | I41: M | J41: M045 | K41: =INDEX('Pricing Rules'!$B$5:$B$8,MATCH(I41,'Pricing Rules'!$A$5:$A$8,0)) | L41: =INDEX('Pricing Rules'!$C$5:$C$8,MATCH(I41,'Pricing Rules'!$A$5:$A$8,0)) | M41: =IF(OR(F41="Live",F41="Live (client-built)"),"Yes",IF(F41="Partial","Yes, with limits","No")) | N41: Closed months stay closed. | O41: Commands: close_period, reopen_period.
A42: M052 | B42: Sales & Trading | C42: Business Profile & GST Registrations | D42: Company identity and multiple GST registrations. | E42: Business profile; GST registrations; setup checklist | F42: Live | G42: Shree Ganesh | H42: capabilities/trading | I42: S | J42: M001 | K42: =INDEX('Pricing Rules'!$B$5:$B$8,MATCH(I42,'Pricing Rules'!$A$5:$A$8,0)) | L42: =INDEX('Pricing Rules'!$C$5:$C$8,MATCH(I42,'Pricing Rules'!$A$5:$A$8,0)) | M42: =IF(OR(F42="Live",F42="Live (client-built)"),"Yes",IF(F42="Partial","Yes, with limits","No")) | N42: Multi-state businesses handled properly. | O42: UI: /settings/business, /settings/tax.
A43: M053 | B43: Sales & Trading | C43: Plywood Vertical Pack | D43: Board dimensions, grades, shades and textures on top of trading. | E43: Plywood product detail; shade and texture taxonomies | F43: Live (client-built) | G43: Shree Ganesh | H43: capabilities/plywood | I43: M | J43: M042 | K43: =INDEX('Pricing Rules'!$B$5:$B$8,MATCH(I43,'Pricing Rules'!$A$5:$A$8,0)) | L43: =INDEX('Pricing Rules'!$C$5:$C$8,MATCH(I43,'Pricing Rules'!$A$5:$A$8,0)) | M43: =IF(OR(F43="Live",F43="Live (client-built)"),"Yes",IF(F43="Partial","Yes, with limits","No")) | N43: A catalogue that speaks plywood, not generic goods. | O43: Depends on trading. Template for other trading packs.
A44: M054 | B44: Sales & Trading | C44: Trading Analytics | D44: Top customers, top items, weekly totals, unbilled movements. | E44: Sales analysis; top customers and items; weekly totals; activity feed | F44: Live | G44: Shree Ganesh | H44: capabilities/trading | I44: S | J44: M043 | K44: =INDEX('Pricing Rules'!$B$5:$B$8,MATCH(I44,'Pricing Rules'!$A$5:$A$8,0)) | L44: =INDEX('Pricing Rules'!$C$5:$C$8,MATCH(I44,'Pricing Rules'!$A$5:$A$8,0)) | M44: =IF(OR(F44="Live",F44="Live (client-built)"),"Yes",IF(F44="Partial","Yes, with limits","No")) | N44: The numbers a distributor checks every morning. | O44: Queries: trading.sales_analysis, top_customers, top_items, weekly_*_totals.
A45: M060 | B45: Inventory & Procurement | C45: Inventory Items & Groups | D45: Items and categories for operating stock. | E45: Item groups; items; active flags | F45: Live | G45: Kent's | H45: capabilities/inventory | I45: S | K45: =INDEX('Pricing Rules'!$B$5:$B$8,MATCH(I45,'Pricing Rules'!$A$5:$A$8,0)) | L45: =INDEX('Pricing Rules'!$C$5:$C$8,MATCH(I45,'Pricing Rules'!$A$5:$A$8,0)) | M45: =IF(OR(F45="Live",F45="Live (client-built)"),"Yes",IF(F45="Partial","Yes, with limits","No")) | N45: Ingredients, consumables and spares tracked by item. | O45: UI: /inventory.
A46: M061 | B46: Inventory & Procurement | C46: Stock Movements, Wastage & Counts | D46: Record movements, waste and physical stock counts. | E46: Movements; wastage; stock count apply | F46: Live | G46: Kent's | H46: capabilities/inventory | I46: M | J46: M060 | K46: =INDEX('Pricing Rules'!$B$5:$B$8,MATCH(I46,'Pricing Rules'!$A$5:$A$8,0)) | L46: =INDEX('Pricing Rules'!$C$5:$C$8,MATCH(I46,'Pricing Rules'!$A$5:$A$8,0)) | M46: =IF(OR(F46="Live",F46="Live (client-built)"),"Yes",IF(F46="Partial","Yes, with limits","No")) | N46: Close the gap between bought, used and thrown away. | O46: Commands: record_stock_movement, record_wastage, apply_stock_count.
A47: M062 | B47: Inventory & Procurement | C47: Vendors, POs & Vendor Payments | D47: Vendor-side purchasing for operating stock. | E47: Vendors; POs with approval; receipts; vendor payments | F47: Live | G47: Kent's | H47: capabilities/inventory | I47: M | J47: M060, M006 | K47: =INDEX('Pricing Rules'!$B$5:$B$8,MATCH(I47,'Pricing Rules'!$A$5:$A$8,0)) | L47: =INDEX('Pricing Rules'!$C$5:$C$8,MATCH(I47,'Pricing Rules'!$A$5:$A$8,0)) | M47: =IF(OR(F47="Live",F47="Live (client-built)"),"Yes",IF(F47="Partial","Yes, with limits","No")) | N47: Purchasing with an approval step before money leaves. | O47: UI: /inventory/purchase-orders.
A48: M063 | B48: Inventory & Procurement | C48: Stock Requests & Low-stock Reorder | D48: Outlets request stock; low stock drafts the purchase order. | E48: Stock request and decision; transfer; draft PO from low stock | F48: Live | G48: Kent's | H48: capabilities/inventory | I48: M | J48: M060, M030 | K48: =INDEX('Pricing Rules'!$B$5:$B$8,MATCH(I48,'Pricing Rules'!$A$5:$A$8,0)) | L48: =INDEX('Pricing Rules'!$C$5:$C$8,MATCH(I48,'Pricing Rules'!$A$5:$A$8,0)) | M48: =IF(OR(F48="Live",F48="Live (client-built)"),"Yes",IF(F48="Partial","Yes, with limits","No")) | N48: Reordering stops depending on memory. | O48: Commands: request_stock, decide_stock_request, transfer_stock, draft_order_from_low_stock.
A49: M070 | B49: Finance & Accounting | C49: Chart of Accounts & Journals | D49: Basic double-entry books with reversible journals. | E49: Accounts; post and reverse journal entries | F49: Partial | G49: None live | H49: capabilities/accounting | I49: M | K49: =INDEX('Pricing Rules'!$B$5:$B$8,MATCH(I49,'Pricing Rules'!$A$5:$A$8,0)) | L49: =INDEX('Pricing Rules'!$C$5:$C$8,MATCH(I49,'Pricing Rules'!$A$5:$A$8,0)) | M49: =IF(OR(F49="Live",F49="Live (client-built)"),"Yes",IF(F49="Partial","Yes, with limits","No")) | N49: Internal books inside the same system. | O49: MVP. No trial balance, balance sheet, P&L statements or bank reconciliation. UI: /accounting.
A50: M071 | B50: Finance & Accounting | C50: Expense Management | D50: Record expenses and approve them. | E50: Expense records; approve or reject; categories | F50: Live | G50: Colonel Kebabz | H50: capabilities/finance | I50: S | J50: M006 | K50: =INDEX('Pricing Rules'!$B$5:$B$8,MATCH(I50,'Pricing Rules'!$A$5:$A$8,0)) | L50: =INDEX('Pricing Rules'!$C$5:$C$8,MATCH(I50,'Pricing Rules'!$A$5:$A$8,0)) | M50: =IF(OR(F50="Live",F50="Live (client-built)"),"Yes",IF(F50="Partial","Yes, with limits","No")) | N50: Spend visible and approved, not discovered at month end. | O50: UI: /expenses.
A51: M072 | B51: Finance & Accounting | C51: Daily Cash Reconciliation | D51: Count the till at close and record variance. | E51: Daily cash reconciliation per outlet | F51: Live | G51: Colonel Kebabz | H51: capabilities/finance | I51: S | J51: M030 | K51: =INDEX('Pricing Rules'!$B$5:$B$8,MATCH(I51,'Pricing Rules'!$A$5:$A$8,0)) | L51: =INDEX('Pricing Rules'!$C$5:$C$8,MATCH(I51,'Pricing Rules'!$A$5:$A$8,0)) | M51: =IF(OR(F51="Live",F51="Live (client-built)"),"Yes",IF(F51="Partial","Yes, with limits","No")) | N51: Cash differences caught the same day. | O51: UI: /cash-reconciliation.
A52: M073 | B52: Finance & Accounting | C52: Outlet P&L | D52: Profit by outlet from sales, cost and expenses. | E52: Outlet P&L; sales summary by payment method | F52: Live | G52: Colonel Kebabz | H52: capabilities/finance, dinein | I52: M | J52: M071, M090 | K52: =INDEX('Pricing Rules'!$B$5:$B$8,MATCH(I52,'Pricing Rules'!$A$5:$A$8,0)) | L52: =INDEX('Pricing Rules'!$C$5:$C$8,MATCH(I52,'Pricing Rules'!$A$5:$A$8,0)) | M52: =IF(OR(F52="Live",F52="Live (client-built)"),"Yes",IF(F52="Partial","Yes, with limits","No")) | N52: Which outlet actually makes money. | O52: UI: /outlet-pnl.
A53: M074 | B53: Finance & Accounting | C53: Metered & Recurring Billing | D53: Bill by meter reading or billing period. | E53: Meters; readings; rates; billing periods; invoice generation | F53: Live | G53: None live | H53: capabilities/billing | I53: M | K53: =INDEX('Pricing Rules'!$B$5:$B$8,MATCH(I53,'Pricing Rules'!$A$5:$A$8,0)) | L53: =INDEX('Pricing Rules'!$C$5:$C$8,MATCH(I53,'Pricing Rules'!$A$5:$A$8,0)) | M53: =IF(OR(F53="Live",F53="Live (client-built)"),"Yes",IF(F53="Partial","Yes, with limits","No")) | N53: Utility, rental and usage-based billing. | O53: MVP. UI: /billing.
A54: M075 | B54: Finance & Accounting | C54: External Accounting Sync (Tally, Zoho, QuickBooks) | D54: Push or sync to the client's accounting software. | E54: Not built | F54: Planned | G54: None | H54: verity-spec/10_integrations/accounting.md (stub) | I54: L | J54: M070 | K54: =INDEX('Pricing Rules'!$B$5:$B$8,MATCH(I54,'Pricing Rules'!$A$5:$A$8,0)) | L54: =INDEX('Pricing Rules'!$C$5:$C$8,MATCH(I54,'Pricing Rules'!$A$5:$A$8,0)) | M54: =IF(OR(F54="Live",F54="Live (client-built)"),"Yes",IF(F54="Partial","Yes, with limits","No")) | N54: Sold today only as a quoted integration project. | O54: No connector exists. Do not promise a named product.
A55: M076 | B55: Finance & Accounting | C55: Payment Gateway & UPI Collection | D55: Collect payment online against an invoice. | E55: Not built | F55: Planned | G55: None | H55: verity-spec/10_integrations/payments.md (stub) | I55: L | J55: M045 | K55: =INDEX('Pricing Rules'!$B$5:$B$8,MATCH(I55,'Pricing Rules'!$A$5:$A$8,0)) | L55: =INDEX('Pricing Rules'!$C$5:$C$8,MATCH(I55,'Pricing Rules'!$A$5:$A$8,0)) | M55: =IF(OR(F55="Live",F55="Live (client-built)"),"Yes",IF(F55="Partial","Yes, with limits","No")) | N55: Pay link on the invoice. | O55: No gateway integration exists.
A56: M080 | B56: People & Workforce | C56: Employee Directory & Departments | D56: Employees, departments and active status. | E56: Employees on top of Party; departments; compensation record | F56: Live | G56: Platform | H56: capabilities/hr | I56: S | J56: M001 | K56: =INDEX('Pricing Rules'!$B$5:$B$8,MATCH(I56,'Pricing Rules'!$A$5:$A$8,0)) | L56: =INDEX('Pricing Rules'!$C$5:$C$8,MATCH(I56,'Pricing Rules'!$A$5:$A$8,0)) | M56: =IF(OR(F56="Live",F56="Live (client-built)"),"Yes",IF(F56="Partial","Yes, with limits","No")) | N56: One staff record used by every module. | O56: UI: /hr, /hr/[employeeId].
A57: M081 | B57: People & Workforce | C57: Leave Management | D57: Leave types, applications and approval decisions. | E57: Leave types; apply; decide; balances | F57: Live | G57: Platform | H57: capabilities/hr | I57: S | J57: M080, M006 | K57: =INDEX('Pricing Rules'!$B$5:$B$8,MATCH(I57,'Pricing Rules'!$A$5:$A$8,0)) | L57: =INDEX('Pricing Rules'!$C$5:$C$8,MATCH(I57,'Pricing Rules'!$A$5:$A$8,0)) | M57: =IF(OR(F57="Live",F57="Live (client-built)"),"Yes",IF(F57="Partial","Yes, with limits","No")) | N57: Leave approved in the system, not on WhatsApp. | O57: Commands: create_leave_type, apply_for_leave, decide_leave_application.
A58: M082 | B58: People & Workforce | C58: Attendance & Shifts | D58: Define shifts and record attendance. | E58: Shift definitions; attendance records | F58: Live | G58: Colonel Kebabz | H58: capabilities/attendance | I58: M | J58: M080 | K58: =INDEX('Pricing Rules'!$B$5:$B$8,MATCH(I58,'Pricing Rules'!$A$5:$A$8,0)) | L58: =INDEX('Pricing Rules'!$C$5:$C$8,MATCH(I58,'Pricing Rules'!$A$5:$A$8,0)) | M58: =IF(OR(F58="Live",F58="Live (client-built)"),"Yes",IF(F58="Partial","Yes, with limits","No")) | N58: Who worked when, for payroll and rostering. | O58: UI: /attendance.
A59: M083 | B59: People & Workforce | C59: Payroll Inputs | D59: Hours and days worked ready for the payroll run. | E59: Computed from attendance at query time | F59: Partial | G59: Colonel Kebabz | H59: capabilities/attendance | I59: S | J59: M082 | K59: =INDEX('Pricing Rules'!$B$5:$B$8,MATCH(I59,'Pricing Rules'!$A$5:$A$8,0)) | L59: =INDEX('Pricing Rules'!$C$5:$C$8,MATCH(I59,'Pricing Rules'!$A$5:$A$8,0)) | M59: =IF(OR(F59="Live",F59="Live (client-built)"),"Yes",IF(F59="Partial","Yes, with limits","No")) | N59: Feed your payroll provider clean numbers. | O59: Inputs only. No payslips.
A60: M084 | B60: People & Workforce | C60: Payroll Processing & Statutory (PF, ESI, TDS) | D60: Full payroll with statutory compliance. | E60: Not built | F60: Planned | G60: None | H60: taskplans/79 (no Indian statutory spec yet) | I60: XL | J60: M083 | K60: =INDEX('Pricing Rules'!$B$5:$B$8,MATCH(I60,'Pricing Rules'!$A$5:$A$8,0)) | L60: =INDEX('Pricing Rules'!$C$5:$C$8,MATCH(I60,'Pricing Rules'!$A$5:$A$8,0)) | M60: =IF(OR(F60="Live",F60="Live (client-built)"),"Yes",IF(F60="Partial","Yes, with limits","No")) | N60: Do not sell. Research needed first. | O60: Blocked on statutory research (Task 79).
A61: M090 | B61: Food & Hospitality | C61: Dine-in Floor & Tables | D61: Zones, tables and live floor view. | E61: Zones; tables; positioning; move and merge tables | F61: Live (client-built) | G61: Kent's Restaurant | H61: capabilities/dinein | I61: M | J61: M030 | K61: =INDEX('Pricing Rules'!$B$5:$B$8,MATCH(I61,'Pricing Rules'!$A$5:$A$8,0)) | L61: =INDEX('Pricing Rules'!$C$5:$C$8,MATCH(I61,'Pricing Rules'!$A$5:$A$8,0)) | M61: =IF(OR(F61="Live",F61="Live (client-built)"),"Yes",IF(F61="Partial","Yes, with limits","No")) | N61: See which tables are free, seated or waiting for the bill. | O61: UI: /floor, /floor/setup. Website rule: say counter billing, not point of sale.
A62: M091 | B62: Food & Hospitality | C62: Menu Management | D62: Categories, items and variants with availability. | E62: Menu categories; items; variants; active toggle | F62: Live (client-built) | G62: Kent's Restaurant | H62: capabilities/dinein | I62: S | K62: =INDEX('Pricing Rules'!$B$5:$B$8,MATCH(I62,'Pricing Rules'!$A$5:$A$8,0)) | L62: =INDEX('Pricing Rules'!$C$5:$C$8,MATCH(I62,'Pricing Rules'!$A$5:$A$8,0)) | M62: =IF(OR(F62="Live",F62="Live (client-built)"),"Yes",IF(F62="Partial","Yes, with limits","No")) | N62: Mark an item unavailable and it disappears from ordering. | O62: UI: /menu.
A63: M092 | B63: Food & Hospitality | C63: Orders, KOT & Kitchen Display | D63: Waiter orders flow to the kitchen and back. | E63: Create and place orders; add lines; advance line status; void; kitchen screen | F63: Live (client-built) | G63: Kent's Restaurant | H63: capabilities/dinein | I63: M | J63: M090, M091 | K63: =INDEX('Pricing Rules'!$B$5:$B$8,MATCH(I63,'Pricing Rules'!$A$5:$A$8,0)) | L63: =INDEX('Pricing Rules'!$C$5:$C$8,MATCH(I63,'Pricing Rules'!$A$5:$A$8,0)) | M63: =IF(OR(F63="Live",F63="Live (client-built)"),"Yes",IF(F63="Partial","Yes, with limits","No")) | N63: Fewer shouted orders and lost tickets. | O63: UI: /kitchen, /floor/[orderId].
A64: M093 | B64: Food & Hospitality | C64: Counter Billing & Settlement | D64: Generate bills, discounts, payments and refunds. | E64: Bill generation; discounts; payments; settle; refund; counter history | F64: Live (client-built) | G64: Kent's Restaurant | H64: capabilities/dinein | I64: M | J64: M092 | K64: =INDEX('Pricing Rules'!$B$5:$B$8,MATCH(I64,'Pricing Rules'!$A$5:$A$8,0)) | L64: =INDEX('Pricing Rules'!$C$5:$C$8,MATCH(I64,'Pricing Rules'!$A$5:$A$8,0)) | M64: =IF(OR(F64="Live",F64="Live (client-built)"),"Yes",IF(F64="Partial","Yes, with limits","No")) | N64: Bills settled with payment method breakdown. | O64: UI: /counter, /counter/history.
A65: M094 | B65: Food & Hospitality | C65: Recipes & Food Cost | D65: Recipes link menu items to ingredients and cost. | E65: Recipe with ingredients; consumption posting on bill; food cost | F65: Live (client-built) | G65: Colonel Kebabz | H65: capabilities/recipe | I65: M | J65: M060, M091 | K65: =INDEX('Pricing Rules'!$B$5:$B$8,MATCH(I65,'Pricing Rules'!$A$5:$A$8,0)) | L65: =INDEX('Pricing Rules'!$C$5:$C$8,MATCH(I65,'Pricing Rules'!$A$5:$A$8,0)) | M65: =IF(OR(F65="Live",F65="Live (client-built)"),"Yes",IF(F65="Partial","Yes, with limits","No")) | N65: Know what each dish really costs. | O65: UI: /recipes.
A66: M095 | B66: Food & Hospitality | C66: Guest CRM & Customer 360 | D66: Guests matched by phone with spend and visit history. | E66: Customer upsert on bill; 360 view; segments | F66: Live (client-built) | G66: Colonel Kebabz | H66: capabilities/crm | I66: S | J66: M093 | K66: =INDEX('Pricing Rules'!$B$5:$B$8,MATCH(I66,'Pricing Rules'!$A$5:$A$8,0)) | L66: =INDEX('Pricing Rules'!$C$5:$C$8,MATCH(I66,'Pricing Rules'!$A$5:$A$8,0)) | M66: =IF(OR(F66="Live",F66="Live (client-built)"),"Yes",IF(F66="Partial","Yes, with limits","No")) | N66: Recognise regulars and bring back lapsed ones. | O66: UI: /guests, /customers. Lean V1, no campaigns.
A67: M096 | B67: Food & Hospitality | C67: Loyalty Points | D67: Earn points on spend and redeem them. | E67: Points earned on settle; redeem | F67: Live (client-built) | G67: Colonel Kebabz | H67: capabilities/loyalty | I67: S | J67: M095 | K67: =INDEX('Pricing Rules'!$B$5:$B$8,MATCH(I67,'Pricing Rules'!$A$5:$A$8,0)) | L67: =INDEX('Pricing Rules'!$C$5:$C$8,MATCH(I67,'Pricing Rules'!$A$5:$A$8,0)) | M67: =IF(OR(F67="Live",F67="Live (client-built)"),"Yes",IF(F67="Partial","Yes, with limits","No")) | N67: Reward repeat visits automatically. | O67: Points only. No tiers or reward catalogue.
A68: M097 | B68: Food & Hospitality | C68: Coupons & Offers | D68: Percent or flat discount codes. | E68: Create coupon; apply on bill | F68: Live (client-built) | G68: Colonel Kebabz | H68: capabilities/coupon | I68: S | J68: M093 | K68: =INDEX('Pricing Rules'!$B$5:$B$8,MATCH(I68,'Pricing Rules'!$A$5:$A$8,0)) | L68: =INDEX('Pricing Rules'!$C$5:$C$8,MATCH(I68,'Pricing Rules'!$A$5:$A$8,0)) | M68: =IF(OR(F68="Live",F68="Live (client-built)"),"Yes",IF(F68="Partial","Yes, with limits","No")) | N68: Run offers with a code and see usage. | O68: UI: /coupons. No buy-X-get-Y or time-scoped offers.
A69: M098 | B69: Food & Hospitality | C69: Complaints & Service Recovery | D69: Every complaint becomes a ticket with a status and owner. | E69: File, update status, resolve | F69: Live (client-built) | G69: Colonel Kebabz | H69: capabilities/complaint | I69: S | J69: M095 | K69: =INDEX('Pricing Rules'!$B$5:$B$8,MATCH(I69,'Pricing Rules'!$A$5:$A$8,0)) | L69: =INDEX('Pricing Rules'!$C$5:$C$8,MATCH(I69,'Pricing Rules'!$A$5:$A$8,0)) | M69: =IF(OR(F69="Live",F69="Live (client-built)"),"Yes",IF(F69="Partial","Yes, with limits","No")) | N69: No complaint gets lost in a chat. | O69: UI: /complaints.
A70: M100 | B70: Manufacturing | C70: Bill of Materials | D70: Define what goes into a product. | E70: BOM create; active flag; create order from BOM | F70: Live | G70: Manufacturing pilot | H70: capabilities/manufacturing | I70: M | J70: M060 | K70: =INDEX('Pricing Rules'!$B$5:$B$8,MATCH(I70,'Pricing Rules'!$A$5:$A$8,0)) | L70: =INDEX('Pricing Rules'!$C$5:$C$8,MATCH(I70,'Pricing Rules'!$A$5:$A$8,0)) | M70: =IF(OR(F70="Live",F70="Live (client-built)"),"Yes",IF(F70="Partial","Yes, with limits","No")) | N70: One source for what each product needs. | O70: UI: /manufacturing/boms. Multi-level and revisions not confirmed.
A71: M101 | B71: Manufacturing | C71: Routes & Operation Planning | D71: Define stages and plan operations per order. | E71: Routes and stages; plan operations | F71: Live | G71: Manufacturing pilot | H71: capabilities/manufacturing | I71: M | J71: M100 | K71: =INDEX('Pricing Rules'!$B$5:$B$8,MATCH(I71,'Pricing Rules'!$A$5:$A$8,0)) | L71: =INDEX('Pricing Rules'!$C$5:$C$8,MATCH(I71,'Pricing Rules'!$A$5:$A$8,0)) | M71: =IF(OR(F71="Live",F71="Live (client-built)"),"Yes",IF(F71="Partial","Yes, with limits","No")) | N71: Each order gets its path through the factory. | O71: UI: /manufacturing/routes.
A72: M102 | B72: Manufacturing | C72: Production Orders | D72: Create, start, complete and cancel production orders. | E72: Orders and lines; start; complete; cancel | F72: Live | G72: Manufacturing pilot | H72: capabilities/manufacturing | I72: M | J72: M100 | K72: =INDEX('Pricing Rules'!$B$5:$B$8,MATCH(I72,'Pricing Rules'!$A$5:$A$8,0)) | L72: =INDEX('Pricing Rules'!$C$5:$C$8,MATCH(I72,'Pricing Rules'!$A$5:$A$8,0)) | M72: =IF(OR(F72="Live",F72="Live (client-built)"),"Yes",IF(F72="Partial","Yes, with limits","No")) | N72: See every order, where it is and what blocks it. | O72: UI: /manufacturing.
A73: M103 | B73: Manufacturing | C73: Shop-floor Console | D73: Operators start, hold, resume and complete operations. | E73: Operation start, hold, resume, complete; floor view | F73: Live | G73: Manufacturing pilot | H73: capabilities/manufacturing | I73: M | J73: M101 | K73: =INDEX('Pricing Rules'!$B$5:$B$8,MATCH(I73,'Pricing Rules'!$A$5:$A$8,0)) | L73: =INDEX('Pricing Rules'!$C$5:$C$8,MATCH(I73,'Pricing Rules'!$A$5:$A$8,0)) | M73: =IF(OR(F73="Live",F73="Live (client-built)"),"Yes",IF(F73="Partial","Yes, with limits","No")) | N73: The floor reports progress as it happens. | O73: UI: /manufacturing/floor.
A74: M104 | B74: Manufacturing | C74: Batches & Lot Tracking | D74: Group production into traceable batches. | E74: Create and dissolve batches; reserve batch | F74: Live | G74: Manufacturing pilot | H74: capabilities/manufacturing | I74: M | J74: M102 | K74: =INDEX('Pricing Rules'!$B$5:$B$8,MATCH(I74,'Pricing Rules'!$A$5:$A$8,0)) | L74: =INDEX('Pricing Rules'!$C$5:$C$8,MATCH(I74,'Pricing Rules'!$A$5:$A$8,0)) | M74: =IF(OR(F74="Live",F74="Live (client-built)"),"Yes",IF(F74="Partial","Yes, with limits","No")) | N74: Know exactly which batch went to which customer. | O74: UI: /manufacturing/batches.
... A79: M109 | B79: Manufacturing | C79: Advanced QC (templates, inspections, NCR/CAPA) | D79: Configurable inspections with corrective action. | E79: Not built | F79: Planned | G79: None | H79: taskplans/118 (waits on design partner) | I79: XL | J79: M105 | K79: =INDEX('Pricing Rules'!$B$5:$B$8,MATCH(I79,'Pricing Rules'!$A$5:$A$8,0)) | L79: =INDEX('Pricing Rules'!$C$5:$C$8,MATCH(I79,'Pricing Rules'!$A$5:$A$8,0)) | M79: =IF(OR(F79="Live",F79="Live (client-built)"),"Yes",IF(F79="Partial","Yes, with limits","No")) | N79: Manufacturing Plus scope only after build. | O79: Wider build waits for a named design partner.
A80: M110 | B80: Manufacturing | C80: Material Requirements Planning | D80: Plan purchases from forecast and BOM. | E80: Not built | F80: Planned | G80: None | H80: taskplans/118 | I80: XL | J80: M100 | K80: =INDEX('Pricing Rules'!$B$5:$B$8,MATCH(I80,'Pricing Rules'!$A$5:$A$8,0)) | L80: =INDEX('Pricing Rules'!$C$5:$C$8,MATCH(I80,'Pricing Rules'!$A$5:$A$8,0)) | M80: =IF(OR(F80="Live",F80="Live (client-built)"),"Yes",IF(F80="Partial","Yes, with limits","No")) | N80: Do not sell yet.
A81: M111 | B81: Manufacturing | C81: Subcontracting / Job Work | D81: Send material out for processing and receive it back. | E81: Not built | F81: Planned | G81: None | H81: taskplans/118 | I81: L | J81: M102 | K81: =INDEX('Pricing Rules'!$B$5:$B$8,MATCH(I81,'Pricing Rules'!$A$5:$A$8,0)) | L81: =INDEX('Pricing Rules'!$C$5:$C$8,MATCH(I81,'Pricing Rules'!$A$5:$A$8,0)) | M81: =IF(OR(F81="Live",F81="Live (client-built)"),"Yes",IF(F81="Partial","Yes, with limits","No"))
A82: M112 | B82: Manufacturing | C82: Maintenance Management | D82: Preventive maintenance for machines. | E82: Spec stub only | F82: Planned | G82: None | H82: verity-spec/13_industry_packs/maintenance.md | I82: L | J82: M031 | K82: =INDEX('Pricing Rules'!$B$5:$B$8,MATCH(I82,'Pricing Rules'!$A$5:$A$8,0)) | L82: =INDEX('Pricing Rules'!$C$5:$C$8,MATCH(I82,'Pricing Rules'!$A$5:$A$8,0)) | M82: =IF(OR(F82="Live",F82="Live (client-built)"),"Yes",IF(F82="Partial","Yes, with limits","No"))
A83: M120 | B83: Sales Operations (OMS) | C83: Lead Pipeline & Qualification | D83: Leads move through stages with qualification, health and reactivation. | E83: Create lead; advance stage; update qualification; reactivate; derived lead health | F83: Live (client-built) | G83: PlotArmour outreach | H83: capabilities/outreach | I83: M | J83: M001 | K83: =INDEX('Pricing Rules'!$B$5:$B$8,MATCH(I83,'Pricing Rules'!$A$5:$A$8,0)) | L83: =INDEX('Pricing Rules'!$C$5:$C$8,MATCH(I83,'Pricing Rules'!$A$5:$A$8,0)) | M83: =IF(OR(F83="Live",F83="Live (client-built)"),"Yes",IF(F83="Partial","Yes, with limits","No")) | N83: A pipeline with discipline: stage, owner, next action. | O83: UI: /outreach, /outreach/prospects. 37 commands in this capability.
A84: M121 | B84: Sales Operations (OMS) | C84: Contacts & Duplicate Detection | D84: Contact records linked to leads, duplicates caught. | E84: Create contact; duplicate detection | F84: Live (client-built) | G84: PlotArmour outreach | H84: capabilities/outreach | I84: S | J84: M120 | K84: =INDEX('Pricing Rules'!$B$5:$B$8,MATCH(I84,'Pricing Rules'!$A$5:$A$8,0)) | L84: =INDEX('Pricing Rules'!$C$5:$C$8,MATCH(I84,'Pricing Rules'!$A$5:$A$8,0)) | M84: =IF(OR(F84="Live",F84="Live (client-built)"),"Yes",IF(F84="Partial","Yes, with limits","No")) | N84: Nobody pitches the same person twice.
A85: M122 | B85: Sales Operations (OMS) | C85: Activity Logging | D85: Calls, messages and meetings logged against a lead. | E85: Log activity; attribution record | F85: Live (client-built) | G85: PlotArmour outreach | H85: capabilities/outreach | I85: S | J85: M120 | K85: =INDEX('Pricing Rules'!$B$5:$B$8,MATCH(I85,'Pricing Rules'!$A$5:$A$8,0)) | L85: =INDEX('Pricing Rules'!$C$5:$C$8,MATCH(I85,'Pricing Rules'!$A$5:$A$8,0)) | M85: =IF(OR(F85="Live",F85="Live (client-built)"),"Yes",IF(F85="Partial","Yes, with limits","No")) | N85: Activity you can count and coach on.
A86: M123 | B86: Sales Operations (OMS) | C86: Tasks & Meetings | D86: Follow-up tasks and meeting outcomes. | E86: Create task and status; create meeting and outcome | F86: Live (client-built) | G86: PlotArmour outreach | H86: capabilities/outreach | I86: S | J86: M120 | K86: =INDEX('Pricing Rules'!$B$5:$B$8,MATCH(I86,'Pricing Rules'!$A$5:$A$8,0)) | L86: =INDEX('Pricing Rules'!$C$5:$C$8,MATCH(I86,'Pricing Rules'!$A$5:$A$8,0)) | M86: =IF(OR(F86="Live",F86="Live (client-built)"),"Yes",IF(F86="Partial","Yes, with limits","No")) | N86: No follow-up forgotten.
A87: M124 | B87: Sales Operations (OMS) | C87: Team Hierarchy & Assignments | D87: Teams, leaders, co-leaders, members and domain assignments. | E87: Create and rename team; leader and co-leader; members; assignments | F87: Live (client-built) | G87: PlotArmour outreach | H87: capabilities/outreach | I87: M | J87: M120 | K87: =INDEX('Pricing Rules'!$B$5:$B$8,MATCH(I87,'Pricing Rules'!$A$5:$A$8,0)) | L87: =INDEX('Pricing Rules'!$C$5:$C$8,MATCH(I87,'Pricing Rules'!$A$5:$A$8,0)) | M87: =IF(OR(F87="Live",F87="Live (client-built)"),"Yes",IF(F87="Partial","Yes, with limits","No")) | N87: Managers see their team, juniors see their own work. | O87: UI: /outreach/teams, /outreach/team, /outreach/workspace.
A88: M125 | B88: Sales Operations (OMS) | C88: Targets, Weekly Reports & Assessments | D88: Targets per person, weekly reports and team assessments. | E88: Set target; weekly report; team weekly assessment | F88: Live (client-built) | G88: PlotArmour outreach | H88: capabilities/outreach | I88: M | J88: M124 | K88: =INDEX('Pricing Rules'!$B$5:$B$8,MATCH(I88,'Pricing Rules'!$A$5:$A$8,0)) | L88: =INDEX('Pricing Rules'!$C$5:$C$8,MATCH(I88,'Pricing Rules'!$A$5:$A$8,0)) | M88: =IF(OR(F88="Live",F88="Live (client-built)"),"Yes",IF(F88="Partial","Yes, with limits","No")) | N88: Weekly performance without chasing spreadsheets.
A89: M126 | B89: Sales Operations (OMS) | C89: Check-ins & Coaching Notes | D89: Daily check-ins reviewed by seniors, with coaching notes. | E89: Submit and review check-in; coaching notes | F89: Live (client-built) | G89: PlotArmour outreach | H89: capabilities/outreach | I89: S | J89: M124 | K89: =INDEX('Pricing Rules'!$B$5:$B$8,MATCH(I89,'Pricing Rules'!$A$5:$A$8,0)) | L89: =INDEX('Pricing Rules'!$C$5:$C$8,MATCH(I89,'Pricing Rules'!$A$5:$A$8,0)) | M89: =IF(OR(F89="Live",F89="Live (client-built)"),"Yes",IF(F89="Partial","Yes, with limits","No")) | N89: Coaching on real activity.
A90: M127 | B90: Sales Operations (OMS) | C90: Escalations | D90: Flag, review and resolve blockers. | E90: Flag; set in review; resolve | F90: Live (client-built) | G90: PlotArmour outreach | H90: capabilities/outreach | I90: S | J90: M124 | K90: =INDEX('Pricing Rules'!$B$5:$B$8,MATCH(I90,'Pricing Rules'!$A$5:$A$8,0)) | L90: =INDEX('Pricing Rules'!$C$5:$C$8,MATCH(I90,'Pricing Rules'!$A$5:$A$8,0)) | M90: =IF(OR(F90="Live",F90="Live (client-built)"),"Yes",IF(F90="Partial","Yes, with limits","No")) | N90: Blockers reach managers in hours not weeks.
A91: M128 | B91: Sales Operations (OMS) | C91: Domain Groups & Domain Intelligence | D91: Group target industries and see funnel, velocity and ageing per domain. | E91: Domain groups and domains; funnel, velocity, ageing queries | F91: Live (client-built) | G91: PlotArmour outreach | H91: capabilities/outreach | I91: M | J91: M120 | K91: =INDEX('Pricing Rules'!$B$5:$B$8,MATCH(I91,'Pricing Rules'!$A$5:$A$8,0)) | L91: =INDEX('Pricing Rules'!$C$5:$C$8,MATCH(I91,'Pricing Rules'!$A$5:$A$8,0)) | M91: =IF(OR(F91="Live",F91="Live (client-built)"),"Yes",IF(F91="Partial","Yes, with limits","No")) | N91: See which industries convert and which stall. | O91: UI: /outreach/domains, /outreach/intelligence.
A92: M129 | B92: Sales Operations (OMS) | C92: Research Files | D92: Reserve and confirm research files so effort is not duplicated. | E92: Reserve file; confirm; research notes with upload | F92: Live (client-built) | G92: PlotArmour outreach | H92: capabilities/outreach | I92: S | J92: M012 | K92: =INDEX('Pricing Rules'!$B$5:$B$8,MATCH(I92,'Pricing Rules'!$A$5:$A$8,0)) | L92: =INDEX('Pricing Rules'!$C$5:$C$8,MATCH(I92,'Pricing Rules'!$A$5:$A$8,0)) | M92: =IF(OR(F92="Live",F92="Live (client-built)"),"Yes",IF(F92="Partial","Yes, with limits","No")) | N92: Research done once, shared by everyone.
A93: M130 | B93: Sales Operations (OMS) | C93: Opportunities, Proposals & Closed Clients | D93: Track proposals, advance payments and won clients with attribution. | E93: Opportunity; proposal; closed client; advance payment | F93: Live (client-built) | G93: PlotArmour outreach | H93: capabilities/outreach | I93: M | J93: M120 | K93: =INDEX('Pricing Rules'!$B$5:$B$8,MATCH(I93,'Pricing Rules'!$A$5:$A$8,0)) | L93: =INDEX('Pricing Rules'!$C$5:$C$8,MATCH(I93,'Pricing Rules'!$A$5:$A$8,0)) | M93: =IF(OR(F93="Live",F93="Live (client-built)"),"Yes",IF(F93="Partial","Yes, with limits","No")) | N93: Credit every win to the right person.
A94: M131 | B94: Sales Operations (OMS) | C94: Direction Posts | D94: Managers post directives to the team. | E94: Post direction | F94: Live (client-built) | G94: PlotArmour outreach | H94: capabilities/outreach | I94: S | J94: M124 | K94: =INDEX('Pricing Rules'!$B$5:$B$8,MATCH(I94,'Pricing Rules'!$A$5:$A$8,0)) | L94: =INDEX('Pricing Rules'!$C$5:$C$8,MATCH(I94,'Pricing Rules'!$A$5:$A$8,0)) | M94: =IF(OR(F94="Live",F94="Live (client-built)"),"Yes",IF(F94="Partial","Yes, with limits","No")) | N94: One instruction everyone sees.
A95: M132 | B95: Sales Operations (OMS) | C95: Outreach AI Insights | D95: AI-recorded insights on leads and teams. | E95: Record AI insight | F95: Live (client-built) | G95: PlotArmour outreach | H95: capabilities/outreach | I95: M | J95: M019 | K95: =INDEX('Pricing Rules'!$B$5:$B$8,MATCH(I95,'Pricing Rules'!$A$5:$A$8,0)) | L95: =INDEX('Pricing Rules'!$C$5:$C$8,MATCH(I95,'Pricing Rules'!$A$5:$A$8,0)) | M95: =IF(OR(F95="Live",F95="Live (client-built)"),"Yes",IF(F95="Partial","Yes, with limits","No")) | N95: Patterns spotted automatically.
A96: M140 | B96: Vertical Packs (not built) | C96: Clinic Management Pack | D96: Patient registry, appointments, queue, consultation, prescriptions, pharmacy, lab, billing. | E96: Full capability design exists | F96: Designed | G96: None | H96: docs/reference/verticals/clinic.md | I96: XL | J96: M033, M060 | K96: =INDEX('Pricing Rules'!$B$5:$B$8,MATCH(I96,'Pricing Rules'!$A$5:$A$8,0)) | L96: =INDEX('Pricing Rules'!$C$5:$C$8,MATCH(I96,'Pricing Rules'!$A$5:$A$8,0)) | M96: =IF(OR(F96="Live",F96="Live (client-built)"),"Yes",IF(F96="Partial","Yes, with limits","No")) | N96: Design done, build not started. | O96: 9 modules M1-M9 specified.
A97: M141 | B97: Vertical Packs (not built) | C97: Salon & Spa Pack | D97: Customers, services, appointments, waitlist, packages, memberships, commissions, offers. | E97: Full capability design exists | F97: Designed | G97: None | H97: docs/reference/verticals/salon.md | I97: XL | J97: M033 | K97: =INDEX('Pricing Rules'!$B$5:$B$8,MATCH(I97,'Pricing Rules'!$A$5:$A$8,0)) | L97: =INDEX('Pricing Rules'!$C$5:$C$8,MATCH(I97,'Pricing Rules'!$A$5:$A$8,0)) | M97: =IF(OR(F97="Live",F97="Live (client-built)"),"Yes",IF(F97="Partial","Yes, with limits","No")) | N97: Design done, build not started. | O97: 11 modules specified.
A98: M142 | B98: Vertical Packs (not built) | C98: Coaching Institute Pack | D98: Students, batches, teachers, timetable, attendance, fees, tests and marks, study material. | E98: Capability design exists | F98: Designed | G98: None | H98: docs/reference/verticals/coaching.md | I98: L | J98: M033, M082 | K98: =INDEX('Pricing Rules'!$B$5:$B$8,MATCH(I98,'Pricing Rules'!$A$5:$A$8,0)) | L98: =INDEX('Pricing Rules'!$C$5:$C$8,MATCH(I98,'Pricing Rules'!$A$5:$A$8,0)) | M98: =IF(OR(F98="Live",F98="Live (client-built)"),"Yes",IF(F98="Partial","Yes, with limits","No")) | N98: Design done, build not started. | O98: 6 modules specified.
A99: M143 | B99: Vertical Packs (not built) | C99: Hotel & Resort Pack | D99: Rooms, reservations, guests, housekeeping, front desk. | E99: Reference only | F99: Reference | G99: None | H99: erpclaw-prd HospitalityClaw | I99: XL | J99: M033 | K99: =INDEX('Pricing Rules'!$B$5:$B$8,MATCH(I99,'Pricing Rules'!$A$5:$A$8,0)) | L99: =INDEX('Pricing Rules'!$C$5:$C$8,MATCH(I99,'Pricing Rules'!$A$5:$A$8,0)) | M99: =IF(OR(F99="Live",F99="Live (client-built)"),"Yes",IF(F99="Partial","Yes, with limits","No")) | O99: Reference research only.
A100: M144 | B100: Vertical Packs (not built) | C100: Legal Practice Pack | D100: Matters, time, billing, court dates, conflicts, trust accounting. | E100: Reference only | F100: Reference | G100: None | H100: erpclaw-prd LegalClaw | I100: XL | J100: M153 | K100: =INDEX('Pricing Rules'!$B$5:$B$8,MATCH(I100,'Pricing Rules'!$A$5:$A$8,0)) | L100: =INDEX('Pricing Rules'!$C$5:$C$8,MATCH(I100,'Pricing Rules'!$A$5:$A$8,0)) | M100: =IF(OR(F100="Live",F100="Live (client-built)"),"Yes",IF(F100="Partial","Yes, with limits","No")) | O100: Reference research only.
A101: M145 | B101: Vertical Packs (not built) | C101: Construction Pack | D101: Project sites, BOQ, subcontractor desk, wastage. | E101: Strategy doc only | F101: Planned | G101: None | H101: docs/enterprise-strategy/03 | I101: XL | J101: M153 | K101: =INDEX('Pricing Rules'!$B$5:$B$8,MATCH(I101,'Pricing Rules'!$A$5:$A$8,0)) | L101: =INDEX('Pricing Rules'!$C$5:$C$8,MATCH(I101,'Pricing Rules'!$A$5:$A$8,0)) | M101: =IF(OR(F101="Live",F101="Live (client-built)"),"Yes",IF(F101="Partial","Yes, with limits","No")) | O101: No code.
A102: M146 | B102: Vertical Packs (not built) | C102: Logistics Pack | D102: Transporter registry, LR tracking, freight allocation. | E102: Strategy doc only | F102: Planned | G102: None | H102: docs/enterprise-strategy/03 | I102: XL | J102: M031 | K102: =INDEX('Pricing Rules'!$B$5:$B$8,MATCH(I102,'Pricing Rules'!$A$5:$A$8,0)) | L102: =INDEX('Pricing Rules'!$C$5:$C$8,MATCH(I102,'Pricing Rules'!$A$5:$A$8,0)) | M102: =IF(OR(F102="Live",F102="Live (client-built)"),"Yes",IF(F102="Partial","Yes, with limits","No")) | O102: No code. Manufacturing dispatch is separate.
A103: M147 | B103: Vertical Packs (not built) | C103: Government & PSU Pack | D103: Registries, case management, DIGIT adapters. | E103: Strategy doc only | F103: Planned | G103: None | H103: docs/enterprise-strategy/03 | I103: XL | J103: M005 | K103: =INDEX('Pricing Rules'!$B$5:$B$8,MATCH(I103,'Pricing Rules'!$A$5:$A$8,0)) | L103: =INDEX('Pricing Rules'!$C$5:$C$8,MATCH(I103,'Pricing Rules'!$A$5:$A$8,0)) | M103: =IF(OR(F103="Live",F103="Live (client-built)"),"Yes",IF(F103="Partial","Yes, with limits","No")) | O103: No code.
A104: M148 | B104: Vertical Packs (not built) | C104: School & Higher-ed Pack | D104: Students, grading, fees, LMS sync, admissions. | E104: Reference only | F104: Reference | G104: None | H104: erpclaw-prd EduClaw family | I104: XL | J104: M142 | K104: =INDEX('Pricing Rules'!$B$5:$B$8,MATCH(I104,'Pricing Rules'!$A$5:$A$8,0)) | L104: =INDEX('Pricing Rules'!$C$5:$C$8,MATCH(I104,'Pricing Rules'!$A$5:$A$8,0)) | M104: =IF(OR(F104="Live",F104="Live (client-built)"),"Yes",IF(F104="Partial","Yes, with limits","No")) | O104: Reference research only.
A105: M149 | B105: Vertical Packs (not built) | C105: Property Management Pack | D105: Units, leases, tenants, rent, maintenance. | E105: Reference only | F105: Reference | G105: None | H105: erpclaw-prd PropertyClaw | I105: XL | J105: M074 | K105: =INDEX('Pricing Rules'!$B$5:$B$8,MATCH(I105,'Pricing Rules'!$A$5:$A$8,0)) | L105: =INDEX('Pricing Rules'!$C$5:$C$8,MATCH(I105,'Pricing Rules'!$A$5:$A$8,0)) | M105: =IF(OR(F105="Live",F105="Live (client-built)"),"Yes",IF(F105="Partial","Yes, with limits","No")) | O105: Reference research only.
...

Sheet Pricing Rules
A1: Pricing Rules & Commercial Policy
A2: Blue cells are inputs. Every price formula in Modules, Packages and Quick Quote reads from here. All figures are proposed 2026 list rates, ex-GST.
A4: Complexity | B4: Add-on setup fee | C4: Add-on monthly fee | D4: Meaning
A5: S | B5: 10000 | C5: 500 | D5: Configuration only: switch on, set roles, load masters
A6: M | B6: 25000 | C6: 1000 | D6: Configuration plus workflow mapping and a short training
A7: L | B7: 40000 | C7: 2000 | D7: Multiple workflows, integrations between modules, data mapping
A8: XL | B8: 60000 | C8: 3500 | D8: Large module or pack: significant mapping and acceptance testing
A10: Assumptions
A11: GST rate | B11: 0.18 | C11: Assumed 18% on services. Confirm with finance. Tax is extra to every price shown.
A12: Annual prepay discount | B12: 0.125 | C12: Midpoint of the 10 to 15 percent policy range from the previous workbook.
A13: Extra location setup fee | B13: 10000 | C13: Per location beyond the first. PROPOSED, not in the old workbook.
A14: Extra location monthly fee | B14: 1000 | C14: Per location beyond the first. PROPOSED, not in the old workbook.
A15: Recommended minimum implementation | B15: 125000 | C15: From old policy. Conflicts with package floors, see Pricing Review item 1.
A16: Recommended minimum monthly platform fee | B16: 12000 | C16: From old policy. Conflicts with package floors, see Pricing Review item 2.
A18: Commercial policy (carried over from the previous workbook, wording unchanged)
A19: Commercial item | B19: Recommended policy
A20: Implementation fee | B20: One-time fee covering configuration, setup, workflow mapping, base customization, testing and deployment.
A21: Subscription | B21: Monthly platform/support fee. Final amount depends on modules, users, environment, integrations and SLA.
A22: User licensing | B22: Recommended to avoid aggressive per-seat pricing for MSMEs; use business/package tiers, with user caps only where necessary.
A23: Custom development | B23: Quoted separately using the Verity Customization rate card or a fixed project quote.
A24: Integrations | B24: Third-party API, WhatsApp/SMS, accounting, payment gateway and external platform charges are billed separately where applicable.
A25: AI usage | B25: Model/API usage costs should be passed through or included with a clearly defined monthly allowance.
A26: Hosting | B26: Can be bundled into subscription or quoted separately for dedicated environments.
A27: Data migration | B27: Always scope separately based on source system, volume, cleanup and mapping complexity.
A28: Onboarding | B28: Standard onboarding included in implementation. Complex process consulting/training can be charged separately.
A29: Support | B29: Standard support included in subscription; priority SLA/dedicated support is an add-on.
A30: Annual billing | B30: Offer 10–15% effective discount for annual prepayment where commercially appropriate.
... A34: Pricing status | B34: These are proposed Verity 2026 commercial rates, not historical prices unless separately verified from a quotation/invoice.

Sheet Customization Rates
A1: Customization Rate Card
A2: Per-item rates for work beyond the package. Numbers are from the previous workbook. Open-ended means the Advanced figure is a floor.
A4: Customization | B4: Billing basis | C4: Basic | D4: Standard | E4: Advanced | F4: Charge type | G4: Open-ended? | H4: Build status note
A5: Custom field / field group | B5: Per field/group | C5: 1000 | D5: 2500 | E5: 5000 | F5: One-time | G5: Yes
A6: Custom status / workflow stage | B6: Per workflow | C6: 2500 | D6: 5000 | E6: 10000 | F6: One-time | G6: Yes
A7: Approval workflow | B7: Per workflow | C7: 5000 | D7: 10000 | E7: 25000 | F7: One-time | G7: Yes
A8: Custom form / data-entry screen | B8: Per screen | C8: 5000 | D8: 10000 | E8: 25000 | F8: One-time | G8: Yes
A9: Custom report | B9: Per report | C9: 3000 | D9: 7500 | E9: 20000 | F9: One-time | G9: Yes | H9: Standard reports exist (M021).
A10: Custom dashboard | B10: Per dashboard | C10: 7500 | D10: 15000 | E10: 35000 | F10: One-time | G10: Yes
A11: Custom PDF / document template | B11: Per template | C11: 3000 | D11: 7500 | E11: 15000 | F11: One-time | G11: Yes
A12: Third-party API integration | B12: Per integration | C12: 10000 | D12: 25000 | E12: 50000 | F12: One-time | G12: Yes
A13: Accounting / ERP integration | B13: Per integration | C13: 20000 | D13: 50000 | E13: 100000 | F13: One-time | G13: Yes | H13: No connector exists (M075). Quote as a build.
A14: WhatsApp / SMS integration | B14: Per integration | C14: 10000 | D14: 25000 | E14: 50000 | F14: One-time | G14: Yes | H14: Channel not built (M155). Quote only as a build.
A15: Custom PWA/offline workflow | B15: Per workflow | C15: 15000 | D15: 35000 | E15: 75000 | F15: One-time | G15: Yes | H15: Offline runtime exists, no PWA shell (M013).
A16: AI feature / assistant | B16: Per feature | C16: 20000 | D16: 50000 | E16: 100000 | F16: One-time | G16: Yes | H16: AI assistant is live (M019). Usage cost is separate.
A17: Data migration | B17: Per migration project | C17: 10000 | D17: 25000 | E17: 75000 | F17: One-time | G17: Yes | H17: Import covers items, customers, suppliers only (M017).
A18: Custom module | B18: Per module | C18: 30000 | D18: 75000 | E18: 200000 | F18: One-time | G18: Yes | H18: Platform supports registering capabilities (M011).
A19: Client portal | B19: Per portal | C19: 25000 | D19: 60000 | E19: 150000 | F19: One-time | G19: Yes | H19: Not built (M154). Quote as a build.
A20: Mobile-specific workflow | B20: Per workflow | C20: 15000 | D20: 35000 | E20: 75000 | F20: One-time | G20: Yes | H20: Web app is responsive; native not built.
A21: Custom analytics / BI | B21: Per implementation | C21: 20000 | D21: 50000 | E21: 150000 | F21: One-time | G21: Yes | H21: No report builder (M160). Quote as a build.
A22: Priority SLA / dedicated support | B22: Monthly add-on | C22: 10000 | D22: 20000 | E22: 50000 | F22: Monthly | G22: Yes

Sheet Pricing Review
A1: Pricing Review: open issues in the commercial model
A2: Found while reconciling the previous workbook with the codebase. Nothing here was silently changed. Resolve, then update Pricing Rules / Packages.
A4: # | B4: Area | C4: Issue | D4: Evidence | E4: Impact | F4: Recommendation | G4: Severity | H4: Status | I4: Owner / decision
A5: 1 | B5: Policy | C5: Recommended minimum implementation (Rs 1.25 lakh) is higher than every package setup floor except Manufacturing Plus, Enterprise and Dedicated. | D5: Core 40,000; Trade 50,000; Services 75,000; Production 90,000 against a 1,25,000 minimum. | E5: Packages Core to Production can never be sold at their listed floor if the minimum is enforced. | F5: Decide: drop the minimum, raise the floors, or call it a minimum for custom scope only. | G5: High | H5: Open
A6: 2 | B6: Policy | C6: Recommended minimum recurring fee (Rs 12,000/mo) is higher than every package monthly fee below Enterprise. | D6: Core 2,000; Trade 3,000; Services 5,000; Production 8,000; Mfg Plus 10,000. | E6: Same conflict as item 1 for recurring revenue. | F6: Pick one rule and state it on Packages. | G6: High | H6: Open
A7: 3 | B7: Scope | C7: Verity Core promises quotations. Quotations are not built. | D7: No quotation entity in code. Only purchase orders exist (M152 Planned). | E7: Sales would be selling a module that does not exist. | F7: Build M152, or remove quotations from Core scope until it ships. | G7: High | H7: Open
A8: 4 | B8: Scope | C8: Verity Services promises projects, timesheets and customer-portal-ready architecture. None are built. | D8: M153 and M154 Planned. Outreach tasks are the only task model. | E8: The Services package is mostly unbuilt for its target customers. | F8: Build before selling Services as listed, or sell it as a custom build. | G8: High | H8: Open
A9: 5 | B9: Scope | C9: Verity Manufacturing Plus lists advanced QC, multi-level BOM revisions, approvals and traceability. | D9: Only in-process checkpoints and batch traceability exist. Taskplan 118 waits on a named design partner. | E9: Overpromise risk on the highest-value production package. | F9: Confirm with product before quoting; restrict to what M100 to M108 do. | G9: High | H9: Open
A10: 6 | B10: Scope | C10: Customization card prices WhatsApp/SMS, accounting/ERP integration, client portal, BI and PWA as if they were configurations. | D10: M155, M075, M154, M160 Planned; M013 runtime only. | E10: These are net-new builds. A Rs 10,000 Basic price will not cover them. | F10: Re-price as build projects or hold until built. | G10: Medium | H10: Open
A11: 7 | B11: Scope | C11: The previous Modules sheet listed 38 modules as if all shipped. Many did not exist (quotations, QC templates, NCR/CAPA, projects, timesheets, OCR, WhatsApp, business rules builder). | D11: See Modules status column and Roadmap & Gaps. | E11: Sales and PM were working from a catalogue that did not match the product. | F11: Use the Modules tab as the only catalogue. | G11: High | H11: Open
A12: 8 | B12: Positioning | C12: Old Overview describes Verity as an ERP/CRM for production and service MSMEs. Website and platform docs describe a general operational layer built from eight primitives, and the platform has no per-industry hard-coding. | D12: content/capabilities.js, CLAUDE.md in Verity repo. | E12: Two pitches in the market. | F12: Agree one sentence and use it everywhere. | G12: Medium | H12: Open
A13: 9 | B13: Language | C13: Website copy rules forbid the phrases point of sale, GST filing, payroll processing, storefront, appointment booking. The product has GSTR-1/3B preparation, counter billing, attendance-based payroll inputs. | D13: content/capabilities.js FORBIDDEN_CLAIMS. | E13: Sales may use words the site is forbidden to use, or avoid features that exist. | F13: Use: return preparation, counter billing, payroll inputs. See Website Capabilities. | G13: Medium | H13: Open
A14: 10 | B14: Packaging | C14: Verity Dedicated is a fixed Rs 1,80,000 with no + while every other package is a floor. | D14: Packages tab. | E14: Inconsistent: dedicated environments usually cost more than shared ones. | F14: Mark as floor or explain the fixed price. | G14: Low | H14: Open
A15: 11 | B15: Packaging | C15: No per-module add-on pricing existed. Add-on prices on Modules and Quick Quote are new proposals derived from complexity. | D15: Pricing Rules A5:C8. | E15: Proposed rates, not validated with any client. | F15: Review and approve or replace the four complexity rates. | G15: Medium | H15: Open
A16: 12 | B16: Packaging | C16: No extra-location pricing existed. Multi-site is a headline capability. | D16: Pricing Rules B13:B14 are new proposals. | E16: Multi-outlet clients could be under-priced. | F16: Approve or replace. | G16: Medium | H16: Open
... A24: 20 | B24: Site | C24: Repo sitemap uses theverityai.xyz; the live site is verity.plotarmour.in. | D24: sitemap.xml in verity-explore. | E24: Canonical URL and sitemap disagree. | F24: Align sitemap and canonical tags to the live domain. | G24: Low | H24: Open

Sheet Roadmap & Gaps
A1: Roadmap & Gaps
A2: Everything not yet fully sellable, with what blocks it. Priority and owner are for PM to fill in (blue).
A4: Ref | B4: Item | C4: Type | D4: Status | E4: What is missing / blocker | F4: Source | G4: Priority | H4: Owner
A5: M007 | B5: Notifications | C5: Hardening of partial module | D5: Partial | E5: In-app only. Email/WhatsApp/SMS delivery adapters not built (see M155). | F5: platform/notification.ts
A6: M013 | B6: Offline Sync Runtime | C6: Hardening of partial module | D6: Partial | E6: Runtime only. No installable PWA shell or client queue UI. Tables: OfflineCommand, SyncException. | F6: platform/sync.ts
A7: M014 | B7: API Keys & External Tool Invocation | C7: Hardening of partial module | D7: Partial | E7: Tables: ExternalApiKey, ExternalIdempotency, RequestQuota. Relay integration is ADR-029 proposed (Task 120). No public API docs. | F7: platform/external-tools.ts, tool-manifest.ts
A8: M017 | B8: Data Import & Migration | C8: Hardening of partial module | D8: Partial | E8: Only item, customer and supplier import. Orders, balances, ledgers not importable. UI: /import. | F8: server/actions/import.ts
A9: M020 | B9: Jev Decision Node (AI advisory in workflows) | C9: Horizontal module | D9: Built, not live-verified | E9: Unit-proven only. Needs migration, key, one real call (Task 119). Do not sell yet. | F9: platform/decision.ts
A10: M070 | B10: Chart of Accounts & Journals | C10: Hardening of partial module | D10: Partial | E10: MVP. No trial balance, balance sheet, P&L statements or bank reconciliation. UI: /accounting. | F10: capabilities/accounting
A11: M075 | B11: External Accounting Sync (Tally, Zoho, QuickBooks) | C11: Horizontal module | D11: Planned | E11: No connector exists. Do not promise a named product. | F11: verity-spec/10_integrations/accounting.md (stub)
A12: M076 | B12: Payment Gateway & UPI Collection | C12: Horizontal module | D12: Planned | E12: No gateway integration exists. | F12: verity-spec/10_integrations/payments.md (stub)
A13: M083 | B13: Payroll Inputs | C13: Hardening of partial module | D13: Partial | E13: Inputs only. No payslips. | F13: capabilities/attendance
A14: M084 | B14: Payroll Processing & Statutory (PF, ESI, TDS) | C14: Horizontal module | D14: Planned | E14: Blocked on statutory research (Task 79). | F14: taskplans/79 (no Indian statutory spec yet)
A15: M105 | B15: In-process Checkpoints | C15: Hardening of partial module | D15: Partial | E15: Checkpoints only. No templates, tolerances or NCR/CAPA (see M109). | F15: capabilities/manufacturing
A16: M109 | B16: Advanced QC (templates, inspections, NCR/CAPA) | C16: Horizontal module | D16: Planned | E16: Wider build waits for a named design partner. | F16: taskplans/118 (waits on design partner)
... A53: T87 | B53: Import/export beyond item, customer, supplier | C53: Platform | D53: Partial | E53: Orders, balances, ledgers not importable. | F53: taskplans/87

Sheet Industries
A1: Industry Hubs (9)
A2: From content/industries.js. Capabilities are the website's names; see Website Capabilities for product status.
A4: Industry | B4: Slug | C4: Business types | D4: Headline | E4: Lede | F4: Capabilities used | G4: Pain points | H4: Context
A5: Retail & Commerce | B5: retail-commerce | C5: 20 | D5: Retail runs on stock, and stock runs on records. | E5: A retail business is a stock position, a customer list and a day’s takings, and in most shops those three live in three different places. Verity puts them on one record model so the stock you hold, the orders you have placed and the customers who keep coming back are the same system. | F5: People, Relationships, Records, Workflows, Reports and analytics, Verity AI, Inventory, Orders, Suppliers, Locations | G5: Stock truth lives in two places | Reordering is a memory exercise | Customer history stops at the till | Performance is monthly, not daily | H5: Retail is unusual among industries in that the thing being managed is physically present and constantly moving. Stock arrives from suppliers, sits, sells, gets returned, gets written off, and has to be reordered before it runs out — usually while the person who understands the pattern is serving a customer. The information problem is not that retailers lack data. It is that the sale, the stock movement, the purchase order and the customer’s history are recorded in four systems that do not know about each other, so answering "which lines are tying up money without moving" takes an evening with a spreadsheet.
A6: Food & Hospitality | B6: food-hospitality | C6: 14 | D6: The day is the unit of work, and it does not wait. | E6: Hospitality operations are settled and re-settled every service. Verity keeps the orders, the stock they consume, the people on shift and the money they produce on one record, so the day can be understood while it is still running. | F6: People, Work, Records, Workflows, Reports and analytics, Verity AI, Inventory, Orders, Suppliers, Workforce | G6: Consumption is invisible until it is a shortage | Rosters and revenue are unrelated data | Suppliers are managed by phone | Multi-outlet means multi-spreadsheet | H6: A hospitality business converts perishable stock into revenue on a clock. Everything that matters — covers, order volume, ingredient consumption, staff on shift, waste — happens inside a few hours and then is gone, which is why so much of the sector’s reporting is reconstructed from memory the next morning. The operational questions are not complicated, but they are time-sensitive: what is selling tonight, what are we about to run out of, who is short-staffed, and did today make money. Those answers exist in the orders, the stock movements and the roster — provided those three are the same system.
A7: Professional Services | B7: professional-services | C7: 15 | D7: The product is work, and the work is people’s time. | E7: A professional services firm sells the attention of the people it employs. Verity connects the client, the engagement, the work inside it, the documents it produces and the approvals it needs, so utilisation and delivery stop being separate conversations. | F7: Work, Relationships, Records, People, Workflows, Communication, Reports and analytics, Verity AI | G7: Engagement health is discovered late | Documents outlive the systems holding them | Deadlines are tracked personally | Capacity is a feeling | H7: Every professional firm runs the same shape of operation regardless of discipline: a relationship, an engagement under it, a set of deliverables and deadlines, documents that must be findable years later, and time that either was or was not recoverable. The failure mode is equally consistent. The client relationship sits in one system, the matter or project in another, the documents in a shared drive and the billing in a third, so the question "is this engagement actually profitable and on schedule" requires a person to reconcile them.
A8: Healthcare | B8: healthcare | C8: 11 | D8: Care is delivered by an operation, and the operation is usually invisible. | E8: Behind every consultation is a roster, a consumable, a record and a follow-up. Verity manages that operational layer — the scheduling, stock, staffing, documentation and reporting around care — on one system. | F8: People, Work, Records, Inventory, Workflows, Control, Reports and analytics, Locations | G8: Rosters and demand are set separately | Consumables run out mid-week | Follow-ups depend on someone remembering | Multi-site reporting is reassembled monthly | H8: Healthcare businesses carry an operational load that has nothing to do with clinical skill: staff must be rostered across shifts, consumables and reagents must be in stock, records must be retained and retrievable, follow-ups must actually happen, and every one of those has a compliance dimension. Verity is not a clinical system and does not attempt to be. It manages the practice around the clinic: the people, the stock, the work, the documents and the reporting that determine whether the clinical side can function.
A9: Education | B9: education | C9: 12 | D9: An institution is an operation with a very long memory. | E9: Education organisations manage more people, over more years, with more record-keeping obligations than almost any other sector of comparable size. Verity holds the admissions, the students, the staff, the work and the documentation on one model. | F9: People, Records, Work, Workflows, Communication, Control, Reports and analytics, Verity AI | G9: The same person exists in several systems | Fee follow-up is manual and awkward | Staff workload is uneven and unmeasured | Compliance reporting is an annual scramble | H9: A school or institute runs several parallel operations at once: admissions and enrolment, timetabling and staffing, fee collection and follow-up, academic and administrative records, parent communication, and reporting to boards or regulators. Each tends to acquire its own system, and none of them share a person record. The result is that the same student exists five times, the same parent is contacted from three systems, and any question spanning two of those systems is answered by a member of staff with a spreadsheet.
A10: Real Estate & Construction | B10: real-estate-construction | C10: 10 | D10: The work is distributed, and so is everyone who knows about it. | E10: Real estate and construction operations run across sites, agents, contractors and stages that rarely share a system. Verity holds the pipeline, the properties, the site work and the approvals on one record with one permission model. | F10: Relationships, Work, Records, Locations, Workflows, People, Suppliers, Reports and analytics | G10: Pipeline lives in agents’ phones | Site status arrives as narrative | Approvals stall invisibly | Material and contractor costs are reconciled after the fact | H10: This sector has two distinct operations that share a record set. On one side there is a pipeline: enquiries, viewings, negotiations, agents, commissions. On the other there is execution: sites, crews, materials, inspections, milestones and payments against them. Both suffer the same structural problem — the people who hold the information are not at a desk. Updates arrive as phone calls and photographs, and the system of record is whoever answered.
A11: Manufacturing & B2B | B11: manufacturing-b2b | C11: 13 | D11: Everything that stops a shipment starts somewhere upstream. | E11: Manufacturing and distribution are chains of dependent steps, and a delay at any one of them surfaces at the end as a late order. Verity connects materials, production, quality, stock and dispatch so the cause is visible where it happens. | F11: Work, Records, Workflows, Control, Reports and analytics, Inventory, Orders, Suppliers, Logistics, Locations | G11: Late orders have untraceable causes | Raw material and finished stock are counted separately | Quality holds are communicated informally | Supplier reliability is anecdotal | H11: This is the operation Verity’s record model was shaped around. Raw materials arrive against purchase orders, are consumed by production work, become finished goods in stock, are committed to customer orders and leave through dispatch — with quality checks, approvals and exceptions at every transition. When those transitions are recorded in different systems, the business can see that an order is late but not why. When they share a record, the QC backlog that is holding eleven items is visible in the same view as the dispatch it is blocking.
A12: Personal & Local Services | B12: personal-local-services | C12: 15 | D12: Small operations still have an operation. | E12: A salon, a studio or a repair shop is a business where the owner is also the operator, which is exactly why the record-keeping loses. Verity keeps customers, staff, jobs and stock on one system that does not require an administrator to maintain. | F12: Relationships, People, Work, Workforce, Inventory, Reports and analytics, Verity AI, Communication | G12: Repeat custom is not measured | Staff time is booked, not analysed | Retail stock is a side business nobody runs | The owner is the system | H12: Local service businesses run on repeat custom and staff availability. The economics are simple and unforgiving: a customer who does not come back is not replaced cheaply, and an hour of unfilled staff time is gone. What these businesses rarely have is anyone whose job is to maintain a system. So the customer history is in a book, the staff schedule is on a wall, and the stock check happens when something runs out — and none of that produces the pattern that would tell the owner which customers have quietly stopped coming.
A13: Digital & Technology | B13: digital-technology | C13: 13 | D13: The product is engineered. The business around it usually is not. | E13: Technology businesses instrument their product carefully and run their operations on a stack of disconnected tools. Verity connects the clients, the delivery work, the team capacity and the commercial record into one operational system. | F13: Work, Relationships, People, Records, Workflows, Reports and analytics, Verity AI, Communication | G13: Delivery and commercial data never meet | Capacity is committed before it is checked | Client context is scattered | Operational reporting is built ad hoc | H13: A digital business has excellent visibility into its product and poor visibility into itself. Delivery work sits in an issue tracker, clients in a CRM, contracts in a drive, invoices in an accounting tool and capacity in nobody’s system at all. The questions that go unanswered are commercial rather than technical: which accounts are consuming more delivery than they pay for, which projects are late and why, and how much capacity is actually committed next month.

Sheet Business Types
A1: Business Types (123): outreach and ICP targeting
A2: One row per website business page. Package and modules are a heuristic suggestion, not a quote. Live coverage = share of this page's capability claims that are Live in product.
A4: Slug | B4: Business type | C4: Industry | D4: Rollout tier | E4: Page URL | F4: Hero headline | G4: Lead with this pain point | H4: First discovery question | I4: Decision-maker roles | J4: Suggested package | K4: Suggested modules (IDs) | L4: Vertical pack fit | M4: Live coverage | N4: Capability gaps to avoid promising | O4: SEO keywords | P4: Related business types | Q4: Page title
A5: retail-stores | B5: Retail Stores | C5: Retail & Commerce | D5: 1 | E5: =README!$B$7&"/businesses/"&A5&"/" | F5: The shelf says one thing. The sheet says another. The reorder is due today. | G5: Stock truth lives in two places | H5: Where is my money and what is it doing? | I5: Owner, Store manager, Buyer, Floor staff, Accounts | J5: Verity Trade | K5: M002, M004, M005, M006, M007, M012, M018, M019, M021, M030, M040, M041, M042, M043, M046, M048, M060, M080 | M5: 0.91666667 | N5: Communication (Partial) | O5: AI software for retail stores; retail management software; retail inventory management software; multi store retail operations software; business software for retailers | P5: supermarkets, fashion-stores, electronics-stores, jewellery-stores, furniture-stores, cosmetics-stores | Q5: AI business management software for retail stores | Verity
A6: supermarkets | B6: Supermarkets | C6: Retail & Commerce | D6: 1 | E6: =README!$B$7&"/businesses/"&A6&"/" | F6: Thousands of lines, single-digit margin, and a third of it perishes. | G6: Shrinkage arrives as one unexplained number | H6: Where is the percentage going? | I6: Owner or chain head, Store manager, Section lead, Buyer, Accounts | J6: Verity Trade | K6: M002, M004, M005, M006, M012, M018, M019, M021, M030, M040, M041, M042, M043, M046, M048, M060, M080, M082 | M6: 1 | O6: AI software for supermarkets; supermarket management software; perishable inventory and shrinkage control; category management software; supermarket chain operations software | P6: grocery-stores, retail-stores, convenience-stores, department-stores, distributors, wholesalers | Q6: AI business management software for supermarkets | Verity
A7: grocery-stores | B7: Grocery Stores | C7: Retail & Commerce | D7: 1 | E7: =README!$B$7&"/businesses/"&A7&"/" | F7: The khata is the most important record in the shop and the least protected. | G7: The credit book is memory with a notebook attached | H7: How much is out, and with whom? | I7: Owner, Counter staff, Delivery rider, Whoever orders stock | J7: Verity Trade | K7: M002, M004, M005, M006, M007, M012, M018, M019, M021, M040, M041, M042, M043, M046, M048, M060, M080, M123, M153 | M7: 0.83333333 | N7: Communication (Partial); Work (Partial) | O7: AI software for grocery stores; grocery store management software; kirana store billing and khata software; customer credit tracking for shops; local grocery inventory software | P7: supermarkets, convenience-stores, retail-stores, bakeries, pet-stores, hardware-stores | Q7: AI business management software for grocery stores | Verity
A8: convenience-stores | B8: Convenience Stores | C8: Retail & Commerce | D8: 2 | E8: =README!$B$7&"/businesses/"&A8&"/" | F8: Six hundred square feet. Every facing has to earn its space. | G8: Dead lines occupy the only scarce resource | H8: What should I carry and when should I open? | I8: Owner, Shift staff | J8: Verity Trade | K8: M002, M004, M005, M006, M012, M018, M019, M021, M030, M040, M041, M042, M043, M046, M048, M060, M080, M082 | M8: 1 | O8: AI software for convenience stores; convenience store management software; space productivity and facing analysis; extended hours staffing and shrink control | P8: grocery-stores, supermarkets, retail-stores, bakeries, gift-shops, pet-stores | Q8: AI business management software for convenience stores | Verity
A9: department-stores | B9: Department Stores | C9: Retail & Commerce | D9: 2 | E9: =README!$B$7&"/businesses/"&A9&"/" | F9: Six categories under one roof, competing for the same floor and the same staff. | G9: Departments are compared on sales, not on space | H9: Which departments earn their floor? | I9: Store head, Department manager, Buying, Accounts | J9: Verity Trade | K9: M002, M004, M005, M006, M012, M018, M019, M021, M030, M040, M041, M042, M043, M046, M048, M060, M080, M082 | M9: 1 | O9: AI software for department stores; department store management software; concession settlement and floor productivity; multi category retail space allocation | P9: retail-stores, fashion-stores, shoe-stores, home-decor-stores, beauty-stores, supermarkets | Q9: AI business management software for department stores | Verity
A10: fashion-stores | B10: Fashion Stores | C10: Retail & Commerce | D10: 1 | E10: =README!$B$7&"/businesses/"&A10&"/" | F10: You did not sell out of the dress. You sold out of the sizes people wear. | G10: Sell-through hides broken size runs | H10: Is the season working? | I10: Owner, Buyer, Store manager, Floor staff, Accounts | J10: Verity Trade | K10: M002, M004, M005, M006, M007, M012, M018, M019, M021, M030, M040, M041, M042, M043, M046, M048, M060, M080 | M10: 0.91666667 | N10: Communication (Partial) | O10: AI software for fashion stores; fashion retail management software; apparel inventory size colour matrix; markdown and season buying software; clothing store management system | P10: clothing-boutiques, shoe-stores, retail-stores, cosmetics-stores, jewellery-stores, garment-manufacturers | Q10: AI business management software for fashion stores | Verity
A11: clothing-boutiques | B11: Clothing Boutiques | C11: Retail & Commerce | D11: 1 | E11: =README!$B$7&"/businesses/"&A11&"/" | F11: You buy six of a piece. Which six customers should hear about it? | G11: The clientele lives in the owner’s head | H11: Which buys and which clients are carrying the shop? | I11: Owner, Salesperson, Whoever manages alterations | J11: Verity Trade | K11: M002, M004, M005, M006, M007, M012, M018, M019, M021, M040, M041, M042, M046, M048, M060, M080, M123, M153 | M11: 0.81818182 | N11: Communication (Partial); Work (Partial) | O11: AI software for clothing boutiques; boutique management software; boutique clientele and alteration tracking; small batch apparel inventory software | P11: fashion-stores, shoe-stores, jewellery-stores, tailors, gift-shops, cosmetics-stores | Q11: AI business management software for clothing boutiques | Verity
A12: shoe-stores | B12: Shoe Stores | C12: Retail & Commerce | D12: 2 | E12: =README!$B$7&"/businesses/"&A12&"/" | F12: A style without its middle sizes is not stock. It is display. | G12: Broken size runs are invisible at style level | H12: Is the range still sellable? | I12: Owner, Buyer, Store manager, Floor staff | J12: Verity Trade | K12: M002, M004, M005, M006, M007, M012, M018, M019, M021, M030, M040, M041, M042, M043, M046, M048, M060, M080 | M12: 0.91666667 | N12: Communication (Partial) | O12: AI software for shoe stores; footwear retail management software; size run and stock depth tracking; shoe store returns and fit analysis | P12: fashion-stores, clothing-boutiques, sports-stores, retail-stores, department-stores, garment-manufacturers | Q12: AI business management software for shoe stores | Verity
A13: jewellery-stores | B13: Jewellery Stores | C13: Retail & Commerce | D13: 1 | E13: =README!$B$7&"/businesses/"&A13&"/" | F13: A jewellery store is an inventory problem wearing a retail costume. | G13: Stock is counted, not tracked | H13: Where is my capital and what is it doing? | I13: Owner, Showroom manager, Sales staff, Workshop supervisor, Accounts | J13: Verity Trade | K13: M002, M004, M005, M006, M007, M012, M018, M019, M021, M030, M040, M041, M042, M043, M046, M048, M060, M080 | M13: 0.91666667 | N13: Communication (Partial) | O13: AI software for jewellery stores; jewellery store management software; jewellery inventory management software; CRM for jewellery stores; business software for jewellers; jewellery shop billing and stock software | P13: fashion-stores, gift-shops, cosmetics-stores, electronics-stores, retail-stores, furniture-stores | Q13: AI business management software for jewellery stores | Verity
A14: electronics-stores | B14: Electronics Stores | C14: Retail & Commerce | D14: 1 | E14: =README!$B$7&"/businesses/"&A14&"/" | F14: Every unit has a serial number, and that number is the whole relationship. | G14: The serial number is not linked to the customer | H14: What is my stock worth and what am I not claiming? | I14: Owner, Store manager, Service desk, Sales staff | J14: Verity Trade | K14: M002, M004, M005, M006, M007, M012, M018, M019, M021, M030, M040, M041, M042, M046, M048, M060, M080, M123, M153 | M14: 0.83333333 | N14: Communication (Partial); Work (Partial) | O14: AI software for electronics stores; electronics retail management software; serial number and warranty tracking software; consumer electronics inventory and service software | P14: retail-stores, auto-parts-stores, hardware-stores, furniture-stores, repair-services, distributors | Q14: AI business management software for electronics stores | Verity
A15: furniture-stores | B15: Furniture Stores | C15: Retail & Commerce | D15: 1 | E15: =README!$B$7&"/businesses/"&A15&"/" | F15: You sold it in March. You deliver it in June. Everything in between is the business. | G15: Orders stall on unconfirmed selections | H15: Are we keeping the promises we sell on? | I15: Owner, Operations manager, Showroom staff, Delivery coordinator, Accounts | J15: Verity Trade | K15: M002, M004, M005, M006, M007, M012, M018, M019, M021, M030, M040, M041, M042, M043, M046, M048, M060, M080, M123, M153 | L15: M053 pattern: Trading + vertical pack (Live for plywood) | M15: 0.84615385 | N15: Communication (Partial); Work (Partial) | O15: AI software for furniture stores; furniture retail management software; made to order furniture tracking; furniture delivery and assembly scheduling software | P15: home-decor-stores, retail-stores, interior-designers, furniture-manufacturers, electronics-stores, construction-companies | Q15: AI business management software for furniture stores | Verity
A16: home-decor-stores | B16: Home Decor Stores | C16: Retail & Commerce | D16: 2 | E16: =README!$B$7&"/businesses/"&A16&"/" | F16: Most of your capital is on display and turning twice a year. | G16: Display position is not measured | H16: Is the floor earning its capital? | I16: Owner, Store manager, Delivery and warehouse | J16: Verity Trade | K16: M002, M004, M005, M006, M012, M018, M019, M021, M030, M040, M041, M042, M043, M046, M048, M060, M080, M123, M153 | M16: 0.91666667 | N16: Work (Partial) | O16: AI software for home decor stores; home decor retail management software; display stock and slow turn capital tracking; delivery installation and designer account software | P16: furniture-stores, interior-designers, gift-shops, retail-stores, department-stores, interior-design-firms | Q16: AI business management software for home decor stores | Verity
A17: beauty-stores | B17: Beauty Stores | C17: Retail & Commerce | D17: 2 | E17: =README!$B$7&"/businesses/"&A17&"/" | F17: Twenty brands, one floor, and staff paid by somebody else. | G17: Promoter productivity is not compared | H17: What is each brand actually worth? | I17: Owner, Store manager, Beauty advisor | J17: Verity Trade | K17: M002, M004, M005, M006, M007, M012, M018, M019, M021, M030, M040, M041, M042, M043, M046, M048, M060, M080 | M17: 0.91666667 | N17: Communication (Partial) | O17: AI software for beauty stores; beauty retail management software; brand promoter productivity tracking; multi brand assortment and sampling cost | P17: cosmetics-stores, department-stores, salons, spas, retail-stores, pharmacies | Q17: AI business management software for beauty stores | Verity
A18: cosmetics-stores | B18: Cosmetics Stores | C18: Retail & Commerce | D18: 1 | E18: =README!$B$7&"/businesses/"&A18&"/" | F18: Shade 04 sells. Shades 01 and 09 expire. The report says the range worked. | G18: Shade-level stockouts are invisible | H18: What am I about to write off, and what am I not claiming? | I18: Owner, Store manager, Beauty advisor, Buyer | J18: Verity Trade | K18: M002, M004, M005, M006, M007, M012, M018, M019, M021, M030, M040, M041, M042, M043, M046, M048, M060, M080 | M18: 0.91666667 | N18: Communication (Partial) | O18: AI software for cosmetics stores; cosmetics retail management software; beauty retail batch and expiry tracking; shade level inventory software; brand counter and BA performance software | P18: beauty-stores, fashion-stores, pharmacies, salons, retail-stores, gift-shops | Q18: AI business management software for cosmetics stores | Verity
A19: sports-stores | B19: Sports Stores | C19: Retail & Commerce | D19: 2 | E19: =README!$B$7&"/businesses/"&A19&"/" | F19: Six sports, six seasons, and one stockroom. | G19: One annual pattern across several seasons | H19: Is each season planned properly? | I19: Owner, Store staff, Workshop | J19: Verity Trade | K19: M002, M004, M005, M006, M012, M018, M019, M021, M030, M040, M041, M042, M043, M046, M048, M060, M080, M123, M153 | M19: 0.91666667 | N19: Work (Partial) | O19: AI software for sports stores; sports retail management software; team and club bulk order management; equipment servicing and seasonal stock software | P19: shoe-stores, fashion-stores, retail-stores, gyms, fitness-studios, schools | Q19: AI business management software for sports stores | Verity
A20: bookstores | B20: Bookstores | C20: Retail & Commerce | D20: 1 | E20: =README!$B$7&"/businesses/"&A20&"/" | F20: Most of your stock sells once a year. That is not a mistake — it is the shop. | G20: Returns windows close unnoticed | H20: What is returnable and what is dead? | I20: Owner, Bookseller, Whoever handles accounts | J20: Verity Trade | K20: M002, M004, M005, M006, M007, M012, M018, M019, M021, M040, M041, M042, M043, M046, M048, M060, M080, M123, M153 | M20: 0.83333333 | N20: Communication (Partial); Work (Partial) | O20: AI software for bookstores; bookstore management software; bookshop inventory and returns software; special order and institutional account tracking | P20: gift-shops, retail-stores, schools, colleges, clothing-boutiques, coaching-institutes | Q20: AI business management software for bookstores | Verity
A21: gift-shops | B21: Gift Shops | C21: Retail & Commerce | D21: 2 | E21: =README!$B$7&"/businesses/"&A21&"/" | F21: Everything sells in three weeks. What is left has no second chance. | G21: Occasion stock has no second chance | H21: Am I buying and staffing for the right peak? | I21: Owner, Shop staff, Workroom | J21: Verity Trade | K21: M002, M005, M006, M012, M018, M019, M021, M030, M040, M041, M042, M043, M046, M048, M060, M080, M082, M123, M153 | M21: 0.91666667 | N21: Work (Partial) | O21: AI software for gift shops; gift shop management software; seasonal stock and occasion demand planning; corporate gifting order management | P21: home-decor-stores, bookstores, retail-stores, jewellery-stores, printing-businesses, cosmetics-stores | Q21: AI business management software for gift shops | Verity
A22: pet-stores | B22: Pet Stores | C22: Retail & Commerce | D22: 2 | E22: =README!$B$7&"/businesses/"&A22&"/" | F22: A dog eats the same food every month. That is the most predictable demand in retail. | G22: Refill demand is not followed up | H22: Is the repeat revenue holding? | I22: Owner, Store staff, Groomer | J22: Verity Trade | K22: M002, M004, M005, M006, M012, M018, M019, M021, M030, M040, M041, M042, M043, M046, M048, M060, M080, M123, M153 | M22: 0.91666667 | N22: Work (Partial) | O22: AI software for pet stores; pet store management software; pet food repeat purchase and expiry tracking; grooming service and live animal record software | P22: veterinary-clinics, grocery-stores, retail-stores, convenience-stores, salons, gift-shops | Q22: AI business management software for pet stores | Verity
A23: hardware-stores | B23: Hardware Stores | C23: Retail & Commerce | D23: 2 | E23: =README!$B$7&"/businesses/"&A23&"/" | F23: Eleven thousand lines, most of them worth twenty rupees, and the ones that matter are always out. | G23: A stockout loses the whole list | H23: What is the range earning and who owes me? | I23: Owner, Counter staff, Storekeeper | J23: Verity Trade | K23: M002, M004, M005, M006, M007, M012, M018, M019, M021, M030, M040, M041, M042, M043, M046, M048, M060, M080 | M23: 0.91666667 | N23: Communication (Partial) | O23: AI software for hardware stores; hardware store management software; trade credit and counter account tracking; large SKU count inventory software | P23: auto-parts-stores, building-material-suppliers, retail-stores, industrial-suppliers, convenience-stores, contractors | Q23: AI business management software for hardware stores | Verity
A24: auto-parts-stores | B24: Auto Parts Stores | C24: Retail & Commerce | D24: 2 | E24: =README!$B$7&"/businesses/"&A24&"/" | F24: The part either fits the vehicle or it comes back. | G24: Wrong parts are supplied and returned | H24: Why do parts come back and who owes me? | I24: Owner, Counter staff, Storekeeper | J24: Verity Trade | K24: M002, M004, M005, M006, M007, M012, M018, M019, M021, M030, M040, M041, M042, M043, M046, M048, M060, M080 | M24: 0.91666667 | N24: Communication (Partial) | O24: AI software for auto parts stores; auto parts retail management software; fitment and cross reference tracking; garage trade credit and returns software | P24: hardware-stores, auto-repair-shops, retail-stores, industrial-suppliers, distributors, car-rentals | Q24: AI business management software for auto parts stores | Verity
A25: restaurants | B25: Restaurants | C25: Food & Hospitality | D25: 1 | E25: =README!$B$7&"/businesses/"&A25&"/" | F25: Service ends at eleven. The numbers should not arrive next month. | G25: Consumption is invisible until it is a shortage | H25: Did the week make money, and where did it leak? | I25: Owner, Restaurant manager, Head chef, Purchasing, Accounts | J25: Verity Trade | K25: M002, M005, M006, M007, M012, M018, M019, M021, M030, M033, M040, M041, M042, M043, M046, M048, M060, M080, M082, M090, M091, M092, M093, M094, M095, M123, M153 | L25: M090-M098 Food & Hospitality (Live, proven at Kent's and Colonel Kebabz) | M25: 0.85714286 | N25: Communication (Partial); Work (Partial) | O25: AI software for restaurants; restaurant management software; restaurant inventory management software; restaurant analytics software; business software for restaurants; multi-outlet restaurant management system | P25: cafes, bakeries, cloud-kitchens, catering-businesses, fast-food-businesses, hotels | Q25: AI business management software for restaurants | Verity
A26: cafes | B26: Cafés | C26: Food & Hospitality | D26: 1 | E26: =README!$B$7&"/businesses/"&A26&"/" | F26: Four hundred transactions at a hundred and twenty rupees. Everything is decided in fractions. | G26: The peak is understaffed and nobody sees the cost | H26: Where is the margin going? | I26: Owner, Café manager, Shift lead | J26: Verity Trade | K26: M002, M005, M006, M007, M012, M018, M019, M021, M030, M040, M041, M042, M043, M046, M048, M060, M080, M082, M090, M091, M092, M093, M094, M095, M123, M153 | L26: M090-M098 Food & Hospitality (Live) | M26: 0.84615385 | N26: Communication (Partial); Work (Partial) | O26: AI software for cafes; cafe management software; coffee shop inventory and wastage tracking; cafe staffing and throughput software | P26: restaurants, bakeries, fast-food-businesses, cloud-kitchens, hotels, catering-businesses | Q26: AI business management software for cafés | Verity
A27: bakeries | B27: Bakeries | C27: Food & Hospitality | D27: 1 | E27: =README!$B$7&"/businesses/"&A27&"/" | F27: You decide tonight what tomorrow will sell, and you find out at seven in the evening whether you were right. | G27: The production plan is habit, not history | H27: Are we making the right quantities? | I27: Owner, Head baker, Counter staff, Accounts | J27: Verity Trade | K27: M002, M004, M005, M006, M007, M012, M018, M019, M021, M030, M040, M041, M042, M043, M046, M048, M060, M080, M090, M091, M092, M093, M094, M095, M123, M153 | L27: M090-M098 Food & Hospitality (Live) | M27: 0.84615385 | N27: Communication (Partial); Work (Partial) | O27: AI software for bakeries; bakery management software; bakery production planning software; wholesale bakery order and delivery tracking; custom cake order management | P27: cafes, restaurants, cloud-kitchens, catering-businesses, food-manufacturers, grocery-stores | Q27: AI business management software for bakeries | Verity
A28: cloud-kitchens | B28: Cloud Kitchens | C28: Food & Hospitality | D28: 1 | E28: =README!$B$7&"/businesses/"&A28&"/" | F28: Five brands, one kitchen, one set of costs — and no idea which brand is carrying which. | G28: Per-brand contribution is an allocation, not a measurement | H28: Which brands are worth running? | I28: Operator, Kitchen manager, Station lead, Accounts | J28: Verity Trade | K28: M002, M004, M005, M006, M007, M012, M018, M019, M021, M030, M041, M042, M043, M046, M048, M060, M080, M082, M090, M091, M092, M093, M094, M095, M123, M153 | L28: M090-M098 Food & Hospitality (Live) | M28: 0.84615385 | N28: Communication (Partial); Work (Partial) | O28: AI software for cloud kitchens; cloud kitchen management software; multi brand kitchen operations software; delivery kitchen cost and contribution tracking | P28: restaurants, fast-food-businesses, cafes, bakeries, catering-businesses, ecommerce-businesses | Q28: AI business management software for cloud kitchens | Verity
A29: fast-food-businesses | B29: Fast Food Businesses | C29: Food & Hospitality | D29: 1 | E29: =README!$B$7&"/businesses/"&A29&"/" | F29: Twelve outlets doing the same thing differently is twelve businesses. | G29: Service speed varies by outlet and nobody attributes it | H29: Which outlets are not the same business? | I29: Network owner, Area manager, Shift manager, Supply and purchasing | J29: Verity Trade | K29: M002, M004, M005, M006, M007, M012, M018, M019, M021, M030, M041, M042, M043, M046, M048, M060, M080, M082, M090, M091, M092, M093, M094, M095, M123, M153 | L29: M090-M098 Food & Hospitality (Live) | M29: 0.84615385 | N29: Communication (Partial); Work (Partial) | O29: AI software for fast food businesses; quick service restaurant management software; multi outlet QSR operations software; portion control and service speed tracking | P29: restaurants, cafes, cloud-kitchens, catering-businesses, retail-stores, hotels | Q29: AI business management software for fast food businesses | Verity
A30: catering-businesses | B30: Catering Businesses | C30: Food & Hospitality | D30: 1 | E30: =README!$B$7&"/businesses/"&A30&"/" | F30: The headcount changed on Thursday. Everything downstream of it did not. | G30: A headcount change does not propagate | H30: Which events actually make money? | I30: Owner, Operations manager, Head chef, Accounts | J30: Verity Trade | K30: M002, M004, M005, M006, M007, M012, M018, M019, M021, M030, M040, M041, M042, M043, M046, M048, M060, M080, M082, M090, M091, M092, M093, M094, M095, M123, M153 | L30: M090-M098 Food & Hospitality (Live) | M30: 0.85714286 | N30: Communication (Partial); Work (Partial) | O30: AI software for catering businesses; catering management software; event catering costing and staffing software; banquet and event operations software | P30: restaurants, event-venues, wedding-planners, hotels, cloud-kitchens, bakeries | Q30: AI business management software for catering businesses | Verity
A31: bars-and-lounges | B31: Bars & Lounges | C31: Food & Hospitality | D31: 2 | E31: =README!$B$7&"/businesses/"&A31&"/" | F31: The bottle poured thirty-one measures. It should have poured thirty-eight. | G31: Pour variance is a single stocktake figure | H31: Where is the money going? | I31: Owner, Bar manager, Bartender | J31: Verity Trade | K31: M002, M004, M005, M006, M018, M019, M021, M030, M040, M041, M043, M046, M048, M060, M080, M082, M090, M091, M092, M093, M094, M095, M123, M153 | L31: M090-M098 Food & Hospitality (Live) | M31: 0.91666667 | N31: Work (Partial) | O31: AI software for bars and lounges; bar management software; pour cost and liquor variance tracking; nightlife staffing and tab management | P31: restaurants, hotels, event-venues, cafes, resorts, catering-businesses | Q31: AI business management software for bars and lounges | Verity
A32: hotels | B32: Hotels | C32: Food & Hospitality | D32: 1 | E32: =README!$B$7&"/businesses/"&A32&"/" | F32: The guest experiences one hotel. The hotel runs as six departments that barely speak. | G32: Rooms stay out of order longer than anyone realises | H32: What is costing us rooms and guests? | I32: General manager, Front office, Housekeeping, Maintenance, Stores and purchasing | J32: Verity Trade | K32: M002, M004, M005, M006, M007, M012, M018, M019, M021, M030, M040, M041, M042, M046, M048, M060, M080, M082, M123, M153 | L32: M143 Hotel pack (Reference) | M32: 0.84615385 | N32: Communication (Partial); Work (Partial) | O32: AI software for hotels; hotel operations management software; housekeeping and maintenance tracking software; hotel departmental reporting and procurement | P32: restaurants, resorts, event-venues, catering-businesses, facility-management, travel-agencies | Q32: AI business management software for hotels | Verity
A33: resorts | B33: Resorts | C33: Food & Hospitality | D33: 2 | E33: =README!$B$7&"/businesses/"&A33&"/" | F33: The guest stays four nights and touches nine departments. | G33: The guest journey is not recorded anywhere | H33: What is the guest actually experiencing? | I33: General manager, Operations manager, Activities lead, Front office | J33: Verity Trade | K33: M002, M005, M006, M007, M012, M018, M019, M021, M030, M040, M041, M042, M046, M048, M060, M080, M082, M123, M153 | L33: M143 Hotel pack (Reference) | M33: 0.83333333 | N33: Communication (Partial); Work (Partial) | O33: AI software for resorts; resort operations management software; activity scheduling and guest journey tracking; remote supply and seasonal staffing software | P33: hotels, event-venues, tour-operators, travel-agencies, guest-houses, restaurants | Q33: AI business management software for resorts | Verity
A34: hostels | B34: Hostels | C34: Food & Hospitality | D34: 2 | E34: =README!$B$7&"/businesses/"&A34&"/" | F34: You do not sell rooms. You sell beds, one at a time, to people staying different lengths. | G34: Allocation strands bed-nights | H34: Are we selling every bed we could? | I34: Owner, Reception, Housekeeping | J34: Verity Trade | K34: M002, M004, M005, M006, M007, M018, M019, M021, M030, M040, M041, M043, M046, M048, M060, M080, M123, M153 | L34: M143 Hotel pack (Reference) | M34: 0.83333333 | N34: Communication (Partial); Work (Partial) | O34: AI software for hostels; hostel management software; bed level inventory and dorm allocation; group booking and communal facility management | P34: guest-houses, hotels, resorts, travel-agencies, tour-operators, event-venues | Q34: AI business management software for hostels | Verity
A35: guest-houses | B35: Guest Houses | C35: Food & Hospitality | D35: 2 | E35: =README!$B$7&"/businesses/"&A35&"/" | F35: Six rooms, no front desk, and a commission bill you have never added up. | G35: Commission is paid and never measured | H35: What am I paying and what is coming? | I35: Owner, Helper or caretaker | J35: Verity Trade | K35: M002, M004, M005, M006, M007, M018, M019, M021, M030, M040, M041, M043, M046, M048, M060, M080, M123, M153 | L35: M143 Hotel pack (Reference) | M35: 0.83333333 | N35: Communication (Partial); Work (Partial) | O35: AI software for guest houses; guest house management software; direct versus channel booking cost; small property arrival and supply planning | P35: hostels, hotels, resorts, travel-agencies, restaurants, property-management | Q35: AI business management software for guest houses | Verity
A36: travel-agencies | B36: Travel Agencies | C36: Food & Hospitality | D36: 2 | E36: =README!$B$7&"/businesses/"&A36&"/" | F36: Every booking is four suppliers with four cancellation deadlines you do not control. | G36: Component deadlines are held in several places | H36: What are we missing and what have we not claimed? | I36: Owner, Consultant, Operations | J36: Verity Trade | K36: M002, M004, M005, M006, M007, M012, M018, M019, M021, M030, M040, M041, M042, M043, M046, M080, M123, M153 | M36: 0.83333333 | N36: Communication (Partial); Work (Partial) | O36: AI software for travel agencies; travel agency management software; supplier deadline and deposit tracking; booking documentation and commission recovery | P36: tour-operators, hotels, resorts, event-venues, guest-houses, hostels | Q36: AI business management software for travel agencies | Verity
A37: tour-operators | B37: Tour Operators | C37: Food & Hospitality | D37: 2 | E37: =README!$B$7&"/businesses/"&A37&"/" | F37: You commit hotels and vehicles in March for a departure that may not fill by August. | G37: Viability decisions are taken late | H37: What have we committed and what have we sold? | I37: Owner, Operations, Sales and reservations | J37: Verity Trade | K37: M002, M004, M005, M006, M007, M012, M018, M019, M021, M030, M040, M041, M042, M043, M046, M080, M123, M153 | M37: 0.83333333 | N37: Communication (Partial); Work (Partial) | O37: AI software for tour operators; tour operator management software; departure viability and minimum group tracking; guide vehicle allocation and supplier commitment | P37: travel-agencies, resorts, hotels, event-venues, hostels, guest-houses | Q37: AI business management software for tour operators | Verity
A38: event-venues | B38: Event Venues | C38: Food & Hospitality | D38: 2 | E38: =README!$B$7&"/businesses/"&A38&"/" | F38: The product is a date, and there are only so many good ones. | G38: Holds block dates indefinitely | H38: Is the calendar selling? | I38: Owner, Coordinator, Operations | J38: Verity Trade | K38: M002, M004, M005, M006, M007, M018, M019, M021, M030, M040, M041, M043, M046, M048, M060, M080, M123, M153 | M38: 0.83333333 | N38: Communication (Partial); Work (Partial) | O38: AI software for event venues; event venue management software; date inventory and hold expiry tracking; venue turnaround and supplier coordination | P38: hotels, catering-businesses, wedding-planners, resorts, bars-and-lounges, photographers | Q38: AI business management software for event venues | Verity
A39: law-firms | B39: Law Firms | C39: Professional Services | D39: 1 | E39: =README!$B$7&"/businesses/"&A39&"/" | F39: A matter that has quietly consumed twice its budget looks exactly like a healthy one. | G39: Engagement health is discovered late | H39: Is the firm healthy? | I39: Managing partner, Practice head, Responsible partner, Associate, Practice manager | J39: Verity Services | K39: M002, M004, M005, M006, M007, M012, M018, M019, M021, M030, M040, M042, M080, M123, M153 | L39: M144 Legal pack (Reference) | M39: 0.81818182 | N39: Communication (Partial); Work (Partial) | O39: AI software for law firms; legal practice management software; matter management software; law firm document and deadline management; business software for lawyers | P39: accounting-firms, ca-firms, consulting-firms, architecture-firms, recruitment-agencies, it-services-companies | Q39: AI business management software for law firms | Verity
A40: accounting-firms | B40: Accounting Firms | C40: Professional Services | D40: 1 | E40: =README!$B$7&"/businesses/"&A40&"/" | F40: The work is predictable. The clients are not, and that is the whole problem. | G40: The chase for records is personal and untracked | H40: Can we deliver the calendar, and are we recovering? | I40: Partner, Manager, Associate, Practice administrator | J40: Verity Services | K40: M002, M004, M005, M006, M007, M012, M018, M019, M021, M030, M040, M042, M080, M123, M153 | M40: 0.8 | N40: Communication (Partial); Work (Partial) | O40: AI software for accounting firms; accounting practice management software; client document chasing and job tracking; bookkeeping workflow and capacity software | P40: ca-firms, consulting-firms, law-firms, financial-advisors, it-services-companies, recruitment-agencies | Q40: AI business management software for accounting firms | Verity
A41: ca-firms | B41: CA Firms | C41: Professional Services | D41: 1 | E41: =README!$B$7&"/businesses/"&A41&"/" | F41: Ninety clients, four hundred registrations, and a penalty attached to every date. | G41: Obligations are tracked per client, not per registration | H41: What is our exposure and can we cover it? | I41: Partner, Manager, Article, Administrator | J41: Verity Services | K41: M002, M004, M005, M006, M007, M012, M018, M019, M021, M030, M040, M042, M080, M123, M153 | M41: 0.8 | N41: Communication (Partial); Work (Partial) | O41: AI software for CA firms; chartered accountant practice management software; statutory compliance tracking for CA firms; audit engagement and article allocation software | P41: accounting-firms, consulting-firms, law-firms, financial-advisors, insurance-agencies, it-services-companies | Q41: AI business management software for CA firms | Verity
A42: consulting-firms | B42: Consulting Firms | C42: Professional Services | D42: 1 | E42: =README!$B$7&"/businesses/"&A42&"/" | F42: You won the work in March and staffed it with whoever was free in April. | G42: Staffing does not match what was sold | H42: Is the firm profitable and deliverable? | I42: Managing partner, Practice lead, Engagement lead, Resourcing manager, Consultant | J42: Verity Services | K42: M002, M004, M005, M006, M007, M012, M018, M019, M021, M030, M040, M042, M080, M123, M153 | M42: 0.8 | N42: Communication (Partial); Work (Partial) | O42: AI software for consulting firms; consulting firm management software; engagement staffing and utilisation software; professional services delivery and realisation tracking | P42: marketing-agencies, accounting-firms, law-firms, it-services-companies, recruitment-agencies, design-agencies | Q42: AI business management software for consulting firms | Verity
A43: marketing-agencies | B43: Marketing Agencies | C43: Professional Services | D43: 1 | E43: =README!$B$7&"/businesses/"&A43&"/" | F43: The account looks fine. It is consuming twice the delivery it pays for. | G43: Account profitability is a guess | H43: Which accounts are actually making money? | I43: Founder, Account lead, Delivery lead, Creative or strategist, Operations | J43: Verity Services | K43: M002, M004, M005, M006, M007, M012, M018, M019, M021, M030, M040, M041, M042, M046, M080, M123, M153 | M43: 0.83333333 | N43: Communication (Partial); Work (Partial) | O43: AI software for marketing agencies; agency management software; agency resource and capacity planning; client retainer and project management software; creative agency operations software | P43: advertising-agencies, design-agencies, pr-agencies, content-agencies, consulting-firms, software-agencies | Q43: AI business management software for marketing agencies | Verity
A44: advertising-agencies | B44: Advertising Agencies | C44: Professional Services | D44: 2 | E44: =README!$B$7&"/businesses/"&A44&"/" | F44: You are billing millions of somebody else’s money and earning a percentage of it. | G44: Plan, delivery and invoice do not match | H44: What is our income and where is it leaking? | I44: Managing director, Account lead, Media, Finance | J44: Verity Services | K44: M002, M004, M005, M006, M007, M012, M018, M019, M021, M030, M040, M041, M042, M043, M046, M080, M123, M153 | M44: 0.83333333 | N44: Communication (Partial); Work (Partial) | O44: AI software for advertising agencies; advertising agency management software; media commitment and billing reconciliation; production pass-through cost tracking | P44: marketing-agencies, pr-agencies, design-agencies, content-agencies, consulting-firms, saas-companies | Q44: AI business management software for advertising agencies | Verity
A45: pr-agencies | B45: PR Agencies | C45: Professional Services | D45: 2 | E45: =README!$B$7&"/businesses/"&A45&"/" | F45: The retainer buys a month. Nobody counts what the month cost. | G45: Retainer scope expands without a conversation | H45: Which accounts are profitable and which are at risk? | I45: Managing partner, Account lead, Consultant | J45: Verity Services | K45: M002, M004, M005, M006, M007, M012, M018, M019, M021, M030, M040, M041, M042, M043, M046, M080, M123, M153 | M45: 0.83333333 | N45: Communication (Partial); Work (Partial) | O45: AI software for PR agencies; public relations agency management software; retainer scope and effort tracking; media relationship and coverage record software | P45: marketing-agencies, advertising-agencies, content-agencies, design-agencies, consulting-firms, startups | Q45: AI business management software for PR agencies | Verity
A46: design-agencies | B46: Design Agencies | C46: Professional Services | D46: 2 | E46: =README!$B$7&"/businesses/"&A46&"/" | F46: The third round was free. So were the fourth and the fifth. | G46: Revision rounds exceed the allowance uncounted | H46: Where is the studio giving work away? | I46: Founder, Producer, Designer | J46: Verity Services | K46: M002, M004, M005, M006, M007, M012, M018, M019, M021, M030, M040, M041, M042, M043, M046, M080, M123, M153 | M46: 0.83333333 | N46: Communication (Partial); Work (Partial) | O46: AI software for design agencies; design studio management software; revision round and asset licensing tracking; designer capacity and project margin software | P46: marketing-agencies, content-agencies, advertising-agencies, pr-agencies, software-agencies, interior-designers | Q46: AI business management software for design agencies | Verity
A47: architecture-firms | B47: Architecture Firms | C47: Professional Services | D47: 2 | E47: =README!$B$7&"/businesses/"&A47&"/" | F47: The fee is staged. The work is not, and the gap is where practices lose money. | G47: Effort is not measured against the stage fee | H47: Which stages lose money? | I47: Partner, Project lead, Architect or technician, Practice administrator | J47: Verity Services | K47: M002, M004, M005, M006, M007, M012, M018, M019, M021, M030, M040, M041, M042, M043, M046, M080, M123, M153 | M47: 0.83333333 | N47: Communication (Partial); Work (Partial) | O47: AI software for architecture firms; architecture practice management software; work stage and fee stage tracking; drawing revision and approval management | P47: interior-designers, construction-companies, real-estate-developers, interior-design-firms, consulting-firms, contractors | Q47: AI business management software for architecture firms | Verity
A48: interior-designers | B48: Interior Designers | C48: Professional Services | D48: 2 | E48: =README!$B$7&"/businesses/"&A48&"/" | F48: The design was approved in April. The sofa arrives in September. | G48: Late confirmations cost a full lead time | H48: Are projects on programme and on margin? | I48: Principal, Project coordinator, Designer | J48: Verity Services | K48: M002, M004, M005, M006, M007, M012, M018, M019, M021, M030, M040, M041, M042, M043, M046, M080, M123, M153 | M48: 0.83333333 | N48: Communication (Partial); Work (Partial) | O48: AI software for interior designers; interior design business management software; specification and procurement tracking; lead time and site coordination software | P48: architecture-firms, interior-design-firms, furniture-stores, home-decor-stores, contractors, construction-companies | Q48: AI business management software for interior designers | Verity
A49: real-estate-agencies | B49: Real Estate Agencies | C49: Professional Services | D49: 1 | E49: =README!$B$7&"/businesses/"&A49&"/" | F49: Your pipeline is real. It is just distributed across six phones. | G49: The pipeline lives in agents’ phones | H49: What is the business going to close? | I49: Principal, Sales manager, Agent, Listings coordinator, Accounts | J49: Verity Services | K49: M002, M004, M005, M006, M007, M012, M018, M019, M021, M030, M040, M041, M042, M046, M080, M123, M153 | L49: M149 Property pack (Reference) | M49: 0.83333333 | N49: Communication (Partial); Work (Partial) | O49: AI software for real estate agencies; CRM for real estate agencies; real estate lead management software; property management software for brokers; real estate agency management system | P49: property-dealers, property-management, real-estate-developers, construction-companies, contractors, interior-designers | Q49: AI business management software for real estate agencies | Verity
A50: recruitment-agencies | B50: Recruitment Agencies | C50: Professional Services | D50: 1 | E50: =README!$B$7&"/businesses/"&A50&"/" | F50: You are not short of candidates. You are short of candidates for the four roles that will actually close. | G50: Unfillable mandates absorb the desk | H50: Where is effort going and what is it converting? | I50: Agency owner, Desk manager, Consultant, Accounts | J50: Verity Services | K50: M002, M004, M005, M006, M007, M012, M018, M019, M021, M030, M040, M042, M080, M123, M153 | M50: 0.8 | N50: Communication (Partial); Work (Partial) | O50: AI software for recruitment agencies; recruitment agency management software; candidate pipeline and submission tracking; staffing agency placement and guarantee tracking | P50: it-services-companies, consulting-firms, marketing-agencies, accounting-firms, law-firms, startups | Q50: AI business management software for recruitment agencies | Verity
A51: insurance-agencies | B51: Insurance Agencies | C51: Professional Services | D51: 2 | E51: =README!$B$7&"/businesses/"&A51&"/" | F51: A policy that lapses is a client you already had. | G51: Renewals are processed rather than worked | H51: Is the book growing or shrinking? | I51: Principal, Advisor, Claims support, Accounts | J51: Verity Services | K51: M002, M004, M005, M006, M007, M012, M018, M019, M021, M030, M040, M041, M042, M043, M046, M080, M123, M153 | M51: 0.83333333 | N51: Communication (Partial); Work (Partial) | O51: AI software for insurance agencies; insurance agency management software; policy renewal and lapse tracking; commission recovery and claims support software | P51: financial-advisors, accounting-firms, ca-firms, law-firms, real-estate-agencies, consulting-firms | Q51: AI business management software for insurance agencies | Verity
A52: financial-advisors | B52: Financial Advisors | C52: Professional Services | D52: 2 | E52: =README!$B$7&"/businesses/"&A52&"/" | F52: The review was due in March. It is September and the file says nothing. | G52: Review cycles slip while income continues | H52: Are we delivering what the income pays for? | I52: Principal, Advisor, Paraplanner, Administrator | J52: Verity Services | K52: M002, M004, M005, M006, M007, M012, M018, M019, M021, M030, M040, M041, M042, M043, M046, M080, M123, M153 | M52: 0.83333333 | N52: Communication (Partial); Work (Partial) | O52: AI software for financial advisors; financial advisory practice management software; client review cycle and suitability records; trail income reconciliation software | P52: insurance-agencies, accounting-firms, ca-firms, law-firms, consulting-firms, saas-companies | Q52: AI business management software for financial advisors | Verity
A53: it-services-companies | B53: IT Services Companies | C53: Professional Services | D53: 1 | E53: =README!$B$7&"/businesses/"&A53&"/" | F53: The contract says four hours. The engineer who knows that client is on another site. | G53: SLA breaches are reported, not predicted | H53: Which accounts are we losing money on? | I53: Services director, Service desk manager, Engineer, Account manager, Accounts | J53: Verity Services | K53: M002, M004, M005, M006, M007, M012, M018, M019, M021, M030, M040, M042, M048, M060, M080, M123, M153 | M53: 0.81818182 | N53: Communication (Partial); Work (Partial) | O53: AI software for IT services companies; managed services provider software; SLA and ticket tracking software; IT services resource allocation and contract management | P53: software-agencies, consulting-firms, saas-companies, recruitment-agencies, cybersecurity-companies, startups | Q53: AI business management software for IT services companies | Verity
A54: hospitals | B54: Hospitals | C54: Healthcare | D54: 1 | E54: =README!$B$7&"/businesses/"&A54&"/" | F54: The bed was free at eleven. It was occupied again at six. | G54: Discharge takes hours after clinical clearance | H54: Where are we losing capacity and revenue? | I54: Hospital administrator, Nursing superintendent, Theatre manager, Billing and claims, Stores and biomedical | J54: Verity Services | K54: M002, M004, M005, M006, M007, M012, M018, M019, M021, M030, M040, M042, M048, M060, M080, M082, M123, M153 | L54: M140 Clinic pack (Designed) | M54: 0.83333333 | N54: Communication (Partial); Work (Partial) | O54: AI software for hospitals; hospital operations management software; bed and theatre utilisation tracking; charge capture and claim cycle software; hospital equipment maintenance and staffing | P54: clinics, diagnostic-labs, dental-clinics, pharmacies, medical-distributors, facility-management | Q54: AI business management software for hospitals | Verity
A55: clinics | B55: Clinics | C55: Healthcare | D55: 1 | E55: =README!$B$7&"/businesses/"&A55&"/" | F55: The clinical work is the easy part to see. The practice around it is not. | G55: Follow-ups depend on someone remembering | H55: Is the practice running well and growing? | I55: Practice owner, Practice manager, Clinician, Front desk, Accounts | J55: Verity Services | K55: M002, M004, M005, M006, M007, M012, M018, M019, M021, M030, M040, M042, M048, M060, M080, M082, M123, M153 | L55: M140 Clinic pack (Designed) | M55: 0.83333333 | N55: Communication (Partial); Work (Partial) | O55: AI software for clinics; clinic management software; practice management software; multi branch clinic operations software; clinic reporting and staff rostering | P55: dental-clinics, hospitals, diagnostic-labs, pharmacies, physiotherapy-clinics, veterinary-clinics | Q55: AI business management software for clinics | Verity
A56: dental-clinics | B56: Dental Clinics | C56: Healthcare | D56: 1 | E56: =README!$B$7&"/businesses/"&A56&"/" | F56: The treatment was accepted in March. Three appointments in, it stopped. | G56: Accepted plans stall unnoticed | H56: Are we delivering the work patients accepted? | I56: Principal, Practice manager, Clinician, Reception | J56: Verity Services | K56: M002, M004, M005, M006, M007, M012, M018, M019, M021, M040, M042, M043, M048, M060, M080, M082, M123, M153 | L56: M140 Clinic pack (Designed) | M56: 0.83333333 | N56: Communication (Partial); Work (Partial) | O56: AI software for dental clinics; dental practice management software; dental lab work tracking software; treatment plan and recall management | P56: clinics, dermatology-clinics, physiotherapy-clinics, diagnostic-labs, optical-stores, hospitals | Q56: AI business management software for dental clinics | Verity
A57: dermatology-clinics | B57: Dermatology Clinics | C57: Healthcare | D57: 2 | E57: =README!$B$7&"/businesses/"&A57&"/" | F57: A vial costs more than the consultation and expires whether or not you use it. | G57: Partly used vials expire | H57: What am I about to write off and what do I owe? | I57: Practice owner, Practitioner, Clinic manager | J57: Verity Services | K57: M002, M004, M005, M006, M007, M012, M018, M019, M021, M040, M041, M042, M046, M048, M060, M080, M082, M123, M153 | L57: M140 Clinic pack (Designed) | M57: 0.83333333 | N57: Communication (Partial); Work (Partial) | O57: AI software for dermatology clinics; dermatology and aesthetics practice management; injectable batch and expiry tracking; treatment course package and documentation software | P57: clinics, salons, spas, cosmetics-stores, physiotherapy-clinics, dental-clinics | Q57: AI business management software for dermatology clinics | Verity
A58: physiotherapy-clinics | B58: Physiotherapy Clinics | C58: Healthcare | D58: 2 | E58: =README!$B$7&"/businesses/"&A58&"/" | F58: A course of eight sessions delivered as five is not a discount. It is an outcome that did not happen. | G58: Courses stop before their planned end | H58: Are courses completing? | I58: Practice owner, Therapist, Reception and administration | J58: Verity Services | K58: M002, M004, M005, M006, M007, M012, M018, M019, M021, M030, M040, M042, M043, M080, M082, M123, M153 | L58: M140 Clinic pack (Designed) | M58: 0.83333333 | N58: Communication (Partial); Work (Partial) | O58: AI software for physiotherapy clinics; physiotherapy practice management software; course of treatment and attendance tracking; insurance approval and utilisation software | P58: clinics, dermatology-clinics, mental-wellness-practices, gyms, fitness-studios, dental-clinics | Q58: AI business management software for physiotherapy clinics | Verity
A59: diagnostic-labs | B59: Diagnostic Labs | C59: Healthcare | D59: 1 | E59: =README!$B$7&"/businesses/"&A59&"/" | F59: A sample is a clock that starts when it is drawn and ends when the report is read. | G59: Turnaround is reported as an average with no causes | H59: Where are we losing turnaround and demand? | I59: Lab director, Lab manager, Pathologist, Collection supervisor, Accounts and relationships | J59: Verity Services | K59: M002, M004, M005, M006, M007, M012, M018, M019, M021, M030, M040, M042, M048, M060, M080, M123, M153 | L59: M140 Clinic pack (Designed) | M59: 0.81818182 | N59: Communication (Partial); Work (Partial) | O59: AI software for diagnostic labs; pathology lab management software; sample turnaround time tracking; reagent inventory and expiry software; referring doctor and collection centre management | P59: pharmacies, clinics, hospitals, dental-clinics, medical-distributors, physiotherapy-clinics | Q59: AI business management software for diagnostic labs | Verity
A60: pharmacies | B60: Pharmacies | C60: Healthcare | D60: 1 | E60: =README!$B$7&"/businesses/"&A60&"/" | F60: Thousands of batches, each with a date, and a return window that closes before it. | G60: Return windows close before anyone looks | H60: What am I about to lose to a date? | I60: Owner, Pharmacist in charge, Counter staff, Accounts | J60: Verity Services | K60: M002, M004, M005, M006, M007, M012, M018, M019, M021, M030, M040, M041, M042, M043, M046, M048, M060, M080 | M60: 0.91666667 | N60: Communication (Partial) | O60: AI software for pharmacies; pharmacy management software; batch expiry and returns tracking; pharmacy inventory and refill software; chemist shop billing and credit software | P60: medical-distributors, diagnostic-labs, clinics, hospitals, cosmetics-stores, grocery-stores | Q60: AI business management software for pharmacies | Verity
A61: optical-stores | B61: Optical Stores | C61: Healthcare | D61: 2 | E61: =README!$B$7&"/businesses/"&A61&"/" | F61: The frame was in stock. The lenses take nine days and the patient was told four. | G61: Collection dates are promised optimistically | H61: Where are we losing patients and margin? | I61: Owner, Dispensing staff, Reception | J61: Verity Services | K61: M002, M004, M005, M006, M007, M012, M018, M019, M021, M030, M040, M041, M042, M043, M046, M048, M060, M080 | M61: 0.91666667 | N61: Communication (Partial) | O61: AI software for optical stores; optical retail management software; lens lab order and remake tracking; eye test recall and prescription records | P61: dental-clinics, clinics, pharmacies, retail-stores, diagnostic-labs, cosmetics-stores | Q61: AI business management software for optical stores | Verity
A62: veterinary-clinics | B62: Veterinary Clinics | C62: Healthcare | D62: 2 | E62: =README!$B$7&"/businesses/"&A62&"/" | F62: Preventive care runs on a calendar. Emergencies do not, and they use the same vets. | G62: Preventive recalls go unworked | H62: Are we capturing the predictable revenue? | I62: Practice owner, Vet, Practice manager, Reception | J62: Verity Services | K62: M002, M004, M005, M006, M007, M018, M019, M021, M030, M040, M041, M046, M048, M060, M080, M082, M123, M153 | L62: M140 Clinic pack (Designed) | M62: 0.83333333 | N62: Communication (Partial); Work (Partial) | O62: AI software for veterinary clinics; veterinary practice management software; vaccination recall and preventive care tracking; in-house pharmacy stock and capacity software | P62: clinics, pet-stores, pharmacies, dental-clinics, diagnostic-labs, physiotherapy-clinics | Q62: AI business management software for veterinary clinics | Verity
A63: mental-wellness-practices | B63: Mental Wellness Practices | C63: Healthcare | D63: 2 | E63: =README!$B$7&"/businesses/"&A63&"/" | F63: A cancelled slot cannot be resold on the day, and the person who needed it is on a waitlist. | G63: Cancelled slots go unfilled beside a waitlist | H63: Is capacity meeting demand? | I63: Practice lead, Practitioner, Administration | J63: Verity Services | K63: M002, M004, M005, M006, M007, M012, M018, M019, M021, M030, M040, M042, M043, M080, M082, M123, M153 | L63: M140 Clinic pack (Designed) | M63: 0.83333333 | N63: Communication (Partial); Work (Partial) | O63: AI software for mental wellness practices; therapy practice management software; session continuity and waitlist management; practitioner capacity and confidentiality controls | P63: clinics, physiotherapy-clinics, dermatology-clinics, yoga-studios, coaching-institutes, dental-clinics | Q63: AI business management software for mental wellness practices | Verity
A64: medical-distributors | B64: Medical Distributors | C64: Healthcare | D64: 2 | E64: =README!$B$7&"/businesses/"&A64&"/" | F64: Every unit has a batch, a date and a temperature it must not have exceeded. | G64: Batch traceability is partial | H64: Where is my working capital and what is at risk? | I64: Owner, Warehouse and compliance, Sales, Accounts | J64: Verity Services | K64: M002, M004, M005, M006, M007, M018, M019, M021, M030, M040, M041, M043, M046, M048, M060, M080, M107 | M64: 0.83333333 | N64: Communication (Partial); Logistics (Partial) | O64: AI software for medical distributors; medical distribution management software; batch expiry and cold chain tracking; rate contract and institutional credit software | P64: distributors, pharmacies, hospitals, diagnostic-labs, wholesalers, industrial-suppliers | Q64: AI business management software for medical distributors | Verity
A65: schools | B65: Schools | C65: Education | D65: 1 | E65: =README!$B$7&"/businesses/"&A65&"/" | F65: The same child exists in five systems, and none of them agree. | G65: The same person exists several times | H65: Is the institution running as it should? | I65: Principal, Administrator, Accounts, Admissions, Coordinator | J65: Verity Services | K65: M002, M004, M005, M006, M007, M012, M018, M019, M021, M030, M040, M042, M080, M082, M123, M153 | L65: M148 School & Higher-ed pack (Reference) | M65: 0.83333333 | N65: Communication (Partial); Work (Partial) | O65: AI software for schools; school management software; school administration system; admissions and fee management software; school reporting and record management | P65: colleges, coaching-institutes, tuition-centres, test-preparation-centres, universities, skill-training-institutes | Q65: AI business management software for schools | Verity
A66: colleges | B66: Colleges | C66: Education | D66: 1 | E66: =README!$B$7&"/businesses/"&A66&"/" | F66: The accreditation data exists. It just takes three months to assemble. | G66: Accreditation data takes months to assemble | H66: Is the institution running and reportable? | I66: Principal or director, Head of department, Administrator, Accounts, Placement cell | J66: Verity Services | K66: M002, M004, M005, M006, M007, M012, M018, M019, M021, M030, M040, M042, M080, M082, M123, M153 | L66: M148 School & Higher-ed pack (Reference) | M66: 0.81818182 | N66: Communication (Partial); Work (Partial) | O66: AI software for colleges; college administration software; faculty workload and course registration system; accreditation reporting and placement tracking | P66: schools, universities, coaching-institutes, test-preparation-centres, skill-training-institutes, vocational-training-centres | Q66: AI business management software for colleges | Verity
A67: universities | B67: Universities | C67: Education | D67: 2 | E67: =README!$B$7&"/businesses/"&A67&"/" | F67: The grant has conditions, a spending profile and a report date, and it lives in a folder. | G67: Grant conditions live with the investigator | H67: Are our obligations being met? | I67: Vice-chancellor or registrar, Dean or head of department, Principal investigator, Research office, Administration | J67: Verity Services | K67: M002, M004, M005, M006, M007, M012, M018, M019, M021, M030, M040, M042, M043, M080, M082, M123, M153 | L67: M148 School & Higher-ed pack (Reference) | M67: 0.83333333 | N67: Communication (Partial); Work (Partial) | O67: AI software for universities; university administration software; research grant administration and compliance; faculty workload and accreditation reporting | P67: colleges, schools, edtech-companies, skill-training-institutes, vocational-training-centres, consulting-firms | Q67: AI business management software for universities | Verity
A68: coaching-institutes | B68: Coaching Institutes | C68: Education | D68: 1 | E68: =README!$B$7&"/businesses/"&A68&"/" | F68: A batch of eleven costs the same to run as a batch of forty. | G68: Batch viability is never calculated | H68: Which batches make money? | I68: Director, Centre head, Counsellor, Accounts | J68: Verity Services | K68: M002, M004, M005, M006, M007, M012, M018, M019, M021, M030, M040, M042, M080, M123, M153 | L68: M142 Coaching pack (Designed) | M68: 0.8 | N68: Communication (Partial); Work (Partial) | O68: AI software for coaching institutes; coaching institute management software; batch and faculty scheduling software; student enrolment and fee instalment tracking | P68: test-preparation-centres, tuition-centres, schools, colleges, skill-training-institutes, language-institutes | Q68: AI business management software for coaching institutes | Verity
A69: tuition-centres | B69: Tuition Centres | C69: Education | D69: 1 | E69: =README!$B$7&"/businesses/"&A69&"/" | F69: A missed session is a promise you still owe and an hour you cannot resell. | G69: Make-up sessions accumulate untracked | H69: What do we owe and what are we wasting? | I69: Owner, Coordinator, Tutor | J69: Verity Services | K69: M002, M004, M005, M006, M007, M012, M018, M019, M021, M030, M040, M042, M080, M123, M153 | L69: M142 Coaching pack (Designed) | M69: 0.8 | N69: Communication (Partial); Work (Partial) | O69: AI software for tuition centres; tuition centre management software; tutor scheduling and session tracking; per student tuition fee and attendance software | P69: coaching-institutes, test-preparation-centres, schools, music-schools, language-institutes, dance-academies | Q69: AI business management software for tuition centres | Verity
A70: test-preparation-centres | B70: Test Preparation Centres | C70: Education | D70: 1 | E70: =README!$B$7&"/businesses/"&A70&"/" | F70: You market last year’s results and manage this year’s cohort blind. | G70: Declining students are found too late | H70: Is this cohort tracking towards outcomes? | I70: Director, Academic head, Test series coordinator, Counsellor | J70: Verity Services | K70: M002, M004, M005, M006, M007, M012, M018, M019, M021, M030, M040, M042, M080, M123, M153 | L70: M142 Coaching pack (Designed) | M70: 0.8 | N70: Communication (Partial); Work (Partial) | O70: AI software for test preparation centres; test series operations software; cohort performance and student progression tracking; scholarship and fee structure management | P70: coaching-institutes, tuition-centres, schools, colleges, skill-training-institutes, edtech-companies | Q70: AI business management software for test preparation centres | Verity
A71: edtech-companies | B71: EdTech Companies | C71: Education | D71: 2 | E71: =README!$B$7&"/businesses/"&A71&"/" | F71: Enrolment is the number you report. Completion is the number that renews. | G71: Completion varies enormously and is not attributed | H71: Which courses actually work? | I71: Founder, Content lead, Learning or success lead, Support lead | J71: Verity Services | K71: M002, M004, M005, M006, M007, M012, M018, M019, M021, M030, M040, M041, M042, M043, M046, M080, M123, M153 | M71: 0.83333333 | N71: Communication (Partial); Work (Partial) | O71: AI software for edtech companies; edtech operations management software; content production and learner completion tracking; cohort economics and institutional contract software | P71: saas-companies, skill-training-institutes, universities, content-agencies, coaching-institutes, language-institutes | Q71: AI business management software for EdTech companies | Verity
A72: language-institutes | B72: Language Institutes | C72: Education | D72: 2 | E72: =README!$B$7&"/businesses/"&A72&"/" | F72: A class only forms if enough students reach the same level at the same time. | G72: Learners complete a level and disappear | H72: Are learners progressing and classes forming? | I72: Director, Academic coordinator, Teacher, Administration | J72: Verity Services | K72: M002, M004, M005, M006, M007, M012, M018, M019, M021, M030, M040, M042, M043, M080, M082, M123, M153 | L72: M142 Coaching pack (Designed) | M72: 0.83333333 | N72: Communication (Partial); Work (Partial) | O72: AI software for language institutes; language school management software; level based class formation and progression; certification exam and corporate contract tracking | P72: coaching-institutes, skill-training-institutes, music-schools, tuition-centres, edtech-companies, schools | Q72: AI business management software for language institutes | Verity
A73: skill-training-institutes | B73: Skill Training Institutes | C73: Education | D73: 2 | E73: =README!$B$7&"/businesses/"&A73&"/" | F73: You are selling a job, and the placement rate is the only thing that proves it. | G73: Placement outcomes are claimed rather than evidenced | H73: Is the placement outcome real and holding? | I73: Director, Placement officer, Trainer, Compliance | J73: Verity Services | K73: M002, M004, M005, M006, M007, M012, M018, M019, M021, M030, M040, M042, M043, M048, M060, M080, M123, M153 | L73: M142 Coaching pack (Designed) | M73: 0.83333333 | N73: Communication (Partial); Work (Partial) | O73: AI software for skill training institutes; skill development institute management software; placement outcome and employer relationship tracking; batch capacity and certification compliance software | P73: vocational-training-centres, coaching-institutes, recruitment-agencies, colleges, edtech-companies, language-institutes | Q73: AI business management software for skill training institutes | Verity
A74: music-schools | B74: Music Schools | C74: Education | D74: 2 | E74: =README!$B$7&"/businesses/"&A74&"/" | F74: A student who misses the grade exam window waits another six months. | G74: Examination windows close on unready students | H74: Are we delivering and progressing students? | I74: Principal, Teacher, Administration | J74: Verity Services | K74: M002, M005, M006, M007, M012, M018, M019, M021, M030, M040, M042, M043, M048, M060, M080, M082, M123, M153 | L74: M142 Coaching pack (Designed) | M74: 0.83333333 | N74: Communication (Partial); Work (Partial) | O74: AI software for music schools; music school management software; lesson scheduling and teacher allocation; grade exam pathway and instrument hire tracking | P74: dance-academies, tuition-centres, coaching-institutes, language-institutes, schools, skill-training-institutes | Q74: AI business management software for music schools | Verity
A75: dance-academies | B75: Dance Academies | C75: Education | D75: 2 | E75: =README!$B$7&"/businesses/"&A75&"/" | F75: The showcase is the year. It is also the largest unbudgeted project in the academy. | G75: Showcase cost is committed without a budget | H75: Is the year funding itself? | I75: Principal, Teacher, Coordinator | J75: Verity Services | K75: M002, M004, M005, M006, M007, M012, M018, M019, M021, M030, M040, M042, M048, M060, M080, M082, M123, M153 | L75: M142 Coaching pack (Designed) | M75: 0.83333333 | N75: Communication (Partial); Work (Partial) | O75: AI software for dance academies; dance studio management software; batch class and studio utilisation tracking; showcase production and costume management | P75: music-schools, yoga-studios, fitness-studios, tuition-centres, coaching-institutes, event-venues | Q75: AI business management software for dance academies | Verity
A76: vocational-training-centres | B76: Vocational Training Centres | C76: Education | D76: 2 | E76: =README!$B$7&"/businesses/"&A76&"/" | F76: A trade is taught on equipment, and the equipment decides how many you can teach. | G76: Intake mix does not match workshop capacity | H76: Is capacity matched to intake? | I76: Centre head, Workshop supervisor, Assessor, Compliance | J76: Verity Services | K76: M002, M004, M005, M006, M007, M012, M018, M019, M021, M030, M040, M042, M048, M060, M080, M123, M153 | L76: M142 Coaching pack (Designed) | M76: 0.81818182 | N76: Communication (Partial); Work (Partial) | O76: AI software for vocational training centres; vocational training centre management software; practical assessment and workshop management; trade training equipment and consumables software | P76: skill-training-institutes, coaching-institutes, colleges, manufacturers, contractors, universities | Q76: AI business software for vocational training centres | Verity
A77: real-estate-developers | B77: Real Estate Developers | C77: Real Estate & Construction | D77: 1 | E77: =README!$B$7&"/businesses/"&A77&"/" | F77: The milestone was achieved in March. The demand went out in June. | G77: Demands lag milestone achievement | H77: What have we earned and what have we collected? | I77: Promoter, CRM head, Sales head, Project head, Handover team | J77: Verity Services | K77: M002, M004, M005, M006, M007, M012, M018, M019, M021, M030, M040, M041, M042, M043, M046, M080, M123, M153 | L77: M149 Property pack (Reference) | M77: 0.83333333 | N77: Communication (Partial); Work (Partial) | O77: AI software for real estate developers; real estate development management software; construction linked payment and demand tracking; project unit inventory and booking software | P77: construction-companies, property-dealers, real-estate-agencies, property-management, contractors, architects | Q77: AI business management software for real estate developers | Verity
A78: property-dealers | B78: Property Dealers | C78: Real Estate & Construction | D78: 1 | E78: =README!$B$7&"/businesses/"&A78&"/" | F78: Between the token and the registry, a deal has ten ways to die. | G78: Document problems surface after the token | H78: What will actually register? | I78: Principal, Dealer, Documentation | J78: Verity Services | K78: M002, M004, M005, M006, M007, M012, M018, M019, M021, M030, M040, M042, M080, M123, M153 | L78: M149 Property pack (Reference) | M78: 0.8 | N78: Communication (Partial); Work (Partial) | O78: AI software for property dealers; property dealer management software; resale listing and buyer matching software; token agreement and commission tracking | P78: real-estate-agencies, property-management, real-estate-developers, construction-companies, financial-advisors, interior-designers | Q78: AI business management software for property dealers | Verity
A79: property-management | B79: Property Management | C79: Real Estate & Construction | D79: 1 | E79: =README!$B$7&"/businesses/"&A79&"/" | F79: A lease that lapses without notice costs more than a month of rent. | G79: Renewals lapse while notice periods run | H79: Is the portfolio occupied and collecting? | I79: Business owner, Property manager, Maintenance coordinator, Accounts | J79: Verity Services | K79: M002, M004, M005, M006, M007, M012, M018, M019, M021, M030, M040, M041, M042, M046, M080, M123, M153 | L79: M149 Property pack (Reference) | M79: 0.81818182 | N79: Communication (Partial); Work (Partial) | O79: AI software for property management; property management software; lease renewal and rent collection tracking; maintenance request and vendor management software | P79: real-estate-agencies, property-dealers, facility-management, real-estate-developers, construction-companies, hotels | Q79: AI business management software for property management | Verity
A80: construction-companies | B80: Construction Companies | C80: Real Estate & Construction | D80: 1 | E80: =README!$B$7&"/businesses/"&A80&"/" | F80: The project was profitable at tender and is not now, and the difference happened in fifty small pieces. | G80: Variations are executed without instruction | H80: Are the projects still profitable? | I80: Managing director, Commercial manager, Project manager, Site engineer, Procurement | J80: Verity Services | K80: M002, M004, M005, M006, M007, M012, M018, M019, M021, M030, M041, M042, M046, M048, M060, M080, M123, M153 | L80: M145 Construction pack (Planned) | M80: 0.81818182 | N80: Communication (Partial); Work (Partial) | O80: AI software for construction companies; construction project management software; BOQ and progress billing tracking; subcontractor and material at site management | P80: contractors, real-estate-developers, building-material-suppliers, architects, property-management, manufacturers | Q80: AI business management software for construction companies | Verity
A81: contractors | B81: Contractors | C81: Real Estate & Construction | D81: 1 | E81: =README!$B$7&"/businesses/"&A81&"/" | F81: Four sites, one set of people, and a running bill you have not raised on any of them. | G81: Running bills are raised late | H81: Which jobs are making money and where is my cash? | I81: Owner, Site supervisor, Whoever bills | J81: Verity Services | K81: M002, M004, M005, M006, M007, M018, M019, M021, M030, M040, M041, M046, M048, M060, M080, M123, M153 | L81: M145 Construction pack (Planned) | M81: 0.81818182 | N81: Communication (Partial); Work (Partial) | O81: AI software for contractors; contractor management software; running bill and retention tracking; labour gang and material advance management | P81: construction-companies, real-estate-developers, interior-designers, building-material-suppliers, repair-services, facility-management | Q81: AI business management software for contractors | Verity
A82: architects | B82: Architects | C82: Real Estate & Construction | D82: 3 | E82: =README!$B$7&"/businesses/"&A82&"/" | F82: Every drawing that leaves needs your name on it, and there is one of you. | G82: Everything queues behind one reviewer | H82: What needs me, and what is waiting on someone else? | I82: Architect, Project assistant, Draughtsperson, Practice administration | J82: Verity Services | K82: M002, M004, M005, M006, M007, M012, M018, M019, M021, M030, M040, M042, M043, M080, M123, M153 | M82: 0.81818182 | N82: Communication (Partial); Work (Partial) | O82: AI software for architects; architect practice management software; drawing issue and revision tracking; architect project and submission software | P82: architecture-firms, interior-design-firms, home-builders, construction-companies, contractors, real-estate-developers | Q82: AI business management software for architects | Verity
A83: interior-design-firms | B83: Interior Design Firms | C83: Real Estate & Construction | D83: 3 | E83: =README!$B$7&"/businesses/"&A83&"/" | F83: The design hours are billed. The hours spent finding the tile are not. | G83: Sourcing hours are invisible in the fee | H83: Which projects are paying? | I83: Principal, Design lead, Designer, Procurement coordinator | J83: Verity Services | K83: M002, M004, M005, M006, M007, M012, M018, M019, M021, M030, M040, M042, M043, M080, M123, M153 | M83: 0.81818182 | N83: Communication (Partial); Work (Partial) | O83: AI software for interior design firms; interior design studio management software; design studio utilisation and profitability; interior design project resourcing software | P83: interior-designers, architects, architecture-firms, home-builders, design-agencies, furniture-manufacturers | Q83: AI business management software for interior design firms | Verity
A84: home-builders | B84: Home Builders | C84: Real Estate & Construction | D84: 3 | E84: =README!$B$7&"/businesses/"&A84&"/" | F84: The buyer changed the kitchen, and nobody told the electrician. | G84: Work starts on unpriced changes | H84: Which homes are making money? | I84: Owner, Site supervisor, Buyer liaison, Commercial | J84: Verity Services | K84: M002, M004, M005, M006, M007, M012, M018, M019, M021, M030, M040, M042, M043, M048, M060, M080, M123, M153 | L84: M145 Construction pack (Planned) | M84: 0.83333333 | N84: Communication (Partial); Work (Partial) | O84: AI software for home builders; home builder management software; per-home cost and change order tracking; residential construction scheduling software | P84: construction-companies, contractors, architects, interior-design-firms, real-estate-developers, building-material-suppliers | Q84: AI business management software for home builders | Verity
A85: facility-management | B85: Facility Management | C85: Real Estate & Construction | D85: 3 | E85: =README!$B$7&"/businesses/"&A85&"/" | F85: The contract is written in response times, and nobody is counting them until the review. | G85: Service level performance is known too late | H85: Which contracts are healthy? | I85: Managing director, Operations manager, Technician, Account manager | J85: Verity Services | K85: M002, M004, M005, M006, M007, M012, M018, M019, M021, M030, M040, M042, M043, M048, M060, M080, M123, M153 | M85: 0.83333333 | N85: Communication (Partial); Work (Partial) | O85: AI software for facility management companies; facility management software; service level and response time tracking; planned preventive maintenance software | P85: property-management, cleaning-services, repair-services, construction-companies, contractors, building-material-suppliers | Q85: AI business software for facility management | Verity
A86: building-material-suppliers | B86: Building Material Suppliers | C86: Real Estate & Construction | D86: 3 | E86: =README!$B$7&"/businesses/"&A86&"/" | F86: The load is worth less than the credit you extended to receive it back. | G86: Vehicles run under-loaded and unconsolidated | H86: Where is the money and the margin? | I86: Owner, Dispatch in-charge, Sales, Accounts | J86: Verity Services | K86: M002, M004, M007, M018, M019, M021, M030, M040, M041, M043, M046, M048, M060, M080, M107 | L86: M053 pattern: Trading + vertical pack (Live for plywood) | M86: 0.81818182 | N86: Communication (Partial); Logistics (Partial) | O86: AI software for building material suppliers; building material supplier software; site delivery and load planning software; contractor credit exposure management | P86: distributors, wholesalers, hardware-stores, construction-companies, contractors, home-builders | Q86: AI business software for building material suppliers | Verity
A87: manufacturers | B87: Manufacturers | C87: Manufacturing & B2B | D87: 1 | E87: =README!$B$7&"/businesses/"&A87&"/" | F87: The order is late. The reason is four steps upstream. | G87: Late orders have untraceable causes | H87: What is going to be late, and why? | I87: Plant head, Production supervisor, Quality, Purchasing, Dispatch | J87: Verity Production | K87: M002, M004, M005, M006, M007, M012, M018, M019, M021, M030, M040, M041, M042, M043, M046, M048, M060, M080, M082, M107, M123, M153 | M87: 0.8125 | N87: Communication (Partial); Logistics (Partial); Work (Partial) | O87: AI software for manufacturers; manufacturing management software; production planning and inventory software; ERP alternative for manufacturers; quality and dispatch tracking software | P87: textile-manufacturers, garment-manufacturers, distributors, wholesalers, construction-companies, contractors | Q87: AI business management software for manufacturers | Verity
A88: textile-manufacturers | B88: Textile Manufacturers | C88: Manufacturing & B2B | D88: 1 | E88: =README!$B$7&"/businesses/"&A88&"/" | F88: The shade matched in the lab and did not match across the lot. | G88: Material at job workers is untracked | H88: How much material is outside and is it coming back? | I88: Owner, Production head, Quality, Purchase and processing, Sales | J88: Verity Production | K88: M002, M004, M005, M006, M012, M018, M019, M021, M030, M041, M042, M043, M046, M048, M060, M080, M082, M123, M153 | M88: 0.91666667 | N88: Work (Partial) | O88: AI software for textile manufacturers; textile mill management software; dye lot and shade matching tracking; job work and greige inventory software | P88: garment-manufacturers, manufacturers, wholesalers, distributors, fashion-stores, packaging-companies | Q88: AI business management software for textile manufacturers | Verity
A89: garment-manufacturers | B89: Garment Manufacturers | C89: Manufacturing & B2B | D89: 1 | E89: =README!$B$7&"/businesses/"&A89&"/" | F89: The shipment date is fixed. Everything upstream of it is not. | G89: Approvals compress the production window | H89: Which shipments will slip and what will it cost? | I89: Owner, Merchandiser, Production manager, Cutting and stores, Quality | J89: Verity Production | K89: M002, M004, M005, M006, M007, M012, M018, M019, M021, M030, M041, M042, M043, M046, M048, M060, M080, M123, M153 | M89: 0.83333333 | N89: Communication (Partial); Work (Partial) | O89: AI software for garment manufacturers; apparel manufacturing management software; cut make trim and line output tracking; buyer order and shipment deadline software | P89: textile-manufacturers, manufacturers, fashion-stores, clothing-boutiques, exporters, packaging-companies | Q89: AI business management software for garment manufacturers | Verity
A90: furniture-manufacturers | B90: Furniture Manufacturers | C90: Manufacturing & B2B | D90: 3 | E90: =README!$B$7&"/businesses/"&A90&"/" | F90: Same sofa, eleven fabrics, three timbers, two arm styles. It is not the same sofa. | G90: The configuration is lost between order and shop floor | H90: Where is value stuck? | I90: Owner, Production manager, Stores, Dispatch | J90: Verity Production | K90: M002, M004, M005, M006, M012, M018, M019, M021, M030, M040, M041, M042, M043, M046, M048, M060, M080, M107, M123, M153 | M90: 0.84615385 | N90: Logistics (Partial); Work (Partial) | O90: AI software for furniture manufacturers; furniture manufacturing management software; made to order furniture production software; furniture finished goods and dispatch software | P90: manufacturers, furniture-stores, interior-design-firms, industrial-suppliers, wholesalers, packaging-companies | Q90: AI business management software for furniture manufacturers | Verity
A91: chemical-manufacturers | B91: Chemical Manufacturers | C91: Manufacturing & B2B | D91: 3 | E91: =README!$B$7&"/businesses/"&A91&"/" | F91: The formula says 94%. The reactor gave 87%, and nobody can say which input caused it. | G91: Yield variance has no attributable cause | H91: Where is yield going? | I91: Managing director, Production manager, Quality, Safety and compliance | J91: Verity Manufacturing Plus | K91: M002, M004, M005, M006, M012, M018, M019, M021, M030, M041, M042, M043, M046, M048, M060, M080, M107, M123, M153 | M91: 0.83333333 | N91: Logistics (Partial); Work (Partial) | O91: AI software for chemical manufacturers; chemical manufacturing management software; batch yield and reconciliation software; hazardous material storage and compliance software | P91: manufacturers, pharmaceutical-manufacturers, food-manufacturers, industrial-suppliers, packaging-companies, exporters | Q91: AI business management software for chemical manufacturers | Verity
